Workbook

Sheet Dashboard
A1: Dashboard – Test Progress by Module (Cycle 1)
A3: Module | B3: QA Owner | C3: Test Scenario | D3: Executed | E3: Testing | F3: Not Start | G3: In progress | H3: Passed | I3: Failed | J3: Blocked | K3: Cancelled | L3: TC Total | M3: Pass Rate
A4: EC – Employee Central | B4: Petcharut | C4: =SUM(C5:C7) -> 272 | D4: =H4+I4+J4 -> 17 | E4: =COUNTIF(EC!$M$2:$M$100000,"Ready to test")+COUNTIF(EC!$M$2:$M$100000,"Pending confirm")+COUNTIF(EC!$M$2:$M$100000,"Testing")+COUNTIF(EC!$M$2:$M$100000,"Re-Testing")+COUNTIF(EC!$M$2:$M$100000,"In progress") -> 3 | F4: =L4-G4-H4-I4-J4 -> 157 | G4: =COUNTIF(EC!$M$2:$M$100000,"Pending confirm")+COUNTIF(EC!$M$2:$M$100000,"Testing")+COUNTIF(EC!$M$2:$M$100000,"Re-Testing")+COUNTIF(EC!$M$2:$M$100000,"In progress") -> 3 | H4: =COUNTIF(EC!$M$2:$M$100000,"Passed")+COUNTIF(EC!$M$2:$M$100000,"Re-Test Passed")+COUNTIF(EC!$M$2:$M$100000,"Pass") -> 8 | I4: =COUNTIF(EC!$M$2:$M$100000,"Failed")+COUNTIF(EC!$M$2:$M$100000,"Re-Test Failed") -> 7 | J4: =COUNTIF(EC!$M$2:$M$100000,"Blocked") -> 2 | K4: =COUNTIF(EC!$M$2:$M$100000,"Cancel")+COUNTIF(EC!$M$2:$M$100000,"Cancelled") -> 95 | L4: =COUNTIFS(EC!$C$2:$C$100000,"<>",EC!$M$2:$M$100000,"<>Cancel",EC!$M$2:$M$100000,"<>Cancelled") -> 177 | M4: =IFERROR(H4/L4,"") -> 0.04519774
A5: Hiring | C5: =COUNTIFS(EC!$B$2:$B$100000,"Hiring",EC!$C$2:$C$100000,"<>") -> 150 | D5: =H5+I5+J5 -> 9 | E5: =COUNTIFS(EC!$B$2:$B$100000,"Hiring",EC!$M$2:$M$100000,"Ready to test")+COUNTIFS(EC!$B$2:$B$100000,"Hiring",EC!$M$2:$M$100000,"Pending confirm")+COUNTIFS(EC!$B$2:$B$100000,"Hiring",EC!$M$2:$M$100000,"Testing")+COUNTIFS(EC!$B$2:$B$100000,"Hiring",EC!$M$2:$M$100000,"Re-Testing")+COUNTIFS(EC!$B$2:$B$100000,"Hiring",EC!$M$2:$M$100000,"In progress") -> 1 | F5: =L5-G5-H5-I5-J5 -> 65 | G5: =COUNTIFS(EC!$B$2:$B$100000,"Hiring",EC!$M$2:$M$100000,"Pending confirm")+COUNTIFS(EC!$B$2:$B$100000,"Hiring",EC!$M$2:$M$100000,"Testing")+COUNTIFS(EC!$B$2:$B$100000,"Hiring",EC!$M$2:$M$100000,"Re-Testing")+COUNTIFS(EC!$B$2:$B$100000,"Hiring",EC!$M$2:$M$100000,"In progress") -> 1 | H5: =COUNTIFS(EC!$B$2:$B$100000,"Hiring",EC!$M$2:$M$100000,"Passed")+COUNTIFS(EC!$B$2:$B$100000,"Hiring",EC!$M$2:$M$100000,"Re-Test Passed")+COUNTIFS(EC!$B$2:$B$100000,"Hiring",EC!$M$2:$M$100000,"Pass") -> 1 | I5: =COUNTIFS(EC!$B$2:$B$100000,"Hiring",EC!$M$2:$M$100000,"Failed")+COUNTIFS(EC!$B$2:$B$100000,"Hiring",EC!$M$2:$M$100000,"Re-Test Failed") -> 6 | J5: =COUNTIFS(EC!$B$2:$B$100000,"Hiring",EC!$M$2:$M$100000,"Blocked") -> 2 | K5: =COUNTIFS(EC!$B$2:$B$100000,"Hiring",EC!$M$2:$M$100000,"Cancel")+COUNTIFS(EC!$B$2:$B$100000,"Hiring",EC!$M$2:$M$100000,"Cancelled") -> 75 | L5: =COUNTIFS(EC!$B$2:$B$100000,"Hiring",EC!$C$2:$C$100000,"<>",EC!$M$2:$M$100000,"<>Cancel",EC!$M$2:$M$100000,"<>Cancelled") -> 75 | M5: =IFERROR(H5/L5,"") -> 0.013333333
A6: Probation | C6: =COUNTIFS(EC!$B$2:$B$100000,"Probation",EC!$C$2:$C$100000,"<>") -> 88 | D6: =H6+I6+J6 -> 0 | E6: =COUNTIFS(EC!$B$2:$B$100000,"Probation",EC!$M$2:$M$100000,"Ready to test")+COUNTIFS(EC!$B$2:$B$100000,"Probation",EC!$M$2:$M$100000,"Pending confirm")+COUNTIFS(EC!$B$2:$B$100000,"Probation",EC!$M$2:$M$100000,"Testing")+COUNTIFS(EC!$B$2:$B$100000,"Probation",EC!$M$2:$M$100000,"Re-Testing")+COUNTIFS(EC!$B$2:$B$100000,"Probation",EC!$M$2:$M$100000,"In progress") -> 0 | F6: =L6-G6-H6-I6-J6 -> 88 | G6: =COUNTIFS(EC!$B$2:$B$100000,"Probation",EC!$M$2:$M$100000,"Pending confirm")+COUNTIFS(EC!$B$2:$B$100000,"Probation",EC!$M$2:$M$100000,"Testing")+COUNTIFS(EC!$B$2:$B$100000,"Probation",EC!$M$2:$M$100000,"Re-Testing")+COUNTIFS(EC!$B$2:$B$100000,"Probation",EC!$M$2:$M$100000,"In progress") -> 0 | H6: =COUNTIFS(EC!$B$2:$B$100000,"Probation",EC!$M$2:$M$100000,"Passed")+COUNTIFS(EC!$B$2:$B$100000,"Probation",EC!$M$2:$M$100000,"Re-Test Passed")+COUNTIFS(EC!$B$2:$B$100000,"Probation",EC!$M$2:$M$100000,"Pass") -> 0 | I6: =COUNTIFS(EC!$B$2:$B$100000,"Probation",EC!$M$2:$M$100000,"Failed")+COUNTIFS(EC!$B$2:$B$100000,"Probation",EC!$M$2:$M$100000,"Re-Test Failed") -> 0 | J6: =COUNTIFS(EC!$B$2:$B$100000,"Probation",EC!$M$2:$M$100000,"Blocked") -> 0 | K6: =COUNTIFS(EC!$B$2:$B$100000,"Probation",EC!$M$2:$M$100000,"Cancel")+COUNTIFS(EC!$B$2:$B$100000,"Probation",EC!$M$2:$M$100000,"Cancelled") -> 0 | L6: =COUNTIFS(EC!$B$2:$B$100000,"Probation",EC!$C$2:$C$100000,"<>",EC!$M$2:$M$100000,"<>Cancel",EC!$M$2:$M$100000,"<>Cancelled") -> 88 | M6: =IFERROR(H6/L6,"") -> 0
A7: Consent | C7: =COUNTIFS(EC!$B$2:$B$100000,"Consent",EC!$C$2:$C$100000,"<>") -> 34 | D7: =H7+I7+J7 -> 8 | E7: =COUNTIFS(EC!$B$2:$B$100000,"Consent",EC!$M$2:$M$100000,"Ready to test")+COUNTIFS(EC!$B$2:$B$100000,"Consent",EC!$M$2:$M$100000,"Pending confirm")+COUNTIFS(EC!$B$2:$B$100000,"Consent",EC!$M$2:$M$100000,"Testing")+COUNTIFS(EC!$B$2:$B$100000,"Consent",EC!$M$2:$M$100000,"Re-Testing")+COUNTIFS(EC!$B$2:$B$100000,"Consent",EC!$M$2:$M$100000,"In progress") -> 2 | F7: =L7-G7-H7-I7-J7 -> 4 | G7: =COUNTIFS(EC!$B$2:$B$100000,"Consent",EC!$M$2:$M$100000,"Pending confirm")+COUNTIFS(EC!$B$2:$B$100000,"Consent",EC!$M$2:$M$100000,"Testing")+COUNTIFS(EC!$B$2:$B$100000,"Consent",EC!$M$2:$M$100000,"Re-Testing")+COUNTIFS(EC!$B$2:$B$100000,"Consent",EC!$M$2:$M$100000,"In progress") -> 2 | H7: =COUNTIFS(EC!$B$2:$B$100000,"Consent",EC!$M$2:$M$100000,"Passed")+COUNTIFS(EC!$B$2:$B$100000,"Consent",EC!$M$2:$M$100000,"Re-Test Passed")+COUNTIFS(EC!$B$2:$B$100000,"Consent",EC!$M$2:$M$100000,"Pass") -> 7 | I7: =COUNTIFS(EC!$B$2:$B$100000,"Consent",EC!$M$2:$M$100000,"Failed")+COUNTIFS(EC!$B$2:$B$100000,"Consent",EC!$M$2:$M$100000,"Re-Test Failed") -> 1 | J7: =COUNTIFS(EC!$B$2:$B$100000,"Consent",EC!$M$2:$M$100000,"Blocked") -> 0 | K7: =COUNTIFS(EC!$B$2:$B$100000,"Consent",EC!$M$2:$M$100000,"Cancel")+COUNTIFS(EC!$B$2:$B$100000,"Consent",EC!$M$2:$M$100000,"Cancelled") -> 20 | L7: =COUNTIFS(EC!$B$2:$B$100000,"Consent",EC!$C$2:$C$100000,"<>",EC!$M$2:$M$100000,"<>Cancel",EC!$M$2:$M$100000,"<>Cancelled") -> 14 | M7: =IFERROR(H7/L7,"") -> 0.5
A8: BE – Benefits | B8: Chutiman | C8: =SUM(C9:C10) -> 431 | D8: =H8+I8+J8 -> 195 | E8: =COUNTIF(BE!$M$2:$M$99997,"Ready to test")+COUNTIF(BE!$M$2:$M$99997,"Pending confirm")+COUNTIF(BE!$M$2:$M$99997,"Testing")+COUNTIF(BE!$M$2:$M$99997,"Re-Testing")+COUNTIF(BE!$M$2:$M$99997,"In progress") -> 232 | F8: =L8-G8-H8-I8-J8 -> 232 | G8: =COUNTIF(BE!$M$2:$M$99997,"Pending confirm")+COUNTIF(BE!$M$2:$M$99997,"Testing")+COUNTIF(BE!$M$2:$M$99997,"Re-Testing")+COUNTIF(BE!$M$2:$M$99997,"In progress") -> 4 | H8: =COUNTIF(BE!$M$2:$M$99997,"Passed")+COUNTIF(BE!$M$2:$M$99997,"Re-Test Passed")+COUNTIF(BE!$M$2:$M$99997,"Pass") -> 149 | I8: =COUNTIF(BE!$M$2:$M$99997,"Failed")+COUNTIF(BE!$M$2:$M$99997,"Re-Test Failed") -> 40 | J8: =COUNTIF(BE!$M$2:$M$99997,"Blocked") -> 6 | K8: =COUNTIF(BE!$M$2:$M$99997,"Cancel")+COUNTIF(BE!$M$2:$M$99997,"Cancelled") -> 0 | L8: =COUNTIFS(BE!$D$2:$D$99997,"<>",BE!$M$2:$M$99997,"<>Cancel",BE!$M$2:$M$99997,"<>Cancelled") -> 431 | M8: =IFERROR(H8/L8,"") -> 0.34570766
A9: Benefit Plan | C9: =COUNTIFS(BE!$B$2:$B$99997,"Benefit Plan",BE!$D$2:$D$99997,"<>") -> 222 | D9: =H9+I9+J9 -> 195 | E9: =COUNTIFS(BE!$B$2:$B$99997,"Benefit Plan",BE!$M$2:$M$99997,"Ready to test")+COUNTIFS(BE!$B$2:$B$99997,"Benefit Plan",BE!$M$2:$M$99997,"Pending confirm")+COUNTIFS(BE!$B$2:$B$99997,"Benefit Plan",BE!$M$2:$M$99997,"Testing")+COUNTIFS(BE!$B$2:$B$99997,"Benefit Plan",BE!$M$2:$M$99997,"Re-Testing")+COUNTIFS(BE!$B$2:$B$99997,"Benefit Plan",BE!$M$2:$M$99997,"In progress") -> 23 | F9: =L9-G9-H9-I9-J9 -> 23 | G9: =COUNTIFS(BE!$B$2:$B$99997,"Benefit Plan",BE!$M$2:$M$99997,"Pending confirm")+COUNTIFS(BE!$B$2:$B$99997,"Benefit Plan",BE!$M$2:$M$99997,"Testing")+COUNTIFS(BE!$B$2:$B$99997,"Benefit Plan",BE!$M$2:$M$99997,"Re-Testing")+COUNTIFS(BE!$B$2:$B$99997,"Benefit Plan",BE!$M$2:$M$99997,"In progress") -> 4 | H9: =COUNTIFS(BE!$B$2:$B$99997,"Benefit Plan",BE!$M$2:$M$99997,"Passed")+COUNTIFS(BE!$B$2:$B$99997,"Benefit Plan",BE!$M$2:$M$99997,"Re-Test Passed")+COUNTIFS(BE!$B$2:$B$99997,"Benefit Plan",BE!$M$2:$M$99997,"Pass") -> 149 | I9: =COUNTIFS(BE!$B$2:$B$99997,"Benefit Plan",BE!$M$2:$M$99997,"Failed")+COUNTIFS(BE!$B$2:$B$99997,"Benefit Plan",BE!$M$2:$M$99997,"Re-Test Failed") -> 40 | J9: =COUNTIFS(BE!$B$2:$B$99997,"Benefit Plan",BE!$M$2:$M$99997,"Blocked") -> 6 | K9: =COUNTIFS(BE!$B$2:$B$99997,"Benefit Plan",BE!$M$2:$M$99997,"Cancel")+COUNTIFS(BE!$B$2:$B$99997,"Benefit Plan",BE!$M$2:$M$99997,"Cancelled") -> 0 | L9: =COUNTIFS(BE!$B$2:$B$99997,"Benefit Plan",BE!$D$2:$D$99997,"<>",BE!$M$2:$M$99997,"<>Cancel",BE!$M$2:$M$99997,"<>Cancelled") -> 222 | M9: =IFERROR(H9/L9,"") -> 0.67117117
A10: Benefit Rule | C10: =COUNTIFS(BE!$B$2:$B$99997,"Benefit Rule",BE!$D$2:$D$99997,"<>") -> 209 | D10: =H10+I10+J10 -> 0 | E10: =COUNTIFS(BE!$B$2:$B$99997,"Benefit Rule",BE!$M$2:$M$99997,"Ready to test")+COUNTIFS(BE!$B$2:$B$99997,"Benefit Rule",BE!$M$2:$M$99997,"Pending confirm")+COUNTIFS(BE!$B$2:$B$99997,"Benefit Rule",BE!$M$2:$M$99997,"Testing")+COUNTIFS(BE!$B$2:$B$99997,"Benefit Rule",BE!$M$2:$M$99997,"Re-Testing")+COUNTIFS(BE!$B$2:$B$99997,"Benefit Rule",BE!$M$2:$M$99997,"In progress") -> 209 | F10: =L10-G10-H10-I10-J10 -> 209 | G10: =COUNTIFS(BE!$B$2:$B$99997,"Benefit Rule",BE!$M$2:$M$99997,"Pending confirm")+COUNTIFS(BE!$B$2:$B$99997,"Benefit Rule",BE!$M$2:$M$99997,"Testing")+COUNTIFS(BE!$B$2:$B$99997,"Benefit Rule",BE!$M$2:$M$99997,"Re-Testing")+COUNTIFS(BE!$B$2:$B$99997,"Benefit Rule",BE!$M$2:$M$99997,"In progress") -> 0 | H10: =COUNTIFS(BE!$B$2:$B$99997,"Benefit Rule",BE!$M$2:$M$99997,"Passed")+COUNTIFS(BE!$B$2:$B$99997,"Benefit Rule",BE!$M$2:$M$99997,"Re-Test Passed")+COUNTIFS(BE!$B$2:$B$99997,"Benefit Rule",BE!$M$2:$M$99997,"Pass") -> 0 | I10: =COUNTIFS(BE!$B$2:$B$99997,"Benefit Rule",BE!$M$2:$M$99997,"Failed")+COUNTIFS(BE!$B$2:$B$99997,"Benefit Rule",BE!$M$2:$M$99997,"Re-Test Failed") -> 0 | J10: =COUNTIFS(BE!$B$2:$B$99997,"Benefit Rule",BE!$M$2:$M$99997,"Blocked") -> 0 | K10: =COUNTIFS(BE!$B$2:$B$99997,"Benefit Rule",BE!$M$2:$M$99997,"Cancel")+COUNTIFS(BE!$B$2:$B$99997,"Benefit Rule",BE!$M$2:$M$99997,"Cancelled") -> 0 | L10: =COUNTIFS(BE!$B$2:$B$99997,"Benefit Rule",BE!$D$2:$D$99997,"<>",BE!$M$2:$M$99997,"<>Cancel",BE!$M$2:$M$99997,"<>Cancelled") -> 209 | M10: =IFERROR(H10/L10,"") -> 0
A11: TM – Time Management | B11: Siriya | C11: =SUM(C12:C17) -> 223 | D11: =H11+I11+J11 -> 108 | E11: =COUNTIF(TM!$M$2:$M$100000,"Ready to test")+COUNTIF(TM!$M$2:$M$100000,"Pending confirm")+COUNTIF(TM!$M$2:$M$100000,"Testing")+COUNTIF(TM!$M$2:$M$100000,"Re-Testing")+COUNTIF(TM!$M$2:$M$100000,"In progress") -> 12 | F11: =L11-G11-H11-I11-J11 -> 102 | G11: =SUM(G12:G17) -> 11 | H11: =COUNTIF(TM!$M$2:$M$100000,"Passed")+COUNTIF(TM!$M$2:$M$100000,"Re-Test Passed")+COUNTIF(TM!$M$2:$M$100000,"Pass") -> 17 | I11: =COUNTIF(TM!$M$2:$M$100000,"Failed")+COUNTIF(TM!$M$2:$M$100000,"Re-Test Failed") -> 5 | J11: =COUNTIF(TM!$M$2:$M$100000,"Blocked") -> 86 | K11: =COUNTIF(TM!$M$2:$M$100000,"Cancel")+COUNTIF(TM!$M$2:$M$100000,"Cancelled") -> 2 | L11: =SUM(L12:L17) -> 221 | M11: =IFERROR(H11/L11,"") -> 0.076923077
A12: Web Clocking | C12: =COUNTIFS(TM!$B$2:$B$100000,"Web Clocking") -> 58 | D12: =H12+I12+J12 -> 47 | E12: =COUNTIFS(TM!$B$2:$B$100000,"Web Clocking",TM!$M$2:$M$100000,"Ready to test")+COUNTIFS(TM!$B$2:$B$100000,"Web Clocking",TM!$M$2:$M$100000,"Pending confirm")+COUNTIFS(TM!$B$2:$B$100000,"Web Clocking",TM!$M$2:$M$100000,"Testing")+COUNTIFS(TM!$B$2:$B$100000,"Web Clocking",TM!$M$2:$M$100000,"Re-Testing")+COUNTIFS(TM!$B$2:$B$100000,"Web Clocking",TM!$M$2:$M$100000,"In progress") -> 11 | F12: =L12-G12-H12-I12-J12 -> 0 | G12: =COUNTIFS(TM!$B$2:$B$100000,"Web Clocking",TM!$M$2:$M$100000,"Ready to test")+COUNTIFS(TM!$B$2:$B$100000,"Web Clocking",TM!$M$2:$M$100000,"Pending confirm")+COUNTIFS(TM!$B$2:$B$100000,"Web Clocking",TM!$M$2:$M$100000,"Testing")+COUNTIFS(TM!$B$2:$B$100000,"Web Clocking",TM!$M$2:$M$100000,"Re-Testing")+COUNTIFS(TM!$B$2:$B$100000,"Web Clocking",TM!$M$2:$M$100000,"In progress") -> 11 | H12: =COUNTIFS(TM!$B$2:$B$100000,"Web Clocking",TM!$M$2:$M$100000,"Passed")+COUNTIFS(TM!$B$2:$B$100000,"Web Clocking",TM!$M$2:$M$100000,"Re-Test Passed")+COUNTIFS(TM!$B$2:$B$100000,"Web Clocking",TM!$M$2:$M$100000,"Pass") -> 2 | I12: =COUNTIFS(TM!$B$2:$B$100000,"Web Clocking",TM!$M$2:$M$100000,"Failed")+COUNTIFS(TM!$B$2:$B$100000,"Web Clocking",TM!$M$2:$M$100000,"Re-Test Failed") -> 1 | J12: =COUNTIFS(TM!$B$2:$B$100000,"Web Clocking",TM!$M$2:$M$100000,"Blocked") -> 44 | K12: =COUNTIFS(TM!$B$2:$B$100000,"Web Clocking",TM!$M$2:$M$100000,"Cancel")+COUNTIFS(TM!$B$2:$B$100000,"Web Clocking",TM!$M$2:$M$100000,"Cancelled") -> 0 | L12: =COUNTIFS(TM!$B$2:$B$100000,"Web Clocking",TM!$M$2:$M$100000,"<>Cancel",TM!$M$2:$M$100000,"<>Cancelled") -> 58 | M12: =IFERROR(H12/L12,"") -> 0.034482759
A13: OT Request | C13: =COUNTIFS(TM!$B$2:$B$100000,"OT Request") -> 16 | D13: =H13+I13+J13 -> 0 | E13: =COUNTIFS(TM!$B$2:$B$100000,"OT Request",TM!$M$2:$M$100000,"Ready to test")+COUNTIFS(TM!$B$2:$B$100000,"OT Request",TM!$M$2:$M$100000,"Pending confirm")+COUNTIFS(TM!$B$2:$B$100000,"OT Request",TM!$M$2:$M$100000,"Testing")+COUNTIFS(TM!$B$2:$B$100000,"OT Request",TM!$M$2:$M$100000,"Re-Testing")+COUNTIFS(TM!$B$2:$B$100000,"OT Request",TM!$M$2:$M$100000,"In progress") -> 0 | F13: =L13-G13-H13-I13-J13 -> 16 | G13: =COUNTIFS(TM!$B$2:$B$100000,"OT Request",TM!$M$2:$M$100000,"Pending confirm")+COUNTIFS(TM!$B$2:$B$100000,"OT Request",TM!$M$2:$M$100000,"Testing")+COUNTIFS(TM!$B$2:$B$100000,"OT Request",TM!$M$2:$M$100000,"Re-Testing")+COUNTIFS(TM!$B$2:$B$100000,"OT Request",TM!$M$2:$M$100000,"In progress") -> 0 | H13: =COUNTIFS(TM!$B$2:$B$100000,"OT Request",TM!$M$2:$M$100000,"Passed")+COUNTIFS(TM!$B$2:$B$100000,"OT Request",TM!$M$2:$M$100000,"Re-Test Passed")+COUNTIFS(TM!$B$2:$B$100000,"OT Request",TM!$M$2:$M$100000,"Pass") -> 0 | I13: =COUNTIFS(TM!$B$2:$B$100000,"OT Request",TM!$M$2:$M$100000,"Failed")+COUNTIFS(TM!$B$2:$B$100000,"OT Request",TM!$M$2:$M$100000,"Re-Test Failed") -> 0 | J13: =COUNTIFS(TM!$B$2:$B$100000,"OT Request",TM!$M$2:$M$100000,"Blocked") -> 0 | K13: =COUNTIFS(TM!$B$2:$B$100000,"OT Request",TM!$M$2:$M$100000,"Cancel")+COUNTIFS(TM!$B$2:$B$100000,"OT Request",TM!$M$2:$M$100000,"Cancelled") -> 0 | L13: =COUNTIFS(TM!$B$2:$B$100000,"OT Request",TM!$M$2:$M$100000,"<>Cancel",TM!$M$2:$M$100000,"<>Cancelled") -> 16 | M13: =IFERROR(H13/L13,"") -> 0
A14: Time Correction | C14: =COUNTIFS(TM!$B$2:$B$100000,"Time Correction") -> 11 | D14: =H14+I14+J14 -> 0 | E14: =COUNTIFS(TM!$B$2:$B$100000,"Time Correction",TM!$M$2:$M$100000,"Ready to test")+COUNTIFS(TM!$B$2:$B$100000,"Time Correction",TM!$M$2:$M$100000,"Pending confirm")+COUNTIFS(TM!$B$2:$B$100000,"Time Correction",TM!$M$2:$M$100000,"Testing")+COUNTIFS(TM!$B$2:$B$100000,"Time Correction",TM!$M$2:$M$100000,"Re-Testing")+COUNTIFS(TM!$B$2:$B$100000,"Time Correction",TM!$M$2:$M$100000,"In progress") -> 0 | F14: =L14-G14-H14-I14-J14 -> 11 | G14: =COUNTIFS(TM!$B$2:$B$100000,"Time Correction",TM!$M$2:$M$100000,"Pending confirm")+COUNTIFS(TM!$B$2:$B$100000,"Time Correction",TM!$M$2:$M$100000,"Testing")+COUNTIFS(TM!$B$2:$B$100000,"Time Correction",TM!$M$2:$M$100000,"Re-Testing")+COUNTIFS(TM!$B$2:$B$100000,"Time Correction",TM!$M$2:$M$100000,"In progress") -> 0 | H14: =COUNTIFS(TM!$B$2:$B$100000,"Time Correction",TM!$M$2:$M$100000,"Passed")+COUNTIFS(TM!$B$2:$B$100000,"Time Correction",TM!$M$2:$M$100000,"Re-Test Passed")+COUNTIFS(TM!$B$2:$B$100000,"Time Correction",TM!$M$2:$M$100000,"Pass") -> 0 | I14: =COUNTIFS(TM!$B$2:$B$100000,"Time Correction",TM!$M$2:$M$100000,"Failed")+COUNTIFS(TM!$B$2:$B$100000,"Time Correction",TM!$M$2:$M$100000,"Re-Test Failed") -> 0 | J14: =COUNTIFS(TM!$B$2:$B$100000,"Time Correction",TM!$M$2:$M$100000,"Blocked") -> 0 | K14: =COUNTIFS(TM!$B$2:$B$100000,"Time Correction",TM!$M$2:$M$100000,"Cancel")+COUNTIFS(TM!$B$2:$B$100000,"Time Correction",TM!$M$2:$M$100000,"Cancelled") -> 0 | L14: =COUNTIFS(TM!$B$2:$B$100000,"Time Correction",TM!$M$2:$M$100000,"<>Cancel",TM!$M$2:$M$100000,"<>Cancelled") -> 11 | M14: =IFERROR(H14/L14,"") -> 0
A15: Leave Request | C15: =COUNTIFS(TM!$B$2:$B$100000,"Leave Request") -> 71 | D15: =H15+I15+J15 -> 21 | E15: =COUNTIFS(TM!$B$2:$B$100000,"Leave Request",TM!$M$2:$M$100000,"Ready to test")+COUNTIFS(TM!$B$2:$B$100000,"Leave Request",TM!$M$2:$M$100000,"Pending confirm")+COUNTIFS(TM!$B$2:$B$100000,"Leave Request",TM!$M$2:$M$100000,"Testing")+COUNTIFS(TM!$B$2:$B$100000,"Leave Request",TM!$M$2:$M$100000,"Re-Testing")+COUNTIFS(TM!$B$2:$B$100000,"Leave Request",TM!$M$2:$M$100000,"In progress") -> 1 | F15: =L15-G15-H15-I15-J15 -> 50 | G15: =COUNTIFS(TM!$B$2:$B$100000,"Leave Request",TM!$M$2:$M$100000,"Pending confirm")+COUNTIFS(TM!$B$2:$B$100000,"Leave Request",TM!$M$2:$M$100000,"Testing")+COUNTIFS(TM!$B$2:$B$100000,"Leave Request",TM!$M$2:$M$100000,"Re-Testing")+COUNTIFS(TM!$B$2:$B$100000,"Leave Request",TM!$M$2:$M$100000,"In progress") -> 0 | H15: =COUNTIFS(TM!$B$2:$B$100000,"Leave Request",TM!$M$2:$M$100000,"Passed")+COUNTIFS(TM!$B$2:$B$100000,"Leave Request",TM!$M$2:$M$100000,"Re-Test Passed")+COUNTIFS(TM!$B$2:$B$100000,"Leave Request",TM!$M$2:$M$100000,"Pass") -> 9 | I15: =COUNTIFS(TM!$B$2:$B$100000,"Leave Request",TM!$M$2:$M$100000,"Failed")+COUNTIFS(TM!$B$2:$B$100000,"Leave Request",TM!$M$2:$M$100000,"Re-Test Failed") -> 2 | J15: =COUNTIFS(TM!$B$2:$B$100000,"Leave Request",TM!$M$2:$M$100000,"Blocked") -> 10 | K15: =COUNTIFS(TM!$B$2:$B$100000,"Leave Request",TM!$M$2:$M$100000,"Cancel")+COUNTIFS(TM!$B$2:$B$100000,"Leave Request",TM!$M$2:$M$100000,"Cancelled") -> 0 | L15: =COUNTIFS(TM!$B$2:$B$100000,"Leave Request",TM!$M$2:$M$100000,"<>Cancel",TM!$M$2:$M$100000,"<>Cancelled") -> 71 | M15: =IFERROR(H15/L15,"") -> 0.12676056
A16: Timesheet | C16: =COUNTIFS(TM!$B$2:$B$100000,"Timesheet") -> 55 | D16: =H16+I16+J16 -> 40 | E16: =COUNTIFS(TM!$B$2:$B$100000,"Timesheet",TM!$M$2:$M$100000,"Ready to test")+COUNTIFS(TM!$B$2:$B$100000,"Timesheet",TM!$M$2:$M$100000,"Pending confirm")+COUNTIFS(TM!$B$2:$B$100000,"Timesheet",TM!$M$2:$M$100000,"Testing")+COUNTIFS(TM!$B$2:$B$100000,"Timesheet",TM!$M$2:$M$100000,"Re-Testing")+COUNTIFS(TM!$B$2:$B$100000,"Timesheet",TM!$M$2:$M$100000,"In progress") -> 0 | F16: =L16-G16-H16-I16-J16 -> 13 | G16: =COUNTIFS(TM!$B$2:$B$100000,"Timesheet",TM!$M$2:$M$100000,"Pending confirm")+COUNTIFS(TM!$B$2:$B$100000,"Timesheet",TM!$M$2:$M$100000,"Testing")+COUNTIFS(TM!$B$2:$B$100000,"Timesheet",TM!$M$2:$M$100000,"Re-Testing")+COUNTIFS(TM!$B$2:$B$100000,"Timesheet",TM!$M$2:$M$100000,"In progress") -> 0 | H16: =COUNTIFS(TM!$B$2:$B$100000,"Timesheet",TM!$M$2:$M$100000,"Passed")+COUNTIFS(TM!$B$2:$B$100000,"Timesheet",TM!$M$2:$M$100000,"Re-Test Passed")+COUNTIFS(TM!$B$2:$B$100000,"Timesheet",TM!$M$2:$M$100000,"Pass") -> 6 | I16: =COUNTIFS(TM!$B$2:$B$100000,"Timesheet",TM!$M$2:$M$100000,"Failed")+COUNTIFS(TM!$B$2:$B$100000,"Timesheet",TM!$M$2:$M$100000,"Re-Test Failed") -> 2 | J16: =COUNTIFS(TM!$B$2:$B$100000,"Timesheet",TM!$M$2:$M$100000,"Blocked") -> 32 | K16: =COUNTIFS(TM!$B$2:$B$100000,"Timesheet",TM!$M$2:$M$100000,"Cancel")+COUNTIFS(TM!$B$2:$B$100000,"Timesheet",TM!$M$2:$M$100000,"Cancelled") -> 2 | L16: =COUNTIFS(TM!$B$2:$B$100000,"Timesheet",TM!$M$2:$M$100000,"<>Cancel",TM!$M$2:$M$100000,"<>Cancelled") -> 53 | M16: =IFERROR(H16/L16,"") -> 0.11320755
A17: Cal to PY | C17: =COUNTIFS(TM!$B$2:$B$100000,"Cal to PY") -> 12 | D17: =H17+I17+J17 -> 0 | E17: =COUNTIFS(TM!$B$2:$B$100000,"Cal to PY",TM!$M$2:$M$100000,"Ready to test")+COUNTIFS(TM!$B$2:$B$100000,"Cal to PY",TM!$M$2:$M$100000,"Pending confirm")+COUNTIFS(TM!$B$2:$B$100000,"Cal to PY",TM!$M$2:$M$100000,"Testing")+COUNTIFS(TM!$B$2:$B$100000,"Cal to PY",TM!$M$2:$M$100000,"Re-Testing")+COUNTIFS(TM!$B$2:$B$100000,"Cal to PY",TM!$M$2:$M$100000,"In progress") -> 0 | F17: =L17-G17-H17-I17-J17 -> 12 | G17: =COUNTIFS(TM!$B$2:$B$100000,"Cal to PY",TM!$M$2:$M$100000,"Pending confirm")+COUNTIFS(TM!$B$2:$B$100000,"Cal to PY",TM!$M$2:$M$100000,"Testing")+COUNTIFS(TM!$B$2:$B$100000,"Cal to PY",TM!$M$2:$M$100000,"Re-Testing")+COUNTIFS(TM!$B$2:$B$100000,"Cal to PY",TM!$M$2:$M$100000,"In progress") -> 0 | H17: =COUNTIFS(TM!$B$2:$B$100000,"Cal to PY",TM!$M$2:$M$100000,"Passed")+COUNTIFS(TM!$B$2:$B$100000,"Cal to PY",TM!$M$2:$M$100000,"Re-Test Passed")+COUNTIFS(TM!$B$2:$B$100000,"Cal to PY",TM!$M$2:$M$100000,"Pass") -> 0 | I17: =COUNTIFS(TM!$B$2:$B$100000,"Cal to PY",TM!$M$2:$M$100000,"Failed")+COUNTIFS(TM!$B$2:$B$100000,"Cal to PY",TM!$M$2:$M$100000,"Re-Test Failed") -> 0 | J17: =COUNTIFS(TM!$B$2:$B$100000,"Cal to PY",TM!$M$2:$M$100000,"Blocked") -> 0 | K17: =COUNTIFS(TM!$B$2:$B$100000,"Cal to PY",TM!$M$2:$M$100000,"Cancel")+COUNTIFS(TM!$B$2:$B$100000,"Cal to PY",TM!$M$2:$M$100000,"Cancelled") -> 0 | L17: =COUNTIFS(TM!$B$2:$B$100000,"Cal to PY",TM!$M$2:$M$100000,"<>Cancel",TM!$M$2:$M$100000,"<>Cancelled") -> 12 | M17: =IFERROR(H17/L17,"") -> 0
A18: PY – Payroll | B18: Pongsakorn | C18: =COUNTIFS(PY!$D$3:$D$99991,"<>") -> 360 | D18: =H18+I18+J18 -> 265 | E18: =COUNTIF(PY!$M$3:$M$99998,"Ready to test")+COUNTIF(PY!$M$3:$M$99998,"Pending confirm")+COUNTIF(PY!$M$3:$M$99998,"Testing")+COUNTIF(PY!$M$3:$M$99998,"Re-Testing")+COUNTIF(PY!$M$3:$M$99998,"In progress") -> 0 | F18: =L18-G18-H18-I18-J18 -> 95 | G18: =COUNTIF(PY!$M$3:$M$99998,"Pending confirm")+COUNTIF(PY!$M$3:$M$99998,"Testing")+COUNTIF(PY!$M$3:$M$99998,"Re-Testing")+COUNTIF(PY!$M$3:$M$99998,"In progress") -> 0 | H18: =COUNTIF(PY!$M$3:$M$99998,"Passed")+COUNTIF(PY!$M$3:$M$99998,"Re-Test Passed")+COUNTIF(PY!$M$3:$M$99998,"Pass") -> 141 | I18: =COUNTIF(PY!$M$3:$M$99998,"Failed")+COUNTIF(PY!$M$3:$M$99998,"Re-Test Failed") -> 112 | J18: =COUNTIF(PY!$M$3:$M$99998,"Blocked") -> 12 | K18: =COUNTIF(PY!$M$3:$M$99998,"Cancel")+COUNTIF(PY!$M$3:$M$99998,"Cancelled") -> 0 | L18: =COUNTIFS(PY!$D$3:$D$99991,"<>",PY!$M$3:$M$99991,"<>Cancel",PY!$M$3:$M$99991,"<>Cancelled") -> 360 | M18: =IFERROR(H18/L18,"") -> 0.39166667
A19: Processing | C19: =COUNTIFS(PY!$B$3:$B$99992,"Processing",PY!$D$3:$D$99992,"<>") -> 116 | D19: =H19+I19+J19 -> 23 | E19: =COUNTIFS(PY!$B$3:$B$99998,"Processing",PY!$M$3:$M$99998,"Ready to test")+COUNTIFS(PY!$B$3:$B$99998,"Processing",PY!$M$3:$M$99998,"Pending confirm")+COUNTIFS(PY!$B$3:$B$99998,"Processing",PY!$M$3:$M$99998,"Testing")+COUNTIFS(PY!$B$3:$B$99998,"Processing",PY!$M$3:$M$99998,"Re-Testing")+COUNTIFS(PY!$B$3:$B$99998,"Processing",PY!$M$3:$M$99998,"In progress") -> 0 | F19: =L19-G19-H19-I19-J19 -> 93 | G19: =COUNTIFS(PY!$B$3:$B$99998,"Processing",PY!$M$3:$M$99998,"Pending confirm")+COUNTIFS(PY!$B$3:$B$99998,"Processing",PY!$M$3:$M$99998,"Testing")+COUNTIFS(PY!$B$3:$B$99998,"Processing",PY!$M$3:$M$99998,"Re-Testing")+COUNTIFS(PY!$B$3:$B$99998,"Processing",PY!$M$3:$M$99998,"In progress") -> 0 | H19: =COUNTIFS(PY!$B$3:$B$99998,"Processing",PY!$M$3:$M$99998,"Passed")+COUNTIFS(PY!$B$3:$B$99998,"Processing",PY!$M$3:$M$99998,"Re-Test Passed")+COUNTIFS(PY!$B$3:$B$99998,"Processing",PY!$M$3:$M$99998,"Pass") -> 15 | I19: =COUNTIFS(PY!$B$3:$B$99998,"Processing",PY!$M$3:$M$99998,"Failed")+COUNTIFS(PY!$B$3:$B$99998,"Processing",PY!$M$3:$M$99998,"Re-Test Failed") -> 6 | J19: =COUNTIFS(PY!$B$3:$B$99998,"Processing",PY!$M$3:$M$99998,"Blocked") -> 2 | K19: =COUNTIFS(PY!$B$3:$B$99998,"Processing",PY!$M$3:$M$99998,"Cancel")+COUNTIFS(PY!$B$3:$B$99998,"Processing",PY!$M$3:$M$99998,"Cancelled") -> 0 | L19: =COUNTIFS(PY!$B$3:$B$99992,"Processing",PY!$D$3:$D$99992,"<>",PY!$M$3:$M$99992,"<>Cancel",PY!$M$3:$M$99992,"<>Cancelled") -> 116 | M19: =IFERROR(H19/L19,"") -> 0.12931034
A20: Configuration | C20: =COUNTIFS(PY!$B$3:$B$99992,"Configuration",PY!$D$3:$D$99992,"<>") -> 244 | D20: =H20+I20+J20 -> 242 | E20: =COUNTIFS([1]PY!$B$3:$B$99998,"Configuration",[1]PY!$M$3:$M$99998,"Ready to test")+COUNTIFS([1]PY!$B$3:$B$99998,"Configuration",[1]PY!$M$3:$M$99998,"Pending confirm")+COUNTIFS([1]PY!$B$3:$B$99998,"Configuration",[1]PY!$M$3:$M$99998,"Testing")+COUNTIFS([1]PY!$B$3:$B$99998,"Configuration",[1]PY!$M$3:$M$99998,"Re-Testing")+COUNTIFS([1]PY!$B$3:$B$99998,"Configuration",[1]PY!$M$3:$M$99998,"In progress") -> #VALUE! | F20: =L20-G20-H20-I20-J20 -> 2 | G20: =COUNTIFS(PY!$B$3:$B$99998,"Configuration",PY!$M$3:$M$99998,"Pending confirm")+COUNTIFS(PY!$B$3:$B$99998,"Configuration",PY!$M$3:$M$99998,"Testing")+COUNTIFS(PY!$B$3:$B$99998,"Configuration",PY!$M$3:$M$99998,"Re-Testing")+COUNTIFS(PY!$B$3:$B$99998,"Configuration",PY!$M$3:$M$99998,"In progress") -> 0 | H20: =COUNTIFS(PY!$B$3:$B$99998,"Configuration",PY!$M$3:$M$99998,"Passed")+COUNTIFS(PY!$B$3:$B$99998,"Configuration",PY!$M$3:$M$99998,"Re-Test Passed")+COUNTIFS(PY!$B$3:$B$99998,"Configuration",PY!$M$3:$M$99998,"Pass") -> 126 | I20: =COUNTIFS(PY!$B$3:$B$99998,"Configuration",PY!$M$3:$M$99998,"Failed")+COUNTIFS(PY!$B$3:$B$99998,"Configuration",PY!$M$3:$M$99998,"Re-Test Failed") -> 106 | J20: =COUNTIFS(PY!$B$3:$B$99998,"Configuration",PY!$M$3:$M$99998,"Blocked") -> 10 | K20: =COUNTIFS(PY!$B$3:$B$99998,"Configuration",PY!$M$3:$M$99998,"Cancel")+COUNTIFS(PY!$B$3:$B$99998,"Configuration",PY!$M$3:$M$99998,"Cancelled") -> 0 | L20: =COUNTIFS(PY!$B$3:$B$99992,"Configuration",PY!$D$3:$D$99992,"<>",PY!$M$3:$M$99992,"<>Cancel",PY!$M$3:$M$99992,"<>Cancelled") -> 244 | M20: =IFERROR(H20/L20,"") -> 0.51639344
A21: TOTAL | C21: =C4+C8+C11+C18 -> 1286 | D21: =D4+D8+D11+D18 -> 585 | E21: =E4+E8+E11+E18 -> 247 | F21: =F4+F8+F11+F18 -> 586 | G21: =G4+G8+G11+G18 -> 18 | H21: =H4+H8+H11+H18 -> 315 | I21: =I4+I8+I11+I18 -> 164 | J21: =J4+J8+J11+J18 -> 106 | ... L21: =L4+L8+L11+L18 -> 1189 | M21: =IFERROR(H21/L21,"") -> 0.26492851

Sheet Defects
A1: OPEN DEFECTS / BLOCKERS
A3: Total Open | B3: =COUNTIFS(Blockers!$D$4:$D$103,"<>",Blockers!$I$4:$I$103,"<>Closed",Blockers!$I$4:$I$103,"<>Resolved",Blockers!$I$4:$I$103,"<>Done") -> 5 | C3: Highest | D3: =COUNTIFS(Blockers!$D$4:$D$103,"<>",Blockers!$F$4:$F$103,"Highest",Blockers!$I$4:$I$103,"<>Closed",Blockers!$I$4:$I$103,"<>Resolved",Blockers!$I$4:$I$103,"<>Done") -> 1 | E3: High | F3: =COUNTIFS(Blockers!$D$4:$D$103,"<>",Blockers!$F$4:$F$103,"High",Blockers!$I$4:$I$103,"<>Closed",Blockers!$I$4:$I$103,"<>Resolved",Blockers!$I$4:$I$103,"<>Done") -> 1 | G3: Medium | H3: =COUNTIFS(Blockers!$D$4:$D$103,"<>",Blockers!$F$4:$F$103,"Medium",Blockers!$I$4:$I$103,"<>Closed",Blockers!$I$4:$I$103,"<>Resolved",Blockers!$I$4:$I$103,"<>Done") -> 2 | I3: Low | J3: =COUNTIFS(Blockers!$D$4:$D$103,"<>",Blockers!$F$4:$F$103,"Low",Blockers!$I$4:$I$103,"<>Closed",Blockers!$I$4:$I$103,"<>Resolved",Blockers!$I$4:$I$103,"<>Done") -> 1
A5: # | B5: Module | C5: Bug No. | D5: Date Reported | E5: Issue | K5: Severity | L5: Owner | M5: ETA | N5: Status | O5: Status | P5: Note
A6: 1 | B6: EC | C6: BUG 71875 | D6: 46266 | E6: [EC-Hiring] แก้ไขรายการ Save Draft เดิม แต่ใน DB: transaction_new_hires สร้าง Transaction ใหม่ | K6: 2 - High | L6: Thanakorn Sirikulpan | N6: New | O6: New
A7: 2 | B7: EC | C7: BUG 71873 | D7: 46266 | E7: [EC-Hiring] Field 'Position' แสดงค่าใน dropdownlist ซ้ำ | K7: 3 - Medium | L7: Thanakorn Sirikulpan | N7: New
A8: 3 | B8: EC | C8: BUG 71887 | D8: 46266 | E8: [EC-Hiring] กดปุ่ม 'View Details' New employee หลัง Submit ระบบแสดงหน้าจอ '404 - ไม่พบหน้าที่ค้นหา' | K8: 2 - High | L8: Thanakorn Sirikulpan | N8: New
A9: 4 | B9: EC | C9: BUG 71888 | D9: 46266 | E9: [EC-Hiring] หลัง Submit รายการ Save Draft สำเร็จ ระบบไม่เคลียร์รายการเดิมออกจาก Tab Draft Form | K9: 2 - High | L9: Thanakorn Sirikulpan | N9: New
A10: 5 | B10: EC | C10: BUG 71851 | D10: 46266 | E10: [EC-Consent] กดปุ่ม Decline แล้วระบบ redirects กลับมาที่ link Env. Dev | K10: 3 - Medium | L10: Thanakorn Sirikulpan | N10: New
A11: 6 | B11: BE | C11: BUG 70609 | D11: 46266 | E11: [BE-Plan] Unable to save plan when entering more than 50 characters | K11: 3 - Medium | L11: Panupong (Outsource) Jaengaks | M11: 46269 | N11: New
A12: 7 | B12: BE | C12: BUG 70636 | D12: 46266 | E12: [BE-Plan] Benefit Name filter field too narrow when selecting long name | K12: 4 - Low | L12: Panupong (Outsource) Jaengaks | M12: 46276 | N12: New
A13: 8 | B13: BE | C13: BUG 70659 | D13: 46266 | E13: [BE-Plan] Company list is inconsistent with the selected Country | K13: 3 - Medium | L13: Panupong (Outsource) Jaengaks | M13: 46269 | N13: New
A14: 9 | B14: BE | C14: BUG 70658 | D14: 46266 | E14: [BE-Plan] Company dropdown does not show all list of Company | K14: 3 - Medium | L14: Panupong (Outsource) Jaengaks | M14: 46269 | N14: New
A15: 10 | B15: BE | C15: BUG 70675 | D15: 46266 | E15: [BE-Plan] Company dropdown not sorted by Company Name | K15: 4 - Low | L15: Panupong (Outsource) Jaengaks | M15: 46276 | N15: New
A16: 11 | B16: BE | C16: BUG 70676 | D16: 46266 | E16: [BE-Plan] Company field not display error message "This field is required" | K16: 4 - Low | L16: Panupong (Outsource) Jaengaks | M16: 46276 | N16: New
A17: 12 | B17: BE | C17: BUG 70758 | D17: 46266 | E17: [BE-Plan] Effective Start Date field not display error message "Effective start date must not be greater than effective end date." | K17: 4 - Low | L17: Panupong (Outsource) Jaengaks | M17: 46276 | N17: New
A18: 13 | B18: BE | C18: BUG 70787 | D18: 46266 | E18: [BE-Plan] Eligible Claim Date field is not optional | K18: 3 - Medium | L18: Panupong (Outsource) Jaengaks | M18: 46269 | N18: New
A19: 14 | B19: BE | C19: BUG 70798 | D19: 46266 | E19: [BE-Plan] Eligible Claim Date field not display error message "Eligible Claim date can be at most 365 days." | K19: 4 - Low | L19: Panupong (Outsource) Jaengaks | M19: 46276 | N19: New
A20: 15 | B20: BE | C20: BUG 70813 | D20: 46266 | E20: [BE-Plan] Cannot recreate a deleted Benefit Plan ID | K20: 3 - Medium | L20: Panupong (Outsource) Jaengaks | M20: 46269 | N20: New
A21: 16 | B21: BE | C21: BUG 70814 | D21: 46266 | E21: [BE-Plan] Eligible Claim Date field not display error message "Enter number greater than 0" | K21: 3 - Medium | L21: Panupong (Outsource) Jaengaks | M21: 46269 | N21: New
A22: 17 | B22: BE | C22: BUG 70829 | D22: 46266 | E22: [BE-Plan] Make Correction history is displayed under incorrect Effective Date | K22: 1 - Critical | L22: Panupong (Outsource) Jaengaks | M22: 46269 | N22: New | P22: Block PL_08_29
A23: 18 | B23: BE | C23: BUG 70830 | D23: 46266 | E23: [BE-Plan] Insert calendar allows users to select past dates | K23: 3 - Medium | L23: Panupong (Outsource) Jaengaks | M23: 46269 | N23: New
A24: 19 | B24: BE | C24: BUG 70764 | D24: 46266 | E24: [BE-Plan] Benefit Name does not display an error message when entering spaces only | K24: 4 - Low | L24: Panupong (Outsource) Jaengaks | M24: 46276 | N24: New
A25: 20 | B25: BE | C25: BUG 70831 | D25: 46266 | E25: [BE-Plan] Insert Calendar is not fully displayed | K25: 4 - Low | L25: Panupong (Outsource) Jaengaks | M25: 46276 | N25: New
A26: 21 | B26: BE | C26: BUG 71147 | D26: 46266 | E26: [BE-Plan] Benefit Name field does not support all required special characters | K26: 4 - Low | L26: Panupong (Outsource) Jaengaks | M26: 46276 | N26: New
A27: 22 | B27: BE | C27: BUG 71144 | D27: 46266 | E27: [BE-Plan] Plan ID field does not support all required special characters | K27: 4 - Low | L27: Panupong (Outsource) Jaengaks | M27: 46276 | N27: New
A28: 23 | B28: BE | C28: BUG 71164 | D28: 46266 | E28: [BE-Plan] History displays incorrect status | K28: 1 - Critical | L28: Panupong (Outsource) Jaengaks | M28: 46269 | N28: New
A29: 24 | B29: BE | C29: BUG 71210 | D29: 46266 | E29: [BE-Plan] History displays only Company Code instead of Company Name (Code) for Make Correction and Insert | K29: 4 - Low | L29: Panupong (Outsource) Jaengaks | M29: 46276 | N29: New
A30: 25 | B30: BE | C30: BUG 71440 | D30: 46266 | E30: [BE-Plan] Insert Date can be selected earlier than original Effective Start Date | K30: 3 - Medium | L30: Panupong (Outsource) Jaengaks | M30: 46269 | N30: New
A31: 26 | B31: BE | C31: BUG 71448 | D31: 46266 | E31: [BE-Plan] History displays incorrect action for multiple inserts on the same Effective Start Date | K31: 3 - Medium | L31: Panupong (Outsource) Jaengaks | M31: 46269 | N31: New
A32: 27 | B32: BE | C32: BUG 71453 | D32: 46266 | E32: [BE-Plan] Allow insert with duplicate data | K32: 3 - Medium | L32: Panupong (Outsource) Jaengaks | M32: 46269 | N32: New
A33: 28 | B33: BE | C33: BUG 71727 | D33: 46266 | E33: [BE-Plan] Effective Start/End Date allows invalid date format and year exceeding 4 digits | K33: 4 - Low | L33: Panupong (Outsource) Jaengaks | M33: 46276 | N33: New
A34: 29 | B34: TM | C34: BUG 71868 | D34: 46266 | E34: [TM - Web clock] กดปุ่ม clock in/out ไม่ได้ | K34: 2 - High | L34: Sorawich (Outsource) Tantijitjaru | N34: New
A35: 30 | B35: TM | C35: BUG 71890 | D35: 46266 | E35: [TM - Leave] นามสกุลไม่ตรงกัน | K35: 4 - Low | L35: Sorawich (Outsource) Tantijitjaru | N35: New
A36: 31 | B36: TM | C36: BUG 71891 | D36: 46266 | E36: [TM - Leave] ไฟล์ที่อัพโหลดไปเป็นภาษาอ่านไม่ออก | K36: 4 - Low | L36: Sorawich (Outsource) Tantijitjaru | N36: New
A37: 32 | B37: TM | C37: BUG 71893 | D37: 46266 | E37: [TM - Leave] ลาซ้ำวันเดิมที่เคยลาแต่ต่างเวลากัน | K37: 3 - Medium | L37: Sorawich (Outsource) Tantijitjaru | N37: New
A38: 33 | B38: BE | C38: BUG 71907 | D38: 46266 | E38: [BE-Plan] Wording in Download Sample CSV file do not match specification | K38: 4 - Low | L38: Supawit (Outsource) Janngam | M38: 46276 | N38: New
A39: 34 | B39: BE | C39: BUG 71910 | D39: 46266 | E39: [BE-Plan] Column sequence in Validate & Preview table does not match specification | K39: 4 - Low | L39: Supawit (Outsource) Janngam | M39: 46276 | N39: New
A40: 35 | B40: BE | C40: BUG 71912 | D40: 46266 | E40: [BE-Plan] Validate & Preview displays incorrect Special Claim Condition and Condition values | K40: 3 - Medium | L40: Supawit (Outsource) Janngam | M40: 46269 | N40: New
A41: 36 | B41: BE | C41: BUG 71913 | D41: 46266 | E41: [BE-Plan] Rows per page in Validate & Preview table does not display the selected number of rows | K41: 4 - Low | L41: Supawit (Outsource) Janngam | M41: 46276 | N41: New
A42: 37 | B42: EC | C42: BUG 71932 | D42: 46062 | E42: [EC] Event Reason Dropdown Shows Incorrect Options | K42: 3 - Medium | L42: Thanakorn Sirikulpan | N42: New
A43: 38 | B43: EC | C43: BUG 71983 | D43: 46062 | E43: [EC-Hiring]E ditable fields should not be displayed with a disabled/grey background | K43: 4 - Low | L43: Thanakorn Sirikulpan | N43: New
A44: 39 | B44: EC | C44: BUG 71911 | D44: 46062 | E44: [EC-Hiring] หลัง Session Timeout และ Login เข้าสู่ระบบอีกครั้ง ที่ Tab Draft Form ไม่แสดงข้อมูลรายการ Save Draft | K44: 3 - Medium | L44: Thanakorn Sirikulpan | N44: New
A45: 40 | B45: EC | C45: BUG 71932 | D45: 46062 | E45: [EC-Hiring] ค้นหาด้วย Employee Name แล้วระบบแสดงผลการค้นหาไม่ถูกต้อง | K45: 2 - High | L45: Thanakorn Sirikulpan | N45: New
A46: 41 | B46: EC | C46: BUG 71997 | D46: 46062 | E46: [EC-Hiring] upload file แล้วกด Save Draft ระบบแสดงแจ้งเตือน เมื่อกด Save Draft อีกครั้งระบบไม่แจ้งเตือน แต่แสดงรายการไฟล์ไม่ถูกต้อง | K46: 2 - High | L46: Thanakorn Sirikulpan | N46: New
A47: 42 | B47: BE | C47: BUG 72000 | D47: 46267 | E47: [BE-Plan] Effective End Date resets to 31 Dec 9999 in Insert plan | K47: 2 - High | L47: Panupong (Outsource) Jaengaks | M47: 46269 | N47: New | P47: Block PL_08_20 - 22
A48: 43 | B48: BE | C48: BUG 72002 | D48: 46267 | E48: [BE-Plan] Bulk import cannot proceed to step 2 when using the previously uploaded file | K48: 4 - Low | L48: Supawit (Outsource) Janngam | M48: 46276 | N48: New
A49: 44 | B49: EC | C49: BUG 72003 | D49: 46062 | E49: [EC-Hiring] District (เขต/อำเภอ) Dropdown Options are not available in contact information | K49: 1 - Critical | L49: Thanakorn Sirikulpan | N49: New
A50: 45 | B50: EC | C50: BUG 72004 | D50: 46062 | E50: [EC-Hiring] รูปแบบค่าที่แสดงในฟิลด์ 'Employee Group' ไม่ถูกต้อง | K50: 3 - Medium | L50: Thanakorn Sirikulpan | N50: New
A51: 46 | B51: EC | C51: BUG 72009 | D51: 46062 | E51: [EC-Hiring] Entered Data is lost when changing the language | K51: 2 - High | L51: Thanakorn Sirikulpan | N51: New
A52: 47 | B52: EC | C52: BUG 72008 | D52: 46062 | E52: [EC-Hiring] กรอกข้อมูลเพิ่มพนักงานใหม่ครบถ้วน กดปุ่ม Submit แล้วระบบแสดง popup 'Failed to submit new hire to server. Please try again.' | K52: 1 - Critical | L52: Thanakorn Sirikulpan | N52: New
A53: 48 | B53: EC | C53: BUG 72011 | D53: 46062 | E53: [EC-Hiring] Section requires two clicks to expand when there is no previous data | K53: 4 - Low | L53: Thanakorn Sirikulpan | N53: New
A54: 49 | B54: EC | C54: BUG 72016 | D54: 46062 | E54: EC-Hiring][Keyin] Nationality dropdown shows incorrect search results | K54: 4 - Low | L54: Thanakorn Sirikulpan | N54: New
A55: 50 | B55: EC | C55: BUG 72020 | D55: 46062 | E55: [EC-Hiring][Keyin] Entered information is cleared after navigating back to the previous page | K55: 2 - High | L55: Thanakorn Sirikulpan | N55: New
A56: 51 | B56: BE | C56: BUG 72027 | D56: 46267 | E56: [BE-Plan] Uploaded by displays Employee ID instead of Email Address | K56: 4 - Low | L56: Supawit (Outsource) Janngam | M56: 46276 | N56: New
A57: 52 | B57: BE | C57: BUG 72030 | D57: 46267 | E57: [BE-Plan] Import Job Monitor displays only the latest 15 records | K57: 3 - Medium | L57: Supawit (Outsource) Janngam | M57: 46269 | N57: New
A58: 53 | B58: BE | C58: BUG 72033 | D58: 46267 | E58: [BE-Plan] Incorrect validation error and UI text for Import file exceeding 5,000 records or 5 MB | K58: 4 - Low | L58: Supawit (Outsource) Janngam | M58: 46276 | N58: New
A59: 54 | B59: BE | C59: BUG 72037 | D59: 46267 | E59: [BE-Plan] Validate & Preview displays inccorect operator and does not math the import data | K59: 2 - High | L59: Supawit (Outsource) Janngam | M59: 46269 | N59: New
A60: 55 | B60: EC | C60: BUG 72038 | D60: 46062 | E60: [EC-Hiring][Keyin] User can submit information without filling in mandatory fields | K60: 3 - Medium | L60: Thanakorn Sirikulpan | M60: 46269 | N60: New
A61: 56 | B61: EC | C61: BUG 72036 | D61: 46062 | E61: [EC-Hiring][Keyin] รายการ save draft ระบบไม่แสดงข้อความ validate field 'National ID / Tax ID' | K61: 3 - Medium | L61: Thanakorn Sirikulpan | N61: New
A62: 57 | B62: EC | C62: BUG 72041 | D62: 46062 | E62: [EC-Hiring][Keyin] ระบบแสดงข้อความแจ้งเตือนฟิลด์ 'เลขประจำตัวประชาชน/เลขบัตร' ซ้ำ | K62: 3 - Medium | L62: Thanakorn Sirikulpan | N62: New
A63: 58 | B63: EC | C63: BUG 72042 | D63: 46062 | E63: [EC-Hiring][Keyin] หลัง Submit New Employee สำเร็จ Supervisor ไม่ได้รับ Email Notification | K63: 2 - High | L63: Thanakorn Sirikulpan | M63: 46269 | N63: New
A64: 38 | B64: EC | C64: BUG 72046 | D64: 46062 | E64: [EC-Hiring][Keyin] Employee Data shows incorrect details after submitting employee information | K64: 2 - High | L64: Thanakorn Sirikulpan | M64: 46269 | N64: New
A65: 60 | B65: BE | C65: BUG 72048 | D65: 46267 | E65: [BE-Plan] Can proceed to Step 2 when CSV column sequence or wording does not match the Template | K65: 3 - Medium | L65: Supawit (Outsource) Janngam | M65: 46269 | N65: New
A66: 61 | B66: BE | C66: BUG 72049 | D66: 46267 | E66: [BE-Plan] Can proceed to Step 2 without CSV Header | K66: 3 - Medium | L66: Supawit (Outsource) Janngam | M66: 46269 | N66: New
A67: 62 | B67: EC | C67: ฺBUG 72050 | D67: 46062 | E67: [EC-Hiring][Keyin] ไม่แสดงค่าใน Dropdownlist 'Supervisor ID' | K67: 1 - Critical | L67: Thanakorn Sirikulpan | N67: New
A68: 62 | B68: EC | C68: ฺBUG 72051 | D68: 46062 | E68: [EC-Hiring][Keyin] Address country does not default to Thailand | K68: 4 - Low | L68: Thanakorn Sirikulpan | N68: New
A69: 64
A70: 65
A71: 66
A72: 67
A73: 68
A74: 69
A75: 70
A76: 71
A77: 72
A78: 73
A79: 74
A80: 75
A81: 74 | O81: =IF(#REF!="","",#REF!) -> #REF!
A82: 75 | O82: =IF(#REF!="","",#REF!) -> #REF!
A83: 76 | O83: =IF(#REF!="","",#REF!) -> #REF!
A84: 77 | O84: =IF(#REF!="","",#REF!) -> #REF!
A85: 78 | O85: =IF(#REF!="","",#REF!) -> #REF!
A86: 79 | O86: =IF(#REF!="","",#REF!) -> #REF!
A87: 80 | O87: =IF(#REF!="","",#REF!) -> #REF!
A88: 81 | O88: =IF(#REF!="","",#REF!) -> #REF!
A89: 82 | O89: =IF(#REF!="","",#REF!) -> #REF!
A90: 83 | O90: =IF(#REF!="","",#REF!) -> #REF!
A91: 84 | O91: =IF(#REF!="","",#REF!) -> #REF!
A92: 85 | O92: =IF(#REF!="","",#REF!) -> #REF!
... A107: 100 | O107: =IF(#REF!="","",#REF!) -> #REF!

Sheet Board Track
A1: Dashboard – Test Progress by Module
A2: Module | B2: QA Owner | C2: Total Case | D2: Pending deploy | E2: Pending confirm | F2: Ready to test | G2: Testing | H2: Passed | I2: Failed | J2: Blocked | K2: Re-Testing | L2: Re-Test Passed | M2: Re-Test Failed | N2: Total Progress | O2: %Progress | P2: %Passed
A3: EC – Employee Central | B3: Petcharut | C3: 250 | D3: =COUNTIF(EC!$M:$M,"Pending deploy") -> 0 | E3: =COUNTIF(EC!$M:$M,"Pending confirm") -> 0 | F3: =COUNTIF(EC!$M:$M,"Ready to test") -> 0 | G3: =COUNTIF(EC!$M:$M,"Testing") -> 3 | H3: =COUNTIF(EC!$M:$M,"Passed") -> 8 | I3: =COUNTIF(EC!$M:$M,"Failed") -> 7 | J3: =COUNTIF(EC!$M:$M,"Blocked") -> 2 | K3: =COUNTIF(EC!$M:$M,"Re-Testing") -> 0 | L3: =COUNTIF(EC!$M:$M,"Re-Test Passed") -> 0 | M3: =COUNTIF(EC!$M:$M,"Re-Test Failed") -> 0 | N3: =SUM(G3:M3) -> 20 | O3: =SUM(G3:M3)/C3 -> 0.08
A4: BE – Benefits | B4: Chutiman | C4: =SUM(D4:M4) -> 431 | D4: =COUNTIF(BE!$M:$M,"Pending deploy") -> 4 | E4: =COUNTIF(BE!$M:$M,"Pending confirm") -> 4 | F4: =COUNTIF(BE!$M:$M,"Ready to test") -> 228 | G4: =COUNTIF(BE!$M:$M,"Testing") -> 0 | H4: =COUNTIF(BE!$M:$M,"Passed") -> 139 | I4: =COUNTIF(BE!$M:$M,"Failed") -> 40 | J4: =COUNTIF(BE!$M:$M,"Blocked") -> 6 | K4: =COUNTIF(BE!$M:$M,"Re-Testing") -> 0 | L4: =COUNTIF(BE!$M:$M,"Re-Test Passed") -> 10 | M4: =COUNTIF(BE!$M:$M,"Re-Test Failed") -> 0 | N4: =SUM(G4:M4) -> 195 | O4: =SUM(G4:M4)/C4 -> 0.45243619 | P4: =SUM(H4,L4)/C4 -> 0.34570766
A5: TM – Time Management | B5: Siriya Hacha
A6: PY – Payroll | B6: Pongsakorn
A7: TOTAL

Sheet EC
A1: No | B1: Category | C1: Scenario ID | D1: Test Scenario | E1: Test Case ID | F1: Positive/Negative | G1: Priority | H1: Test Case | I1: Test Data | J1: Menu | K1: Test Script / Steps | L1: Expected Output | M1: Test Status | N1: Test Date | O1: Test by | P1: Bug ticket | Q1: Note | R1: Actual Result Image
A2: 1 | B2: Hiring | C2: E2E-01 | D2: Hiring | Keyin - Success | New Hire | Hire Date = Start of Month | Age < 60 | Male | TH | A - Permanent | E2: HIR-EC-001 | F2: Positive | G2: High | H2: ตรวจสอบการจ้างพนักงานใหม่แบบ Key-in สำเร็จ กรณีวันเริ่มงานต้นเดือน อายุ < 60 ปี สัญชาติไทย และเป็นพนักงานประจำ | I2: - Entry Route = Keyin เงื่อนไขของเคสนี้ - Event Reason = New Hire - Hire Date = 01 Sep 2027 - Date of Birth = Age < 60 - Gender = Male - Nationality = Thai - Province = กรุงเทพมหานคร - District = เลือกเขตที่อยู่ในกรุงเทพมหานคร - Sub-District = เลือกแขวงที่อยู่ใน District ที่เลือก - Postal Code = ตาม Sub-District ที่เลือก - Employee Group = A - Permanent - DVT Project = null - Special benefit group flag = No ค่าที่ต้องคีย์ ชุดข้อมูลจากถัง SIT ตรวจสอบเมื่อ 28 ส.ค. 2026 ชุดข้อมูล TD-01 - Business Group = CRC - Business Unit = CDG (10000075) Policy Profile = CDS - Company = C001 - Position = 40106337 Job Code = MKB12.12 - Department = 30042174 Branch = T153_1733 SSO Location = T153 - Division = 20000079 Cost Center = C00132653 Work Location = 50000127 - Work Schedule = D05H0830 Holiday Calendar = 01 - Personnel Grade (PG) = 10 Employee Sub Group ที่ต้องคีย์ = 10 - ตารางกำหนด Time Status = 01 O.T. Flag = yes สิทธิ์ลาพักผ่อนปีแรก = 6 วัน เงื่อนไขเฉพาะของเคสนี้ - Business Unit = CDG (10000075) Policy Profile = CDS ใช้แทน CDS ที่เคยระบุ ดู CF-SIT-19 - Employee Group = A - Permanent Employee Sub Group = 10 - รายละเอียดเต็มดูชีท Hiring Test Data หมายเหตุ - ดราฟต์เดิมระบุ Department = 30001142 ใช้ 30042174 ตามชุดข้อมูลจริงในถัง SIT - ดราฟต์เดิมระบุ Business Unit = CDS ใช้ CDG / CDG ตามชุดข้อมูลจริงในถัง SIT CDS ปิดใช้งานตั้งแต่ 1 ต.ค. 2024 ตามไฟล์ FO และไม่มี Position ในถัง SIT - ดราฟต์เดิมระบุ Employee Sub Group = 07 ใช้ 10 ตามชุดข้อมูลจริงในถัง SIT - ดราฟต์เดิมระบุ Work Schedule = D05H0800_01 ใช้ D05H0830 ตามชุดข้อมูลจริงในถัง SIT | J2: EC > Hire & Onboard (New Hire) | K2: 1. Login ด้วย <HR_ADMIN_ACCOUNT> - ไปที่ EC > New Hire (Manual Key-in) 2. กรอกข้อมูล Identity ตาม Test Data - กรอก Salutation, First Name / Last Name (TH และ EN), Date of Birth, National ID / Tax ID, Hire Date และ Event Reason 3. กรอกและตรวจสอบ Home Address - เลือก Province = กรุงเทพมหานคร และตรวจสอบรายการ District - เลือก District และตรวจสอบรายการ Sub-District - เลือก Sub-District และตรวจสอบ Postal Code - เปลี่ยน Province และตรวจสอบว่า District / Sub-District / Postal Code เดิมถูกเคลียร์ - เลือก Province / District ใหม่ - เปลี่ยน District โดยคง Province เดิม และตรวจสอบว่า Sub-District / Postal Code เดิมถูกเคลียร์ - เลือก Address ที่ถูกต้องให้ครบถ้วน 4. กรอกข้อมูล Position & Organization - เลือก Department / Position ตาม Test Data - ตรวจสอบค่าที่ระบบดึงจาก Department - ตรวจสอบค่าที่ระบบดึงจาก Position - ตรวจสอบ Minimum / Maximum Job Grade ที่ได้จาก Job Code - ตรวจสอบว่า Job Grade อยู่ในช่วงที่กำหนด - ตรวจสอบ Payroll Frequency ที่ได้จาก Pay Group 5. ตรวจสอบ Time Management Status และ O.T. Flag - ตรวจสอบว่าทั้งสองฟิลด์เป็น Read-only - ตรวจสอบค่าที่ระบบ Auto-Derive เทียบกับ Rule Table ตาม Business Unit / Employee Group / Employee Subgroup 6. กรอก Compensation Information และ Payment Information ให้ครบถ้วน 7. กด Submit เพื่อสร้างพนักงานใหม่ 8. ตรวจสอบ Employee Profile ใน EC - ค้นหาด้วย Employee ID - ตรวจสอบ Employee ID / Status / Hire Date / Event Reason / Employee Group / Employee Subgroup - ตรวจสอบ Home Address - ตรวจสอบ Probation Information - ตรวจสอบ Time Management Status / O.T. Flag - ตรวจสอบค่าที่ระบบดึงจาก Master/ทะเบียน | L2: EC - ระบบสร้าง Employee ID เป็นตัวเลข 8 หลัก โดยหลักแรกเป็น 2 - Employee Status = Active - Hire Date = Today ตามค่าที่กรอก - Event Reason = New Hire - Employee Group = A - Permanent - ระบบบันทึกและส่งต่อ Employee Sub Group เป็นรหัสสองหลักตามค่าที่คีย์ในชุดข้อมูล ไม่ตัดศูนย์นำหน้า เช่น 07 ต้องไม่ถูกเก็บเป็น 7 (Q&A ข้อ 23) - ระบบกรอง District ตาม Province ที่เลือก - ระบบกรอง Sub-District ตาม District ที่เลือก - เมื่อเลือก Sub-District ระบบแสดง Postal Code อัตโนมัติ - เมื่อเปลี่ยน Province ระบบเคลียร์ District / Sub-District / Postal Code เดิม - เมื่อเปลี่ยน District ระบบเคลียร์ Sub-District / Postal Code เดิม - ระบบบันทึก Home Address ตามข้อมูลที่ระบุ - Probation Exemption = No - ระบบเริ่มนับ Probation Day 1 ที่ Hire Date - ระบบ Auto-Derive Time Management Status = 01 - Clocking และ O.T. Flag = Yes ตาม Rule Table - Time Management Status และ O.T. Flag เป็น Read-only และ HR ไม่สามารถแก้ไขเองได้ - ระบบดึงข้อมูลจาก Department ได้แก่ Cost Center / SSO Location / Work Location / Store/Branch Location / Policy Profile / Holiday Calendar / Division - ระบบดึงข้อมูลจาก Position ได้แก่ Company / Job Code / Employee Group / Employee Subgroup / Work Schedule - ระบบดึง Minimum / Maximum Job Grade จาก Job Code และ Job Grade ต้องอยู่ในช่วงที่กำหนด - ระบบดึง Payroll Frequency จาก Pay Group - Probationary Period End Date = ? CF-HIR-08 OQ-HIR-50 - สูตร/เงื่อนไข Rule Table = ? OQ-HIR-13 จุดที่ยังไม่มีคำตอบในเคสนี้ ให้รันจริงแล้วบันทึกค่าที่ระบบแสดงลงช่อง Actual Result Image และช่อง Note เพื่อใช้เป็นคำตอบ แล้วส่งให้ BA หรือ SA ยืนยัน หมายเลขคำถามที่ต้องเก็บคำตอบระหว่างรัน CF-HIR-08, OQ-HIR-50, OQ-HIR-13 | M2: Failed | N2: 46267 | O2: QA-Thitiya | P2: #71932 #71983 #72009 #72003 #72011 #72016 #72020 #72038 #72046 #72051 | Q2: ตัดจากเคส E2E-01 ไฟล์ HR_SIT_E2E_V.0.1 (28).xlsx ชีท E2E All module โมดูลที่เคสเต็มเกี่ยวข้อง EC / BE / TM / PY / Notification ยกไปรอบเชื่อมโมดูล ผลที่คาดหวังฝั่ง Notification / TM / Menu Clock in/out / Menu OT Request / Menu Timesheet / BE / PY / ผลข้ามโมดูล ตรวจหลัง Submit สำเร็จแล้ว ยกไปรอบเชื่อมโมดูล ขั้นตอน ตรวจสอบ Notification หลังสร้างพนักงานใหม่ / ตรวจสอบข้อมูลใน BE / TM / PY เคสนี้มีจุดที่ยังไม่มีคำตอบ 3 จุด ไม่ต้องรอคำตอบก่อนรัน ให้รันเก็บค่าที่ระบบแสดงจริงแล้วแจ้ง BA หรือ SA ยืนยันหลังรัน
A3: 2 | B3: Hiring | C3: E2E-02 | D3: Hiring | Keyin - Success | New Hire | Hire Date = Mid Month | Age > 60 | Female | TH | A - Permanent | Save Draft & Submit | E3: HIR-EC-002 | F3: Positive | G3: High | H3: ตรวจสอบการจ้างพนักงานใหม่แบบ Key-in สำเร็จ กรณีวันเริ่มงานกลางเดือน อายุ > 60 ปี เพศหญิง สัญชาติไทย พนักงานประจำ และบันทึกร่างก่อน Submit | I3: - Entry Route = Keyin เงื่อนไขของเคสนี้ - Event Reason = New hire - Hire Date = 15 Sep 2027 - Date of Birth = Age > 60 - Gender = Female - Nationality = Thai - Employee Group = A - Permanent - DVT Project = null - Hire date = 15 Sep 2027 - Special benefit group flag = No - Branch code = TA57_1001 ค่าที่ต้องคีย์ ชุดข้อมูลจากถัง SIT ตรวจสอบเมื่อ 28 ส.ค. 2026 ชุดข้อมูล TD-01 - Business Group = CRC - Business Unit = CDG (10000075) Policy Profile = CDS - Company = C001 - Position = 40106337 Job Code = MKB12.12 - Department = 30042174 Branch = T153_1733 SSO Location = T153 - Division = 20000079 Cost Center = C00132653 Work Location = 50000127 - Work Schedule = D05H0830 Holiday Calendar = 01 - Personnel Grade (PG) = 10 Employee Sub Group ที่ต้องคีย์ = 10 - ตารางกำหนด Time Status = 01 O.T. Flag = yes สิทธิ์ลาพักผ่อนปีแรก = 6 วัน เงื่อนไขเฉพาะของเคสนี้ - Work Schedule = D05H0830 แก้จากเดิมที่ระบุ D05H0800_02 ซึ่งไม่มีในตาราง ดู CF-SIT-11 - Branch code = T153_1733 แก้จากเดิมที่ระบุ TA57_1001 ซึ่งอยู่นอกขอบเขต ดู CF-SIT-10 - รายละเอียดเต็มดูชีท Hiring Test Data หมายเหตุ - ดราฟต์เดิมระบุ Business Unit = CDS ใช้ CDG ตามชุดข้อมูลจริงในถัง SIT CDS ปิดใช้งานตั้งแต่ 1 ต.ค. 2024 ตามไฟล์ FO และไม่มี Position ในถัง SIT - ดราฟต์เดิมระบุ Holiday Calendar = 02 ใช้ 01 / 01 ตามชุดข้อมูลจริงในถัง SIT - ดราฟต์เดิมระบุ Work Schedule = D05H0800_02 ใช้ D05H0830 / D05H0830 ตามชุดข้อมูลจริงในถัง SIT | J3: EC > Hire & Onboard (New Hire) | K3: 1. Login ด้วย <HR_ADMIN_ACCOUNT> - ไปที่ EC > New Hire (Manual Key-in) 2. กรอกข้อมูล New Hire ตาม Test Data - กรอกข้อมูล Identity ตามข้อมูลที่กำหนด - กำหนด Employee Group = A - Permanent - กรอกข้อมูลบางส่วนให้เพียงพอสำหรับ Save Draft โดยยังไม่ต้องกรอกข้อมูลทั้งหมดให้ครบ 3. กด Save Draft ก่อน Submit - ออกจากรายการ New Hire หลังบันทึกร่างสำเร็จ - ตรวจสอบว่ายังไม่มี Employee ID ถูกสร้าง 4. กลับมาเปิด Draft เดิม - ตรวจสอบข้อมูลที่กรอกไว้ก่อน Save Draft - ตรวจสอบว่าค่าเดิมยังอยู่ครบ - กรอกข้อมูล Mandatory ที่เหลือให้ครบถ้วนเพื่อให้สามารถ Submit ได้ 5. กด Submit เพื่อสร้างพนักงานใหม่ 6. ตรวจสอบ Employee Profile ใน EC - ค้นหาพนักงานที่สร้างใหม่ด้วย Employee ID - ตรวจสอบ Hire Date / Date of Birth / Employee Group - ตรวจสอบว่าพนักงานมี Age > 60 ณ Hire Date - ตรวจสอบว่ารายการ Draft ที่ Submit สำเร็จแล้วไม่ค้างอยู่ในรายการ Draft | L3: EC - ระบบบันทึกใบจ้างที่ยังกรอกไม่ครบเป็น Draft ได้สำเร็จ - ระบบเปิด Draft เดิมกลับมาทำต่อได้ และค่าที่กรอกไว้ก่อนหน้ายังอยู่ครบ - ระบบไม่สร้าง Employee ID จากการ Save Draft - ระบบสร้างพนักงานหลัง Submit สำเร็จ - Hire Date = Today (กลางปี) - Employee Group = A - Permanent - ระบบสร้างพนักงาน Age > 60 ได้ โดยไม่มีการ Block ที่ EC - ใบร่างที่ Submit สำเร็จแล้วหายจากรายการ Draft เพื่อป้องกันการนำรายการเดิมกลับมาทำซ้ำ - สถานะของใบร่าง = DRAFT โดยคำที่ระบบเก็บจริง = ? OQ-HIR-91 - สถานะของใบร่างหลัง Submit = COMPLETED โดยคำที่ระบบเก็บจริง = ? OQ-HIR-91 - ระบบอนุญาตให้ Save Draft เมื่อกรอกชื่อและนามสกุลแล้ว (Q&A ข้อ 28) จุดที่ยังไม่มีคำตอบในเคสนี้ ให้รันจริงแล้วบันทึกค่าที่ระบบแสดงลงช่อง Actual Result Image และช่อง Note เพื่อใช้เป็นคำตอบ แล้วส่งให้ BA หรือ SA ยืนยัน หมายเลขคำถามที่ต้องเก็บคำตอบระหว่างรัน OQ-HIR-91 | M3: Failed | N3: 46266 | O3: QA-Wannaphon | P3: #71875 #71887 | Q3: ตัดจากเคส E2E-02 ไฟล์ HR_SIT_E2E_V.0.1 (28).xlsx ชีท E2E All module โมดูลที่เคสเต็มเกี่ยวข้อง EC / BE / TM / PY / Notification ยกไปรอบเชื่อมโมดูล ผลที่คาดหวังฝั่ง Notification / TM / Menu Clock in/out / Menu OT Request / Menu Timesheet / BE / PY ยกไปรอบเชื่อมโมดูล ขั้นตอน ตรวจสอบ Notification หลังสร้างพนักงานใหม่ / ตรวจสอบข้อมูลใน BE / TM / PY หลัง Submit สำเร็จ เคสนี้มีจุดที่ยังไม่มีคำตอบ 1 จุด ไม่ต้องรอคำตอบก่อนรัน ให้รันเก็บค่าที่ระบบแสดงจริงแล้วแจ้ง BA หรือ SA ยืนยันหลังรัน
A4: 3 | B4: Hiring | C4: E2E-03 | D4: Hiring | Keyin - Success | New Hire | Hire Date > Today | Age < 60 | Female | TH | Special Benefit Group = Yes | A - Permanent | E4: HIR-EC-003 | F4: Positive | G4: High | H4: ตรวจสอบการจ้างพนักงานใหม่แบบ Key-in สำเร็จ กรณีวันเริ่มงานในอนาคต อายุ < 60 ปี เพศหญิง สัญชาติไทย พนักงานประจำ และอยู่ใน Special Benefit Group | I4: - Entry Route = Keyin เงื่อนไขของเคสนี้ - Event Reason = New hire - Hire Date = 01 Jan 2027 - Date of Birth = Age < 60 - Gender = Female - Nationality = Thai - Special Benefit Group = Yes - Employee Group = A - Permanent - Copy Address from Employee = Yes / No - Country / Province / District / Sub-District / Postal Code = ใช้สำหรับตรวจ Required เมื่อเลือก No - Building / Floor / Village / Moo / Lane = ใช้สำหรับตรวจ Optional Field - DVT Project = null - Employee group = A - permanent - Special benefit group flag = Yes ค่าที่ต้องคีย์ ชุดข้อมูลจากถัง SIT ตรวจสอบเมื่อ 28 ส.ค. 2026 ชุดข้อมูล TD-01 - Business Group = CRC - Business Unit = CDG (10000075) Policy Profile = CDS - Company = C001 - Position = 40106337 Job Code = MKB12.12 - Department = 30042174 Branch = T153_1733 SSO Location = T153 - Division = 20000079 Cost Center = C00132653 Work Location = 50000127 - Work Schedule = D05H0830 Holiday Calendar = 01 - Personnel Grade (PG) = 10 Employee Sub Group ที่ต้องคีย์ = 10 - ตารางกำหนด Time Status = 01 O.T. Flag = yes สิทธิ์ลาพักผ่อนปีแรก = 6 วัน เงื่อนไขเฉพาะของเคสนี้ - Special Benefit Group = Yes - รายละเอียดเต็มดูชีท Hiring Test Data หมายเหตุ - ดราฟต์เดิมระบุ Business Unit = CDS ใช้ CDG ตามชุดข้อมูลจริงในถัง SIT CDS ปิดใช้งานตั้งแต่ 1 ต.ค. 2024 ตามไฟล์ FO และไม่มี Position ในถัง SIT | J4: EC > Hire & Onboard (New Hire) | K4: 1. Login ด้วย <HR_ADMIN_ACCOUNT> - ไปที่ EC > New Hire (Manual Key-in) 2. กรอกข้อมูล Identity ตาม Test Data - กำหนด Hire Date > Today - กรอกข้อมูลบุคคลตาม Test Data 3. กรอกข้อมูล Dependent / Emergency Contact - เพิ่ม Dependent จำนวน 1 คน - เลือก Copy Address from Employee = Yes และตรวจสอบข้อมูล Address / ข้อความ “The address will be copied from the employee.” - เปลี่ยนเป็น Copy Address from Employee = No - ตรวจสอบว่า Country / Province / District / Sub-District / Postal Code เป็น Required - ตรวจสอบว่า Building / Floor / Village / Moo / Lane แสดงแต่ไม่เป็น Required - ทำซ้ำเงื่อนไขเดียวกันสำหรับ Emergency Contact 4. กรอกข้อมูลการจ้างงานที่จำเป็น - กำหนด Special Benefit Group = Yes - กำหนด Employee Group = A - Permanent - กรอกข้อมูล Mandatory อื่นให้ครบถ้วนเพื่อให้สามารถ Submit ได้ 5. กด Submit เพื่อสร้างพนักงานใหม่ 6. ตรวจสอบ Employee Profile ใน EC - ค้นหาพนักงานด้วย Employee ID - ตรวจสอบ Hire Date / Employee Group / สถานะพนักงาน - ตรวจสอบ Special Benefit Group = Yes - ตรวจสอบข้อมูล Dependent / Emergency Contact และ Address ที่บันทึก | L4: EC - ระบบสร้าง Employee Record สำหรับ Hire Date > Today ได้ทันทีหลัง Submit โดยไม่ต้องรอถึง Hire Date - Hire Date = วันที่กรอก ซึ่งเป็นวันในอนาคต - Employee Group = A - Permanent - เมื่อ Copy Address from Employee = Yes ระบบใช้ข้อมูล Address ของ Employee และแสดงข้อความ “The address will be copied from the employee.” - เมื่อ Copy Address from Employee = No ระบบกำหนด Country / Province / District / Sub-District / Postal Code เป็น Required - ระบบแสดง Building / Floor / Village / Moo / Lane แต่ไม่กำหนดเป็น Required - พฤติกรรมเดียวกันทั้ง Dependent และ Emergency Contact - ระบบบันทึกข้อมูล Dependent / Emergency Contact ตามข้อมูลที่ระบุหลัง Submit สำเร็จ - ระบบบันทึก Special Benefit Group = Yes ได้ - Employee Status = Active ทันทีหลัง Submit แม้ Hire Date ยังไม่ถึง (Q&A ข้อ 32) | M4: Failed | N4: 46267 | O4: QA-Wannaphon | P4: #72008 | Q4: ตัดจากเคส E2E-03 ไฟล์ HR_SIT_E2E_V.0.1 (28).xlsx ชีท E2E All module โมดูลที่เคสเต็มเกี่ยวข้อง EC / TM / BE / PY / BE : Special Benefit Group = Yes ยกไปรอบเชื่อมโมดูล ผลที่คาดหวังฝั่ง Notification / TM / BE / PY ยกไปรอบเชื่อมโมดูล ขั้นตอน ตรวจสอบข้อมูลใน BE
A5: 4 | B5: Hiring | C5: E2E-04 | D5: Hiring | Keyin - Success | New Hire | Hire Date = Today | Age < 60 | Male | TH | A - Permanent | National ID Duplicate in Different BU | E5: HIR-EC-004 | F5: Positive | G5: High | H5: ตรวจสอบการจ้างพนักงานใหม่แบบ Key-in สำเร็จ กรณีวันเริ่มงานวันนี้ อายุ < 60 ปี เพศชาย สัญชาติไทย พนักงานประจำ และ National ID ซ้ำกับพนักงานต่าง BU | I5: - Entry Route = Keyin เงื่อนไขของเคสนี้ - Event Reason = New Hire - Hire Date = Today - Date of Birth = Age < 60 - Gender = Male - Nationality = Thai - National ID = ใช้ National ID ที่ซ้ำกับพนักงาน Active ที่มีอยู่แล้วใน Different BU และไม่ใช่กรณี Rehire - Thailand Format = N-NNNN-NNNNN-NN-N - Vietnam Format = NNNNNNNNN - Invalid National ID / Tax-ID = จำนวนหลักไม่ครบ - Employee Group = A - Permanent - DVT Project = null - Employee group = A - permanent - Special benefit group flag = No ค่าที่ต้องคีย์ ชุดข้อมูลจากถัง SIT ตรวจสอบเมื่อ 28 ส.ค. 2026 ชุดข้อมูล TD-01 - Business Group = CRC - Business Unit = CDG (10000075) Policy Profile = CDS - Company = C001 - Position = 40106337 Job Code = MKB12.12 - Department = 30042174 Branch = T153_1733 SSO Location = T153 - Division = 20000079 Cost Center = C00132653 Work Location = 50000127 - Work Schedule = D05H0830 Holiday Calendar = 01 - Personnel Grade (PG) = 10 Employee Sub Group ที่ต้องคีย์ = 10 - ตารางกำหนด Time Status = 01 O.T. Flag = yes สิทธิ์ลาพักผ่อนปีแรก = 6 วัน ชุดข้อมูล TD-42 - Business Unit = CFR (10000003) Policy Profile = CFR - Company = C004 - Position = 40007752 Job Code = STB10.12 - Department = 30002647 Branch = T224_1804 SSO Location = T224 - Division = 20001352 Cost Center = C00426100 Work Location = 50000183 - Work Schedule = D06H0800 Holiday Calendar = 03 - Personnel Grade (PG) = 10 Employee Sub Group ที่ต้องคีย์ = 10 เงื่อนไขเฉพาะของเคสนี้ - รอบที่ 1 ใช้ TD-01 Business Unit CDG รอบที่ 2 ใช้ TD-42 Business Unit CFR ด้วยเลขบัตรประชาชนเดียวกัน - รายละเอียดเต็มดูชีท Hiring Test Data หมายเหตุ - ดราฟต์เดิมระบุ Personnel Grade (PG) = 15 ใช้ 10 / 10 ตามชุดข้อมูลจริงในถัง SIT | J5: EC > Hire & Onboard (New Hire) | K5: 1. Login ด้วย <HR_ADMIN_ACCOUNT> - ไปที่ EC > New Hire (Manual Key-in) 2. ตรวจสอบ Duplicate National ID / Tax-ID - กรอก National ID ที่ซ้ำกับพนักงาน Active ที่มีอยู่แล้วใน Different BU และไม่ใช่กรณี Rehire - ตรวจสอบว่าระหว่างกรอก ระบบยังไม่ Validate Duplicate แบบ Real-time 3. ตรวจสอบ Invalid Format ก่อน Duplicate Check - กรอก National ID / Tax-ID ที่จำนวนหลักไม่ครบ - กรอกข้อมูล Mandatory อื่นให้ครบถ้วนเพื่อให้สามารถ Submit ได้ - กด Submit - ตรวจสอบผล Validation - ตรวจสอบว่าระบบ Reject ก่อนเข้าสู่ขั้นตอนตรวจ Duplicate 4. ตรวจสอบ Duplicate ด้วย National ID ที่ Format ถูกต้อง - กรอก National ID ประเทศไทยในรูปแบบ N-NNNN-NNNNN-NN-N โดยใช้ค่าที่ซ้ำกับพนักงาน Active ใน Different BU - กรณีตรวจสอบ Vietnam ให้ใช้รูปแบบ NNNNNNNNN - กำหนด Employee Group = A - Permanent - กรอกข้อมูล Mandatory อื่นให้ครบถ้วนเพื่อให้สามารถ Submit ได้ 5. กด Submit - ตรวจสอบว่าระบบตรวจพบ National ID ซ้ำกับพนักงานที่มีอยู่แล้วใน Different BU - ตรวจสอบ Notice ที่ระบบแสดง - บันทึกข้อความ Notice ที่พบจริง - บันทึกว่าหลังพบ Duplicate ระบบอนุญาตให้ Submit ต่อหรือ Block การ Submit | L5: EC - ระบบตรวจสอบ Duplicate National ID / Tax-ID ตอนกด Submit เท่านั้น และไม่ Validate Duplicate แบบ Real-time ขณะกรอกข้อมูล - ระบบตรวจพบว่า National ID ซ้ำกับพนักงาน Active ที่มีอยู่แล้ว แม้พนักงานเดิมจะอยู่คนละ Business Unit - ระบบแสดง Notice แจ้งว่า National ID / Tax-ID ซ้ำหรือมีอยู่แล้ว - National ID / Tax-ID Format - ระบบรองรับรูปแบบ Thailand = N-NNNN-NNNNN-NN-N - ระบบรองรับรูปแบบ Vietnam = NNNNNNNNN - กรณี National ID / Tax-ID ผิดรูปแบบหรือจำนวนหลักไม่ครบ ระบบ Reject ก่อนเข้าสู่ขั้นตอนตรวจ Duplicate - ข้อความ Notice ที่แน่นอน = ? OQ-HIR-140 - พฤติกรรมหลังพบ Duplicate ว่าระบบอนุญาตให้ Submit ต่อหรือ Block การ Submit = ? OQ-HIR-140 จุดที่ยังไม่มีคำตอบในเคสนี้ ให้รันจริงแล้วบันทึกค่าที่ระบบแสดงลงช่อง Actual Result Image และช่อง Note เพื่อใช้เป็นคำตอบ แล้วส่งให้ BA หรือ SA ยืนยัน หมายเลขคำถามที่ต้องเก็บคำตอบระหว่างรัน OQ-HIR-140 | M5: Cancelled | Q5: ซ้ำกับ 028 ระบุเองว่าเป็นคำตอบทางการของข้อค้างใน E2E-04
A6: 5 | B6: Hiring | C6: E2E-05 | D6: Hiring | Keyin - Success | New Hire | Hire Date = Today | Age < 60 | Female | Non TH | A - Permanent | E6: HIR-EC-005 | F6: Positive | G6: High | H6: ตรวจสอบการจ้างพนักงานใหม่แบบ Key-in สำเร็จ กรณีวันเริ่มงานวันนี้ อายุ < 60 ปี เพศหญิง สัญชาติ Non-TH และเป็นพนักงานประจำ | I6: - Entry Route = Keyin เงื่อนไขของเคสนี้ - Event Reason = New Hire - Hire Date = Today - Date of Birth = Age < 60 - Gender = Female - Nationality / Country = Non-TH และ Non-VN - Passport Number = AB1234567 - Passport Issue Date = 01/02/2021 - Passport Expiry Date = < Current Date - Tax ID = 1234567890123 - Document Type = ? รอตารางค่าจริง - Country = Japan - Document Number = WP2026000123 - Issue Date = 01/03/2025 - Expiry Date = 28/02/2026 - Arrival Date (VISA) = 01/03/2025 - 90-days Report (VISA) = 30/05/2025 - Employee Group = A - Permanent - DVT Project = null - Employee group = A - permanent - Special benefit group flag = No ค่าที่ต้องคีย์ ชุดข้อมูลจากถัง SIT ตรวจสอบเมื่อ 28 ส.ค. 2026 ชุดข้อมูล TD-01 - Business Group = CRC - Business Unit = CDG (10000075) Policy Profile = CDS - Company = C001 - Position = 40106337 Job Code = MKB12.12 - Department = 30042174 Branch = T153_1733 SSO Location = T153 - Division = 20000079 Cost Center = C00132653 Work Location = 50000127 - Work Schedule = D05H0830 Holiday Calendar = 01 - Personnel Grade (PG) = 10 Employee Sub Group ที่ต้องคีย์ = 10 - ตารางกำหนด Time Status = 01 O.T. Flag = yes สิทธิ์ลาพักผ่อนปีแรก = 6 วัน เงื่อนไขเฉพาะของเคสนี้ - Nationality = Non-TH และ Non-VN - รายละเอียดเต็มดูชีท Hiring Test Data หมายเหตุ - ดราฟต์เดิมระบุ Business Unit = CDS ใช้ CDG ตามชุดข้อมูลจริงในถัง SIT CDS ปิดใช้งานตั้งแต่ 1 ต.ค. 2024 ตามไฟล์ FO และไม่มี Position ในถัง SIT | J6: EC > Hire & Onboard (New Hire) | K6: 1. Login ด้วย <HR_ADMIN_ACCOUNT> - ไปที่ EC > New Hire (Manual Key-in) 2. กรอกข้อมูล Identity สำหรับพนักงานต่างชาติ - กำหนด Nationality / Country = Non-TH และ Non-VN - กรอก Passport Number - ตรวจสอบว่า Passport Issue Date และ Passport Expiry Date เป็น Required - กรอก Passport Issue Date และ Passport Expiry Date ตาม Test Data - กรอก Passport / Tax ID แทน National ID 13 หลัก 3. ตรวจสอบ Passport หมดอายุ - กำหนด Passport Expiry Date < Current Date - ตรวจสอบข้อความ “Passport has expired” 4. เพิ่มข้อมูล Work Permit - กรอก Document Type / Country / Document Number / Issue Date / Expiry Date / Arrival Date (VISA) / 90-days Report (VISA) - เพิ่ม Work Permit มากกว่า 1 รายการ - ตรวจสอบว่าระบบรองรับการเพิ่มหลายรายการ 5. กรอกข้อมูลการจ้างงานที่จำเป็น - กำหนด Employee Group = A - Permanent - กรอกข้อมูล Mandatory อื่นให้ครบถ้วนเพื่อให้สามารถ Submit ได้ 6. กด Submit เพื่อสร้างพนักงานใหม่ 7. ตรวจสอบ Employee Profile ใน EC - ค้นหาพนักงานที่สร้างใหม่ด้วย Employee ID - ตรวจสอบ Nationality / Passport / Tax ID - ตรวจสอบข้อมูล Work Permit ทุกรายการ - ตรวจสอบ Arrival Date (VISA) / 90-days Report (VISA) - ตรวจสอบ Employee Group | L6: EC - ระบบรองรับการสร้างพนักงาน Nationality = Non TH - Employee Group = A - Permanent - ระบบให้กรอก Work Permit หรือ Passport แทน National ID 13 หลักได้ - ระบบบันทึก Passport Number / Tax ID / Work Permit ตามข้อมูลที่กรอก - เมื่อกรอก Passport Number ระบบกำหนด Passport Issue Date และ Passport Expiry Date เป็น Required - เมื่อ Passport Expiry Date < Current Date ระบบแสดงข้อความ “Passport has expired” - ระบบรองรับการเพิ่ม Work Permit มากกว่า 1 รายการต่อพนักงาน 1 คน - ระบบบันทึก Document Type / Country / Document Number / Issue Date / Expiry Date / Arrival Date (VISA) / 90-days Report (VISA) ได้ - 90-days Report (VISA) ยังไม่มี Business Rule เพิ่มเติม จึงตรวจเฉพาะว่าสามารถบันทึกค่าตามที่ระบุได้ - พฤติกรรมกรณี Passport หมดอายุว่าเป็น Warning และยัง Submit ได้ หรือ Block การ Submit = ? OQ-HIR-61 - ตารางค่าของ Document Type = ? OQ-HIR-78 - Country ใน Work Permit = Thailand (Q&A ข้อ 33) จุดที่ยังไม่มีคำตอบในเคสนี้ ให้รันจริงแล้วบันทึกค่าที่ระบบแสดงลงช่อง Actual Result Image และช่อง Note เพื่อใช้เป็นคำตอบ แล้วส่งให้ BA หรือ SA ยืนยัน หมายเลขคำถามที่ต้องเก็บคำตอบระหว่างรัน OQ-HIR-61, OQ-HIR-78 | M6: Failed | N6: 46267 | O6: QA-Wannaphon | P6: #72050 | Q6: ตัดจากเคส E2E-05 ไฟล์ HR_SIT_E2E_V.0.1 (28).xlsx ชีท E2E All module โมดูลที่เคสเต็มเกี่ยวข้อง EC / BE / TM / PY / Notification ยกไปรอบเชื่อมโมดูล ผลที่คาดหวังฝั่ง Notification / TM / BE / PY ยกไปรอบเชื่อมโมดูล ขั้นตอน ตรวจสอบผลใน PY เคสนี้มีจุดที่ยังไม่มีคำตอบ 2 จุด ไม่ต้องรอคำตอบก่อนรัน ให้รันเก็บค่าที่ระบบแสดงจริงแล้วแจ้ง BA หรือ SA ยืนยันหลังรัน
A7: 6 | B7: Hiring | C7: E2E-06 | D7: Hiring | Keyin - Success | New Hire | Hire Date = Today | Age = 60 | Male | TH | A - Permanent | E7: HIR-EC-006 | F7: Positive | G7: High | H7: ตรวจสอบการจ้างพนักงานใหม่แบบ Key-in สำเร็จ กรณีวันเริ่มงานวันนี้ อายุ 60 ปี เพศชาย สัญชาติไทย และเป็นพนักงานประจำ | I7: - Entry Route = Keyin เงื่อนไขของเคสนี้ - Event Reason = New hire - Hire Date = Today - Date of Birth = Age = 60 พอดี ณ Hire Date - Gender = Male - Nationality = Thai - Employee Group = A - Permanent - DVT Project = null - Employee group = A - permanent - Special benefit group flag = No ค่าที่ต้องคีย์ ชุดข้อมูลจากถัง SIT ตรวจสอบเมื่อ 28 ส.ค. 2026 ชุดข้อมูล TD-01 - Business Group = CRC - Business Unit = CDG (10000075) Policy Profile = CDS - Company = C001 - Position = 40106337 Job Code = MKB12.12 - Department = 30042174 Branch = T153_1733 SSO Location = T153 - Division = 20000079 Cost Center = C00132653 Work Location = 50000127 - Work Schedule = D05H0830 Holiday Calendar = 01 - Personnel Grade (PG) = 10 Employee Sub Group ที่ต้องคีย์ = 10 - ตารางกำหนด Time Status = 01 O.T. Flag = yes สิทธิ์ลาพักผ่อนปีแรก = 6 วัน เงื่อนไขเฉพาะของเคสนี้ - Date of Birth = อายุครบ 60 ปีพอดี ณ Hire Date - รายละเอียดเต็มดูชีท Hiring Test Data หมายเหตุ - ดราฟต์เดิมระบุ Business Unit = CDS ใช้ CDG ตามชุดข้อมูลจริงในถัง SIT CDS ปิดใช้งานตั้งแต่ 1 ต.ค. 2024 ตามไฟล์ FO และไม่มี Position ในถัง SIT | J7: EC > Hire & Onboard (New Hire) | K7: 1. Login ด้วย <HR_ADMIN_ACCOUNT> - ไปที่ EC > New Hire (Manual Key-in) 2. กรอกข้อมูล New Hire ตาม Test Data - กรอกข้อมูล Identity โดยกำหนด Date of Birth ให้คำนวณแล้ว Age = 60 พอดี ณ Hire Date - กำหนด Employee Group = A - Permanent - กรอกข้อมูล Mandatory อื่นให้ครบถ้วนเพื่อให้สามารถ Submit ได้ 3. กด Submit เพื่อสร้างพนักงานใหม่ 4. ตรวจสอบ Employee Profile ใน EC - ค้นหาพนักงานที่สร้างใหม่ด้วย Employee ID - ตรวจสอบ Date of Birth / Hire Date และอายุของพนักงาน ณ Hire Date - ตรวจสอบ Employee Group | L7: EC - ระบบสร้างพนักงานที่มี Age = 60 พอดี ณ Hire Date ได้ โดยไม่มีการ Block ที่ EC - Date of Birth / Hire Date ที่บันทึกตรงกับข้อมูลที่กรอก และคำนวณได้ Age = 60 พอดี ณ Hire Date - Employee Group = A - Permanent | M7: Cancelled | Q7: อายุ 60 ฝั่ง EC ไม่มีการบล็อก เจตนาจริงคือประกันสังคม (PY) ซ้ำ 024 และ HIR-EC-002 มีอยู่แล้ว: "ระบบสร้างพนักงาน Age > 60 ได้ โดยไม่มีการ Block ที่ EC"
A8: 7 | B8: Hiring | C8: E2E-07 | D8: Hiring | Keyin - Success | New Hire | Hire Date = Today | Age < 60 | Male | TH | B - Expat Outbound | Probation Exemption = Yes | E8: HIR-EC-007 | F8: Positive | G8: High | H8: ตรวจสอบการจ้างพนักงานใหม่แบบ Key-in สำเร็จ กรณีวันเริ่มงานวันนี้ อายุ < 60 ปี เพศชาย สัญชาติไทย กลุ่มพนักงาน Expat Outbound และได้รับยกเว้นทดลองงาน | I8: - Entry Route = Keyin เงื่อนไขของเคสนี้ - Event Reason = New hire - Hire Date = Today - Date of Birth = Age < 60 - Gender = Male - Nationality = Thai - Probation Exemption = Yes - Employee Group = B - Expat Outbound - O.T. Flag = Auto-Derived จาก Rule Table - DVT Project = null - Employee group = B - Expat Outbound - Special benefit group flag = No ค่าที่ต้องคีย์ ชุดข้อมูลจากถัง SIT ตรวจสอบเมื่อ 28 ส.ค. 2026 ชุดข้อมูล TD-01 - Business Group = CRC - Business Unit = CDG (10000075) Policy Profile = CDS - Company = C001 - Position = 40106337 Job Code = MKB12.12 - Department = 30042174 Branch = T153_1733 SSO Location = T153 - Division = 20000079 Cost Center = C00132653 Work Location = 50000127 - Work Schedule = D05H0830 Holiday Calendar = 01 - Personnel Grade (PG) = 10 Employee Sub Group ที่ต้องคีย์ = 10 - ตารางกำหนด Time Status = 01 O.T. Flag = yes สิทธิ์ลาพักผ่อนปีแรก = 6 วัน เงื่อนไขเฉพาะของเคสนี้ - Employee Group = B - Expat Outbound - Employee Sub Group = UC เป็น Employee Sub Group ค่าเดียวที่ตาราง FO ผูกไว้กับกลุ่ม B ดู OQ-HIR-104 - ตารางเวลาให้กลุ่ม B ทุก Employee Sub Group = Time Status 09 O.T. Flag = no - รายละเอียดเต็มดูชีท Hiring Test Data หมายเหตุ - ดราฟต์เดิมระบุ Business Group = CPN ใช้ CRC ตามชุดข้อมูลจริงในถัง SIT - ดราฟต์เดิมระบุ Business Unit = CPN ใช้ CDG ตามชุดข้อมูลจริงในถัง SIT - ดราฟต์เดิมระบุ Company = C066 ใช้ C001 ตามชุดข้อมูลจริงในถัง SIT - ดราฟต์เดิมระบุ Personnel Grade (PG) = 20 ใช้ 10 ตามชุดข้อมูลจริงในถัง SIT | J8: EC > Hire & Onboard (New Hire) | K8: 1. Login ด้วย <HR_ADMIN_ACCOUNT> - ไปที่ EC > New Hire (Manual Key-in) 2. กรอกข้อมูล New Hire ตาม Test Data - กรอกข้อมูล Identity ตามข้อมูลที่กำหนด - กรอกข้อมูล Position & Organization โดยกำหนด Employee Group = B - Expat Outbound - กำหนด Probation Exemption = Yes - ไม่กรอก O.T. Flag และตรวจสอบค่าที่ระบบ Derive จาก Rule Table - กรอกข้อมูล Compensation Information ให้ครบถ้วน 3. กด Submit เพื่อสร้างพนักงานใหม่ 4. ตรวจสอบ Employee Profile ใน EC - กลับไปที่ EC Employee List - ค้นหาพนักงานที่สร้างใหม่ด้วย Employee ID - เปิด Employee Profile และตรวจสอบข้อมูลพนักงาน - ตรวจสอบ Employee Group / Probation Exemption / Pass Probation Date - ตรวจสอบว่าไม่แสดง Probationary Period End Date - ตรวจสอบว่าไม่มี Probation Record สำหรับพนักงานรายนี้ - ตรวจสอบ O.T. Flag ที่ระบบ Derive จาก Rule Table 5. ตรวจสอบผลหลังสร้างพนักงานที่ได้รับ Probation Exemption - ตรวจสอบ Pass Probation Date - ตรวจสอบว่าไม่มีขั้นตอนทดลองงานสำหรับพนักงานรายนี้ | L8: EC - ระบบสร้างพนักงานใหม่สำเร็จ - Employee Group = B - Expat Outbound - Probation Exemption = Yes - ระบบกำหนด Probationary Period End Date = Hire Date (Q&A ข้อ 22) - ระบบไม่แสดง Probationary Period End Date - ระบบไม่สร้าง Probation Record สำหรับพนักงานรายนี้ - พนักงานเข้าสู่สถานะทำงานได้โดยไม่ผ่านขั้น Probation - ระบบ Auto-Derive O.T. Flag จาก Rule Table โดย HR ไม่ต้องกรอกเอง - ค่าจาก Foundation Migration Set ยืนยันได้เพียงว่าเป็นค่าที่มีอยู่ในระบบ ยังไม่ได้ยืนยันว่าเป็นค่าที่ถูกต้องสำหรับ Scenario นี้ - Position Code ที่ใช้จริง = ? OQ-HIR-48 - ระบบใช้ Employee ID เป็นตัวชี้ว่าเป็นรายการ Migration เดิม และไม่สร้างพนักงานซ้ำ (Q&A ข้อ 41) - ค่าที่ระบบเก่ามีแต่ระบบใหม่ไม่มี ระบบแสดงค่าเดิมตามที่ migrate มา (Q&A ข้อ 18) จุดที่ยังไม่มีคำตอบในเคสนี้ ให้รันจริงแล้วบันทึกค่าที่ระบบแสดงลงช่อง Actual Result Image และช่อง Note เพื่อใช้เป็นคำตอบ แล้วส่งให้ BA หรือ SA ยืนยัน หมายเลขคำถามที่ต้องเก็บคำตอบระหว่างรัน OQ-HIR-48 | M8: Cancelled | Q8: ยกเว้นทดลองงาน (+ มีบรรทัด Migration ) ซ้ำ 054
A9: 8 | B9: Hiring | C9: E2E-08 | D9: Hiring | Keyin - Success | New Hire | Hire Date = Today | Age < 60 | Female | Non TH | E - Temporary | E9: HIR-EC-008 | F9: Positive | G9: High | H9: ตรวจสอบการจ้างพนักงานใหม่แบบ Key-in สำเร็จ กรณีวันเริ่มงานวันนี้ อายุ < 60 ปี เพศหญิง สัญชาติ Non-TH และเป็นพนักงานชั่วคราว | I9: - Entry Route = Keyin เงื่อนไขของเคสนี้ - Event Reason = New hire - Hire Date = Today - Date of Birth = Age < 60 - Gender = Female - Nationality = Non TH - Passport / Work Permit = ใช้แทน National ID 13 หลัก - Employee Group = E - Temporary - YOS = 365 วัน - DVT Project = null - Employee group = E - Temporary - Special benefit group flag = No ค่าที่ต้องคีย์ ชุดข้อมูลจากถัง SIT ตรวจสอบเมื่อ 28 ส.ค. 2026 ชุดข้อมูล TD-01 - Business Group = CRC - Business Unit = CDG (10000075) Policy Profile = CDS - Company = C001 - Position = 40106337 Job Code = MKB12.12 - Department = 30042174 Branch = T153_1733 SSO Location = T153 - Division = 20000079 Cost Center = C00132653 Work Location = 50000127 - Work Schedule = D05H0830 Holiday Calendar = 01 - Personnel Grade (PG) = 10 Employee Sub Group ที่ต้องคีย์ = 10 - ตารางกำหนด Time Status = 01 O.T. Flag = yes สิทธิ์ลาพักผ่อนปีแรก = 6 วัน เงื่อนไขเฉพาะของเคสนี้ - Employee Group = E - Temporary - Employee Sub Group = P2 Monthly - ตารางเวลาให้กลุ่ม E P1 ถึง P3 ของ CRC = Time Status 01 O.T. Flag = yes - รายละเอียดเต็มดูชีท Hiring Test Data หมายเหตุ - ดราฟต์เดิมระบุ Business Unit = CFR ใช้ CDG ตามชุดข้อมูลจริงในถัง SIT - ดราฟต์เดิมระบุ Company = C004 ใช้ C001 ตามชุดข้อมูลจริงในถัง SIT | J9: EC > Hire & Onboard (New Hire) | K9: 1. Login ด้วย <HR_ADMIN_ACCOUNT> - ไปที่ EC > New Hire (Manual Key-in) 2. กรอกข้อมูล New Hire ตาม Test Data - กรอกข้อมูล Identity โดยกำหนด Nationality = Non TH - กรอก Passport หรือ Work Permit แทน National ID 13 หลัก - กรอกข้อมูล Position & Organization โดยกำหนด Employee Group = E - Temporary - กรอกข้อมูล Mandatory อื่นให้ครบถ้วนเพื่อให้สามารถ Submit ได้ 3. กด Submit เพื่อสร้างพนักงานใหม่ 4. ตรวจสอบ Employee Profile ใน EC - ค้นหาพนักงานที่สร้างใหม่ด้วย Employee ID - ตรวจสอบ Nationality = Non TH - ตรวจสอบ Employee Group = E - Temporary - ตรวจสอบข้อมูล Passport / Work Permit ที่บันทึก | L9: EC - ระบบสร้างพนักงาน Nationality = Non TH และ Employee Group = E - Temporary ได้สำเร็จ - ระบบบันทึก Nationality = Non TH และ Employee Group = E - Temporary ตามข้อมูลที่ระบุ - ระบบให้กรอก Passport หรือ Work Permit แทน National ID 13 หลักได้ - ระบบบันทึกข้อมูล Passport / Work Permit ตามข้อมูลที่กรอก - Country ใน Work Permit = Thailand (Q&A ข้อ 33) | M9: Cancelled | Q9: ต่างชาติ ต่างแค่ Employee Group ไม่เปลี่ยน validation ซ้ำ 005
A10: 9 | B10: Hiring | C10: E2E-09 | D10: Hiring | Keyin - Success | New Hire | Hire Date = Today | Age < 60 | Female | TH | F - DVT | E10: HIR-EC-009 | F10: Positive | G10: High | H10: ตรวจสอบการจ้างพนักงานใหม่แบบ Key-in สำเร็จ กรณีวันเริ่มงานวันนี้ อายุ < 60 ปี เพศหญิง สัญชาติไทย และกลุ่มพนักงาน DVT | I10: - Entry Route = Keyin เงื่อนไขของเคสนี้ - Event Reason = New Hire - Hire Date = Today - Date of Birth = Age < 60 - Gender = Female - Nationality = TH - Employee Group = F - DVT - DVT Project Name = ? รอตารางโครงการ DVT - Partner University = 06 Burapha University - Type = ? ยังไม่ยืนยันตารางที่ใช้ - Degree Level = zDVTDegreeLv_3 Vocational Certificate - Course = major006 Business Admin - Course of Time = ? ยังไม่ยืนยันหน่วย/รูปแบบ - Academic Year = 2569 - Graduation Date = 31/03/2027 - Bonding End Date = 31/03/2029 - University Type = ต้องระบุเป็น DVT Partnered University หรือ Other University ก่อน Execute - DVT Project = B05 - Employee group = F - DVT - Special benefit group flag = No ค่าที่ต้องคีย์ ชุดข้อมูลจากถัง SIT ตรวจสอบเมื่อ 28 ส.ค. 2026 ชุดข้อมูล TD-01 - Business Group = CRC - Business Unit = CDG (10000075) Policy Profile = CDS - Company = C001 - Position = 40106337 Job Code = MKB12.12 - Department = 30042174 Branch = T153_1733 SSO Location = T153 - Division = 20000079 Cost Center = C00132653 Work Location = 50000127 - Work Schedule = D05H0830 Holiday Calendar = 01 - Personnel Grade (PG) = 10 Employee Sub Group ที่ต้องคีย์ = 10 - ตารางกำหนด Time Status = 01 O.T. Flag = yes สิทธิ์ลาพักผ่อนปีแรก = 6 วัน เงื่อนไขเฉพาะของเคสนี้ - Employee Group = F - DVT - Employee Sub Group = D1 Partner university - ตารางเวลาให้กลุ่ม F ทุก Employee Sub Group = Time Status 01 O.T. Flag = yes - รายละเอียดเต็มดูชีท Hiring Test Data หมายเหตุ - ดราฟต์เดิมระบุ Business Unit = RBS ใช้ CDG ตามชุดข้อมูลจริงในถัง SIT RBS ปิดใช้งานตั้งแต่ 1 ต.ค. 2024 ตามไฟล์ FO และไม่มี Position ในถัง SIT - ดราฟต์เดิมระบุ Company = C002 ใช้ C001 ตามชุดข้อมูลจริงในถัง SIT | J10: EC > Hire & Onboard (New Hire) | K10: 1. Login ด้วย <HR_ADMIN_ACCOUNT> - ไปที่ EC > New Hire (Manual Key-in) 2. กรอกข้อมูล Identity ตาม Test Data 3. ตรวจสอบ DVT-Specific Fields ตาม Employee Group - เลือก Employee Group อื่นที่ไม่ใช่ F - DVT และตรวจสอบว่าฟิลด์ DVT ทั้ง 9 ช่องไม่แสดง - เปลี่ยน Employee Group = F - DVT - ตรวจสอบว่าระบบแสดง DVT Project Name / Partner University / Type / Degree Level / Course / Course of Time / Academic Year / Graduation Date / Bonding End Date - ตรวจสอบว่า Scholarship ไม่แสดงสำหรับ Employee Group = F - DVT 4. กรอกข้อมูล Position & Organization - กำหนด Employee Group = F - DVT - กรอกข้อมูล Mandatory อื่นให้ครบถ้วนเพื่อให้สามารถ Submit ได้ 5. กรอกข้อมูล DVT - กรอก DVT-Specific Fields ทั้ง 9 ช่องตาม Test Data - ระบุ University Type เป็น DVT Partnered University หรือ Other University ตามชุดข้อมูลที่ใช้ทดสอบ 6. กรอกข้อมูล Compensation Information ให้ครบถ้วน 7. กด Submit เพื่อสร้างพนักงานใหม่ 8. ตรวจสอบ Employee Profile ใน EC - ค้นหาพนักงานด้วย Employee ID - ตรวจสอบ Employee Group = F - DVT - ตรวจสอบข้อมูล DVT ทั้ง 9 ช่องที่บันทึก 9. ตรวจสอบข้อมูล DVT ตามประเภทมหาวิทยาลัย - ตรวจสอบผลของ DVT Partnered University / Other University ตาม TC-E2E-115 | L10: EC - ระบบสร้างพนักงาน Employee Group = F - DVT ได้สำเร็จ - เมื่อ Employee Group = F - DVT ระบบแสดง DVT-Specific Fields ทั้ง 9 ช่อง ได้แก่ DVT Project Name / Partner University / Type / Degree Level / Course / Course of Time / Academic Year / Graduation Date / Bonding End Date - เมื่อ Employee Group ไม่ใช่ F - DVT ระบบซ่อน DVT-Specific Fields ทั้ง 9 ช่อง - ระบบบันทึกข้อมูล DVT ทั้ง 9 ช่องตามข้อมูลที่ระบุหลัง Submit สำเร็จ - ระบบไม่แสดง Scholarship เมื่อ Employee Group = F - DVT เนื่องจาก Scholarship เป็นเงื่อนไขของ Employee Group = Permanent DVT - ผลของ DVT Partnered University / Other University เป็นไปตาม Coverage ของ TC-E2E-115 - ต้องกำหนด University Type ที่ใช้ทดสอบให้ชัดเจนก่อน Execute เนื่องจากทั้งสองประเภทมีผลต่างกัน - ตาราง DVT Project Name / Type และรูปแบบ Course of Time = ? OQ-HIR-78 จุดที่ยังไม่มีคำตอบในเคสนี้ ให้รันจริงแล้วบันทึกค่าที่ระบบแสดงลงช่อง Actual Result Image และช่อง Note เพื่อใช้เป็นคำตอบ แล้วส่งให้ BA หรือ SA ยืนยัน หมายเลขคำถามที่ต้องเก็บคำตอบระหว่างรัน OQ-HIR-78 | M10: Testing | O10: QA-Thitiya | Q10: ตัดจากเคส E2E-09 ไฟล์ HR_SIT_E2E_V.0.1 (28).xlsx ชีท E2E All module โมดูลที่เคสเต็มเกี่ยวข้อง REC / File Gateway / EC / BE / TM / PY ยกไปรอบเชื่อมโมดูล ผลที่คาดหวังฝั่ง Notification / TM / BE / PY ยกไปรอบเชื่อมโมดูล ขั้นตอน ตรวจสอบข้อมูลใน BE เคสนี้มีจุดที่ยังไม่มีคำตอบ 1 จุด ไม่ต้องรอคำตอบก่อนรัน ให้รันเก็บค่าที่ระบบแสดงจริงแล้วแจ้ง BA หรือ SA ยืนยันหลังรัน
A11: 10 | B11: Hiring | C11: E2E-10 | D11: Hiring | Keyin - Success | New Hire | Hire Date = Today | Age < 60 | Male | TH | G - Intership | E11: HIR-EC-010 | F11: Positive | G11: Medium | H11: ตรวจสอบการจ้างพนักงานใหม่แบบ Key-in สำเร็จ กรณีวันเริ่มงานวันนี้ อายุ < 60 ปี เพศชาย สัญชาติไทย และเป็นพนักงานฝึกงาน | I11: - Entry Route = Keyin เงื่อนไขของเคสนี้ - Event Reason = New Hire - Hire Date = Today - Date of Birth = Age < 60 - Gender = Male - Nationality = Thai - Employee Group = G - Internship - Probation Exemption = No - DVT Project = null - Employee group = G - Internship - Special benefit group flag = No ค่าที่ต้องคีย์ ชุดข้อมูลจากถัง SIT ตรวจสอบเมื่อ 28 ส.ค. 2026 ชุดข้อมูล TD-01 - Business Group = CRC - Business Unit = CDG (10000075) Policy Profile = CDS - Company = C001 - Position = 40106337 Job Code = MKB12.12 - Department = 30042174 Branch = T153_1733 SSO Location = T153 - Division = 20000079 Cost Center = C00132653 Work Location = 50000127 - Work Schedule = D05H0830 Holiday Calendar = 01 - Personnel Grade (PG) = 10 Employee Sub Group ที่ต้องคีย์ = 10 - ตารางกำหนด Time Status = 01 O.T. Flag = yes สิทธิ์ลาพักผ่อนปีแรก = 6 วัน เงื่อนไขเฉพาะของเคสนี้ - Employee Group = G - Internship - Employee Sub Group = T1 CG Internship - ตารางเวลาให้กลุ่ม G ทุก Employee Sub Group = Time Status 01 O.T. Flag = yes - rule กลุ่ม G ที่ระบุช่วง P1 ถึง P3 ในตารางเวลา ใช้กับ Employee Sub Group ชุดนี้ไม่ได้ ดู CF-SIT-15 - รายละเอียดเต็มดูชีท Hiring Test Data หมายเหตุ - ดราฟต์เดิมระบุ Business Unit = CFR ใช้ CDG ตามชุดข้อมูลจริงในถัง SIT - ดราฟต์เดิมระบุ Company = C004 ใช้ C001 ตามชุดข้อมูลจริงในถัง SIT | J11: EC > Hire & Onboard (New Hire) | K11: 1. Login ด้วย <HR_ADMIN_ACCOUNT> - ไปที่ EC > New Hire (Manual Key-in) 2. กรอกข้อมูล New Hire ตาม Test Data - กรอกข้อมูล Identity ตามข้อมูลที่กำหนด - กรอกข้อมูล Position & Organization โดยกำหนด Employee Group = G - Internship - กรอกข้อมูล Mandatory ที่จำเป็นให้ครบถ้วน 3. กด Submit เพื่อสร้างพนักงานใหม่ 4. ตรวจสอบ Employee Profile ใน EC - ค้นหาพนักงานที่สร้างใหม่ด้วย Employee ID - เปิด Employee Profile - ตรวจสอบ Employee Group = G - Internship - ตรวจสอบว่าไม่แสดงข้อมูล Scholarship 5. ตรวจสอบข้อมูล Internship | L11: EC - ระบบสร้างพนักงานใหม่สำเร็จตาม Expected Result ของ E2E-01 - Employee Group = G - Internship - Probation Exemption = No - ระบบไม่แสดง Scholarship เนื่องจาก Scholarship แสดงเฉพาะ Employee Group = Permanent Internship - Internship Rate เป็นไปตามเงื่อนไข - ระยะ Probation ของ Employee Group = G - Internship = ? OQ-HIR-50 จุดที่ยังไม่มีคำตอบในเคสนี้ ให้รันจริงแล้วบันทึกค่าที่ระบบแสดงลงช่อง Actual Result Image และช่อง Note เพื่อใช้เป็นคำตอบ แล้วส่งให้ BA หรือ SA ยืนยัน หมายเลขคำถามที่ต้องเก็บคำตอบระหว่างรัน OQ-HIR-50 | M11: Cancelled | Q11: Expected "เหมือน E2E-01"
A12: 11 | B12: Hiring | C12: E2E-11 | D12: Hiring | Keyin - Success | New Hire | Hire Date = Today | Age < 60 | Female | TH | H - Contingent Worker | E12: HIR-EC-011 | F12: Positive | G12: Medium | H12: ตรวจสอบการจ้างพนักงานใหม่แบบ Key-in สำเร็จ กรณีวันเริ่มงานวันนี้ อายุ < 60 ปี เพศหญิง สัญชาติไทย และกลุ่มพนักงาน Contingent Worker | I12: - Entry Route = Keyin เงื่อนไขของเคสนี้ - Event Reason = New Hire - Hire Date = Today - Date of Birth = Age < 60 - Gender = Female - Nationality = Thai - Employee Group = H - Contingent Worker - DVT Project = null - Employee group = H - Contingent Worker - Special benefit group flag = No ค่าที่ต้องคีย์ ชุดข้อมูลจากถัง SIT ตรวจสอบเมื่อ 28 ส.ค. 2026 ชุดข้อมูล TD-01 - Business Group = CRC - Business Unit = CDG (10000075) Policy Profile = CDS - Company = C001 - Position = 40106337 Job Code = MKB12.12 - Department = 30042174 Branch = T153_1733 SSO Location = T153 - Division = 20000079 Cost Center = C00132653 Work Location = 50000127 - Work Schedule = D05H0830 Holiday Calendar = 01 - Personnel Grade (PG) = 10 Employee Sub Group ที่ต้องคีย์ = 10 - ตารางกำหนด Time Status = 01 O.T. Flag = yes สิทธิ์ลาพักผ่อนปีแรก = 6 วัน เงื่อนไขเฉพาะของเคสนี้ - Employee Group = H - Contingent Worker - Employee Sub Group = C1 Consultant - ตารางเวลาให้กลุ่ม H ทุก Employee Sub Group = Time Status 09 O.T. Flag = no - รายละเอียดเต็มดูชีท Hiring Test Data หมายเหตุ - ดราฟต์เดิมระบุ Business Unit = CFR ใช้ CDG ตามชุดข้อมูลจริงในถัง SIT - ดราฟต์เดิมระบุ Company = C004 ใช้ C001 ตามชุดข้อมูลจริงในถัง SIT | J12: EC > Hire & Onboard (New Hire) | K12: 1. Login ด้วย <HR_ADMIN_ACCOUNT> - ไปที่ EC > New Hire (Manual Key-in) 2. กรอกข้อมูล New Hire ตาม Test Data - กรอกข้อมูล Identity ตามข้อมูลที่กำหนด - กรอกข้อมูล Position & Organization โดยกำหนด Employee Group = H - Contingent Worker - กรอกข้อมูล Mandatory ที่จำเป็นให้ครบถ้วน 3. กด Submit เพื่อสร้างพนักงานใหม่ 4. ตรวจสอบ Employee Profile ใน EC - ค้นหาพนักงานที่สร้างใหม่ด้วย Employee ID - เปิด Employee Profile - ตรวจสอบ Employee Group = H - Contingent Worker | L12: EC - ระบบสร้างพนักงานใหม่สำเร็จตาม Expected Result ของ E2E-01 - ระบบบันทึก Employee Group = H - Contingent Worker ถูกต้องตามข้อมูลที่ระบุ - กฎธุรกิจและสูตรคำนวณเฉพาะของ Employee Group = H - Contingent Worker = ? OQ-HIR-64 - ระยะ Probation ของ Employee Group = H - Contingent Worker = ? OQ-HIR-50 จุดที่ยังไม่มีคำตอบในเคสนี้ ให้รันจริงแล้วบันทึกค่าที่ระบบแสดงลงช่อง Actual Result Image และช่อง Note เพื่อใช้เป็นคำตอบ แล้วส่งให้ BA หรือ SA ยืนยัน หมายเลขคำถามที่ต้องเก็บคำตอบระหว่างรัน OQ-HIR-64, OQ-HIR-50 | M12: Cancelled | Q12: Expected "เหมือน E2E-01"
A13: 12 | B13: Hiring | C13: E2E-12 | D13: Hiring | Keyin - Success | Replacement | Hire Date = Today | Age < 60 | Male | TH | A - Permanent | E13: HIR-EC-012 | F13: Positive | G13: High | H13: ตรวจสอบการจ้างพนักงานแบบ Replacement ผ่าน Key-in สำเร็จ กรณีวันเริ่มงานวันนี้ อายุ < 60 ปี เพศชาย สัญชาติไทย และเป็นพนักงานประจำ | I13: - Entry Route = Keyin เงื่อนไขของเคสนี้ - Event Reason = Replacement - Hire Date = Today - Date of Birth = Age < 60 - Gender = Male - Nationality = Thai - Replaced Employee ID = Employee ID ของพนักงานที่มีอยู่จริงและสามารถใช้สำหรับ Replacement - Invalid Replaced Employee ID = <NON_EXISTING_EMPLOYEE_ID> - Employee Group = A - Permanent - DVT Project = null - Employee group = A - Permanent - Special benefit group flag = No ค่าที่ต้องคีย์ ชุดข้อมูลจากถัง SIT ตรวจสอบเมื่อ 28 ส.ค. 2026 ชุดข้อมูล TD-46 - Business Group = CRC - Business Unit = CFR (10000003) Policy Profile = CFR - Company = C004 - Position = 40004883 Job Code = LPB10.12 - Department = 30002071 Branch = T170_1750 SSO Location = T170 - Division = 20001368 Cost Center = C00402100 Work Location = 50000034 - Work Schedule = D06H0800 Holiday Calendar = 03 - Personnel Grade (PG) = 10 Employee Sub Group ที่ต้องคีย์ = 10 - ตารางกำหนด Time Status = 01 O.T. Flag = yes สิทธิ์ลาพักผ่อนปีแรก = 6 วัน ชุดข้อมูล TD-42 - Position = 40007752 Job Code = STB10.12 - Department = 30002647 Branch = T224_1804 SSO Location = T224 - Division = 20001352 Cost Center = C00426100 Work Location = 50000183 - Personnel Grade (PG) = 10 Employee Sub Group ที่ต้องคีย์ = 10 เงื่อนไขเฉพาะของเคสนี้ - พนักงานที่ถูกแทนที่ = ผู้ครอง Position 40004883 - Position ที่จ้างเข้ามาใหม่ = TD-42 - ยังไม่มีพนักงานในฐานข้อมูล SIT จึงต้องสร้างพนักงานผู้ถูกแทนที่ก่อนด้วยเคส E2E-01 ดู CF-SIT-08 - รายละเอียดเต็มดูชีท Hiring Test Data หมายเหตุ - ดราฟต์เดิมระบุ Business Unit = CDS ใช้ CFR / CFR ตามชุดข้อมูลจริงในถัง SIT CDS ปิดใช้งานตั้งแต่ 1 ต.ค. 2024 ตามไฟล์ FO และไม่มี Position ในถัง SIT - ดราฟต์เดิมระบุ Company = C001 ใช้ C004 / C004 ตามชุดข้อมูลจริงในถัง SIT | J13: EC > Hire & Onboard (New Hire) | K13: 1. Login ด้วย <HR_ADMIN_ACCOUNT> - ไปที่ EC > New Hire (Manual Key-in) 2. ตรวจสอบการแสดง Replaced Employee ID ตาม Event Reason - เลือก Event Reason = New Hire และตรวจสอบว่าไม่แสดงช่อง Replaced Employee ID - เปลี่ยน Event Reason = Replacement - ตรวจสอบว่าระบบแสดงช่อง Replaced Employee ID และกำหนดเป็น Required 3. ตรวจสอบ Replaced Employee ID ที่ไม่มีอยู่จริง - กรอก Replaced Employee ID = <NON_EXISTING_EMPLOYEE_ID> - กด Verify - ตรวจสอบ Validation / Notice ที่ระบบแสดง - ตรวจสอบว่าไม่สามารถใช้ Employee ID ที่ไม่ถูกต้องดำเนินการต่อได้ 4. ตรวจสอบ Replaced Employee ID ที่ถูกต้อง - กรอก Replaced Employee ID ของพนักงานที่มีอยู่จริงตาม Test Data (พนักงานเดิมมีการ ลาออก / ย้าย / เลื่อนตำแหน่ง) - กด Verify - ตรวจสอบว่า Replaced Employee ID ผ่านการตรวจสอบ 5. กรอกข้อมูล New Hire ตาม Test Data - กรอกข้อมูล Identity ตามข้อมูลที่กำหนด - กรอกข้อมูล Position & Organization โดยกำหนด Employee Group = A - Permanent - กรอกข้อมูล Mandatory ที่จำเป็นให้ครบถ้วน 6. กด Submit เพื่อสร้างพนักงานใหม่ 7. ตรวจสอบ Employee Profile ใน EC - ค้นหาพนักงานที่สร้างใหม่ด้วย Employee ID - เปิด Employee Profile - ตรวจสอบ Event Reason = Replacement - ตรวจสอบ Employee Group = A - Permanent - ตรวจสอบ Replaced Employee ID ที่บันทึก | L13: EC - ระบบสร้างพนักงานใหม่สำเร็จ - ระบบบันทึก Event Reason = Replacement - ระบบบันทึก Employee Group = A - Permanent - Hire Date = Today ตามข้อมูลที่ระบุ - ระบบไม่ตรวจว่า Replaced Employee ID ต้องอยู่ Position / Company / Business Unit เดียวกัน และไม่ตรวจสถานะ active ขอเพียงระบบค้นหาเจอ (Q&A ข้อ 34, 35, 37) Replaced Employee ID - เมื่อ Event Reason = New Hire ระบบไม่แสดงช่อง Replaced Employee ID - เมื่อ Event Reason = Replacement ระบบแสดงช่อง Replaced Employee ID และกำหนดเป็น Required - เมื่อกรอก Replaced Employee ID ที่ไม่มีอยู่จริงและกด Verify ระบบแสดง Validation / Notice และไม่อนุญาตให้ใช้ Employee ID ดังกล่าวดำเนินการต่อ - เมื่อกรอก Replaced Employee ID ที่ถูกต้องและกด Verify ระบบตรวจสอบข้อมูลสำเร็จและสามารถดำเนินการต่อได้ - หลัง Submit สำเร็จ ระบบบันทึก Replaced Employee ID ตรงกับข้อมูลที่ระบุ | M13: Not Start | Q13: ตัดจากเคส E2E-12 ไฟล์ HR_SIT_E2E_V.0.1 (28).xlsx ชีท E2E All module โมดูลที่เคสเต็มเกี่ยวข้อง EC / BE / TM / PY / Notification ยกไปรอบเชื่อมโมดูล ผลที่คาดหวังฝั่ง Notification / TM / BE / PY
A14: 13 | B14: Hiring | C14: E2E-13 | D14: Hiring | Keyin - Success | Migration | Hire Date < Today (Current Year) | Age < 60 | Female | TH | G - Internship | E14: HIR-EC-013 | F14: Positive | G14: Medium | H14: ตรวจสอบการจ้างพนักงานแบบ Migration ผ่าน Key-in สำเร็จ กรณีวันเริ่มงานย้อนหลังภายในปีปัจจุบัน อายุ < 60 ปี เพศหญิง สัญชาติไทย และเป็นพนักงานฝึกงาน | I14: - Entry Route = Keyin เงื่อนไขของเคสนี้ - Event Reason = Migration - Hire Date < Today 01 Aug 2026 - Date of Birth = Age < 60 - Gender = Female - Nationality = Thai - Employee Group = G - Internship - DVT Project = null - Employee group = G - Internship - Special benefit group flag = No ค่าที่ต้องคีย์ ชุดข้อมูลจากถัง SIT ตรวจสอบเมื่อ 28 ส.ค. 2026 ชุดข้อมูล TD-01 - Business Group = CRC - Business Unit = CDG (10000075) Policy Profile = CDS - Company = C001 - Position = 40106337 Job Code = MKB12.12 - Department = 30042174 Branch = T153_1733 SSO Location = T153 - Division = 20000079 Cost Center = C00132653 Work Location = 50000127 - Work Schedule = D05H0830 Holiday Calendar = 01 - Personnel Grade (PG) = 10 Employee Sub Group ที่ต้องคีย์ = 10 - ตารางกำหนด Time Status = 01 O.T. Flag = yes สิทธิ์ลาพักผ่อนปีแรก = 6 วัน เงื่อนไขเฉพาะของเคสนี้ - Employee Group = G - Internship Employee Sub Group = T1 - Event Reason = Migration - รายละเอียดเต็มดูชีท Hiring Test Data หมายเหตุ - ดราฟต์เดิมระบุ Business Unit = CDS ใช้ CDG ตามชุดข้อมูลจริงในถัง SIT CDS ปิดใช้งานตั้งแต่ 1 ต.ค. 2024 ตามไฟล์ FO และไม่มี Position ในถัง SIT | J14: EC > Hire & Onboard (New Hire) | K14: 1. Login ด้วย <HR_ADMIN_ACCOUNT> - ไปที่ EC > New Hire (Manual Key-in) 2. กรอกข้อมูลตาม Test Data - กำหนด Event Reason = Migration - กำหนด Hire Date < Today - กรอกข้อมูล Identity ตามข้อมูลที่กำหนด - กำหนด Employee Group = G - Internship - กรอกข้อมูล Mandatory อื่นให้ครบถ้วนเพื่อให้สามารถ Submit ได้ 3. กด Submit เพื่อสร้างข้อมูลพนักงาน 4. ตรวจสอบ Employee Profile ใน EC - ค้นหาพนักงานด้วย Employee ID - ตรวจสอบ Event Reason = Migration - ตรวจสอบ Hire Date เป็นวันที่ย้อนหลัง - ตรวจสอบ Employee Group = G - Internship - ตรวจสอบ Employee Status | L14: EC - ระบบบันทึกข้อมูลพนักงานจาก Migration ได้สำเร็จ - Event Reason = Migration - Hire Date = วันที่ย้อนหลังตามข้อมูลที่ระบุ และน้อยกว่า Today - Employee Group = G - Internship - Employee Status = Active - ระบบไม่สร้าง Employee Record ซ้ำจากรายการเดียวกัน - ระบบไม่ส่ง Notification ซ้ำจากการ Migration - ระบบใช้ Employee ID เป็นตัวชี้ว่าเป็นรายการ Migration เดิม และไม่สร้างพนักงานซ้ำ (Q&A ข้อ 41) - ค่าที่ระบบเก่ามีแต่ระบบใหม่ไม่มี ระบบแสดงค่าเดิมตามที่ migrate มา (Q&A ข้อ 18) | M14: Not Start | Q14: ตัดจากเคส E2E-13 ไฟล์ HR_SIT_E2E_V.0.1 (28).xlsx ชีท E2E All module โมดูลที่เคสเต็มเกี่ยวข้อง EC / BE / TM / PY ยกไปรอบเชื่อมโมดูล ผลที่คาดหวังฝั่ง Notification / TM / BE / PY / ผลข้ามโมดูล ตรวจหลัง Submit สำเร็จแล้ว ยกไปรอบเชื่อมโมดูล ขั้นตอน ตรวจสอบผลหลัง Migration
A15: 14 | B15: Hiring | C15: E2E-14 | D15: Hiring | RCM - Success | New Hire | Hire Date = Today | Age < 60 | Female | TH | E - Temporary | E15: HIR-EC-014 | F15: Positive | G15: High | H15: ตรวจสอบการจ้างพนักงานใหม่ผ่าน RCM สำเร็จ กรณีวันเริ่มงานวันนี้ อายุ < 60 ปี เพศหญิง สัญชาติไทย และเป็นพนักงานชั่วคราว | I15: - Entry Route = RCM เงื่อนไขของเคสนี้ - Event Reason = New Hire - Hire Date = Today - Date of Birth = Age < 60 - Gender = Female - Nationality = Thai - Employee Group = E - Temporary ค่าที่ต้องคีย์ ชุดข้อมูลจากถัง SIT ตรวจสอบเมื่อ 28 ส.ค. 2026 ชุดข้อมูล TD-50 - Business Group = CRC - Business Unit = CFR (10000003) Policy Profile = CFR - Company = C004 - Position = 40172617 Job Code = STA10.03 - Department = 30002732 Store/ Branch Code = T251_1831 SSO Location = T251 - Division = 20001351 Cost Center = C00429550 Work Location = 50000472 - Work Schedule = D06H0800 Holiday Calendar = 03 - Personnel Grade (PG) = NA - Employee Group = E - Temporary Employee Sub Group = P1-Daily - Employment Type = P สถานะ Position = ว่าง - ตาราง time_status_mapping กำหนด Time Status = 2 O.T. Flag = yes - สิทธิ์ลาพักผ่อนปีแรก = ? แถว Quota ของกลุ่มนี้ระบุ Personnel Grade (PG) 01 ถึง 20 ซึ่งไม่ครอบ NA ดู OQ-HIR-111 เงื่อนไขเฉพาะของเคสนี้ - คีย์ Employee Group = E - Temporary Employee Sub Group = P1-Daily ตามชุดข้อมูล - Hire Date = วันที่ทดสอบ Gender = Female Nationality = Thai - Personnel Grade (PG) ของ Position นี้เป็น NA จึงคีย์ Employee Sub Group เป็นรหัส P1 ไม่ใช่ตัวเลข - รายละเอียดเต็มดูชีท Hiring Test Data | J15: EC > Manage Pending Recruits | K15: 1. Login ด้วย <HR_ADMIN_ACCOUNT> - ไปที่ Manage Pending Recruits - เปิดรายการพนักงานที่รับมาจาก RCM - ตรวจสอบข้อมูลที่ได้รับจาก RCM - ตรวจสอบว่าฟิลด์ใดถูกล็อกไม่ให้แก้ไขหลังรับจาก RCM และบันทึก Actual Behavior 2. กรอกข้อมูลส่วนที่เหลือให้ครบถ้วนตาม Test Data - กำหนด Event Reason = New Hire - กำหนด Hire Date = Today - กำหนด Employee Group = E - Temporary - กรอกข้อมูล Mandatory อื่นให้ครบถ้วนเพื่อให้สามารถ Submit ได้ 3. กด Submit เพื่อสร้างพนักงานใหม่ 4. ตรวจสอบ Employee Profile ใน EC - ค้นหาพนักงานด้วย Employee ID - ตรวจสอบ Event Reason = New Hire - ตรวจสอบ Hire Date = Today - ตรวจสอบ Employee Group = E - Temporary 5. ตรวจสอบรายการใน Manage Pending Recruits หลัง Submit สำเร็จ - ตรวจสอบว่ารายการที่ Submit สำเร็จแล้วไม่ค้างอยู่ใน Manage Pending Recruits - ตรวจสอบว่าไม่ต้องให้ HR กด Submit รายการเดิมซ้ำอีกครั้ง | L15: EC - RCM สร้างพนักงานใน EC โดยตรง ไม่ต้องให้ HR Admin กด Submit (Q&A ข้อ 7 และ 53) - ระบบสร้างพนักงานใหม่สำเร็จโดยอัตโนมัติเมื่อรับข้อมูลจาก RCM - Event Reason = New Hire - Hire Date = Today - Employee Group = E - Temporary - เป้าหมายเดิมระบุว่าข้อมูลเข้าภายใน 1 รอบ Sync ไม่เกิน 90 นาที แต่รอบงานจริงและวิธียืนยันการรับข้อมูล = ? OQ-HIR-46 - ฟิลด์ที่ระบบล็อกไม่ให้แก้หลังรับจาก RCM = ? OQ-HIR-23 - การ Mapping Event Reason จาก RCM ไปเป็นรหัสของ EC และพฤติกรรมกรณีพบค่าที่ไม่รู้จัก = ? OQ-HIR-27 - พบ National ID ซ้ำ ถ้าพนักงานเดิมเป็น inactive ระบบสร้าง Employee ID ใหม่ ถ้าเป็น active ระบบ update ข้อมูลที่ส่งเข้ามาทับ (Q&A ข้อ 44) จุดที่ยังไม่มีคำตอบในเคสนี้ ให้รันจริงแล้วบันทึกค่าที่ระบบแสดงลงช่อง Actual Result Image และช่อง Note เพื่อใช้เป็นคำตอบ แล้วส่งให้ BA หรือ SA ยืนยัน หมายเลขคำถามที่ต้องเก็บคำตอบระหว่างรัน OQ-HIR-46, OQ-HIR-23, OQ-HIR-27 | M15: Not Start
A16: 15 | B16: Hiring | C16: E2E-15 | D16: Hiring | RCM - Success | New Hire | Hire Date < Today | Age < 60 | Male | TH | A - Permanent | E16: HIR-EC-015 | F16: Positive | G16: High | H16: ตรวจสอบการจ้างพนักงานใหม่ผ่าน RCM สำเร็จ กรณีวันเริ่มงานย้อนหลัง อายุ < 60 ปี เพศชาย สัญชาติไทย และเป็นพนักงานประจำ | I16: - Entry Route = RCM เงื่อนไขของเคสนี้ - Event Reason = New Hire - Hire Date < Today - Date of Birth = Age < 60 - Gender = Male - Nationality = Thai - Employee Group = A - Permanent ค่าที่ต้องคีย์ ชุดข้อมูลจากถัง SIT ตรวจสอบเมื่อ 28 ส.ค. 2026 ชุดข้อมูล TD-01 - Business Group = CRC - Business Unit = CDG (10000075) Policy Profile = CDS - Company = C001 - Position = 40106337 Job Code = MKB12.12 - Department = 30042174 Store/ Branch Code = T153_1733 SSO Location = T153 - Division = 20000079 Cost Center = C00132653 Work Location = 50000127 - Work Schedule = D05H0830 Holiday Calendar = 01 - Personnel Grade (PG) = 10 - Employee Group = A - Permanent Employee Sub Group = 10 - Employment Type = F สถานะ Position = ว่าง - ตาราง time_status_mapping กำหนด Time Status = 01 O.T. Flag = yes - สิทธิ์ลาพักผ่อนปีแรก = 6 เงื่อนไขเฉพาะของเคสนี้ - คีย์ Employee Group = A - Permanent Employee Sub Group = 10 ตามชุดข้อมูล - Hire Date = ย้อนหลังจากวันที่ทดสอบ 5 วัน Gender = Male Nationality = Thai - รายละเอียดเต็มดูชีท Hiring Test Data | J16: EC > Manage Pending Recruits | K16: 1. Login ด้วย <HR_ADMIN_ACCOUNT> - ไปที่ Manage Pending Recruits - เปิดรายการพนักงานที่รับมาจาก RCM - ตรวจสอบข้อมูลที่ได้รับจาก RCM - ตรวจสอบว่าฟิลด์ใดถูกล็อกไม่ให้แก้ไขหลังรับจาก RCM และบันทึก Actual Behavior 2. กรอกข้อมูลส่วนที่เหลือให้ครบถ้วนตาม Test Data - กำหนด Event Reason = New Hire - กำหนด Hire Date < Today - กำหนด Employee Group = A - Permanent - กรอกข้อมูล Mandatory อื่นให้ครบถ้วนเพื่อให้สามารถ Submit ได้ 3. กด Submit เพื่อสร้างพนักงานใหม่ 4. ตรวจสอบ Employee Profile ใน EC - ค้นหาพนักงานด้วย Employee ID - ตรวจสอบ Event Reason = New Hire - ตรวจสอบ Hire Date เป็นวันที่ย้อนหลัง - ตรวจสอบ Employee Group = A - Permanent 5. ตรวจสอบรายการใน Manage Pending Recruits หลัง Submit สำเร็จ - ตรวจสอบว่ารายการที่ Submit สำเร็จแล้วไม่ค้างอยู่ใน Manage Pending Recruits - ตรวจสอบว่าไม่ต้องให้ HR กด Submit รายการเดิมซ้ำอีกครั้ง | L16: EC - RCM สร้างพนักงานใน EC โดยตรง ไม่ต้องให้ HR Admin กด Submit (Q&A ข้อ 7 และ 53) - ระบบสร้างพนักงานใหม่สำเร็จโดยอัตโนมัติเมื่อรับข้อมูลจาก RCM - Event Reason = New Hire - Hire Date = วันที่ย้อนหลังและน้อยกว่า Today - Employee Group = A - Permanent - ระบบยอมรับ Hire Date ย้อนหลังและไม่ Block ที่ EC - เป้าหมายเดิมระบุว่าข้อมูลเข้าภายใน 1 รอบ Sync ไม่เกิน 90 นาที แต่รอบงานจริงและวิธียืนยันการรับข้อมูล = ? OQ-HIR-46 - ฟิลด์ที่ระบบล็อกไม่ให้แก้หลังรับจาก RCM = ? OQ-HIR-23 - การ Mapping Event Reason จาก RCM ไปยัง EC และพฤติกรรมกรณีพบค่าที่ไม่รู้จัก = ? OQ-HIR-27 - พบ National ID ซ้ำ ถ้าพนักงานเดิมเป็น inactive ระบบสร้าง Employee ID ใหม่ ถ้าเป็น active ระบบ update ข้อมูลที่ส่งเข้ามาทับ (Q&A ข้อ 44) จุดที่ยังไม่มีคำตอบในเคสนี้ ให้รันจริงแล้วบันทึกค่าที่ระบบแสดงลงช่อง Actual Result Image และช่อง Note เพื่อใช้เป็นคำตอบ แล้วส่งให้ BA หรือ SA ยืนยัน หมายเลขคำถามที่ต้องเก็บคำตอบระหว่างรัน OQ-HIR-46, OQ-HIR-23, OQ-HIR-27 | M16: Not Start
A17: 16 | B17: Hiring | C17: E2E-16 | D17: Hiring | RCM - Success | New Hire | Hire Date = Today | Age < 60 | Male | Non TH | C - Expat Inbound | E17: HIR-EC-016 | F17: Positive | G17: High | H17: ตรวจสอบการจ้างพนักงานใหม่ผ่าน RCM สำเร็จ กรณีวันเริ่มงานวันนี้ อายุ < 60 ปี เพศชาย สัญชาติ Non-TH และกลุ่มพนักงาน Expat Inbound | I17: - Entry Route = RCM เงื่อนไขของเคสนี้ - Event Reason = New Hire - Hire Date = Today - Date of Birth = Age < 60 - Gender = Male - Nationality = Non TH - Employee Group = C - Expat Inbound ค่าที่ต้องคีย์ ชุดข้อมูลจากถัง SIT ตรวจสอบเมื่อ 28 ส.ค. 2026 ชุดข้อมูล TD-48 - Business Group = CRC - Business Unit = CDG (10000075) Policy Profile = CDS - Company = C001 - Position = 40001381 Job Code = GAB10.21 - Department = 30046501 Store/ Branch Code = T134_1714 SSO Location = T134 - Division = 20000087 Cost Center = C00126100 Work Location = 50000087 - Work Schedule = D05H0830 Holiday Calendar = 01 - Personnel Grade (PG) = 12 - Employee Group = C - Expat Inbound Employee Sub Group = 12 - Employment Type = F สถานะ Position = ว่าง - ตาราง time_status_mapping กำหนด Time Status = 9 O.T. Flag = no - สิทธิ์ลาพักผ่อนปีแรก = 6 เงื่อนไขเฉพาะของเคสนี้ - คีย์ Employee Group = C - Expat Inbound Employee Sub Group = 12 ตามชุดข้อมูล - Hire Date = วันที่ทดสอบ Gender = Male Nationality = ไม่ใช่ไทย - ต้องกรอกเลขหนังสือเดินทางและใบอนุญาตทำงานที่ยังไม่หมดอายุ - รายละเอียดเต็มดูชีท Hiring Test Data | J17: EC > Manage Pending Recruits | K17: 1. Login ด้วย <HR_ADMIN_ACCOUNT> - ไปที่ EC > Manage Pending Recruits - เปิดรายการพนักงานที่รับมาจาก RCM - ตรวจสอบข้อมูลที่ได้รับจาก RCM - ตรวจสอบว่ารายการสามารถเปิดเพื่อกรอกข้อมูลส่วนที่เหลือต่อได้ 2. กรอกข้อมูลส่วนที่เหลือให้ครบถ้วน - กำหนด Event Reason = New Hire - กำหนด Hire Date = Today - กำหนด Nationality = Non TH - กำหนด Employee Group = C - Expat Inbound - กรอกข้อมูล Mandatory อื่นให้ครบถ้วนเพื่อให้สามารถ Submit ได้ 3. กด Submit เพื่อสร้างพนักงานใหม่ 4. ตรวจสอบ Employee Profile ใน EC - ค้นหาพนักงานด้วย Employee ID - ตรวจสอบ Event Reason = New Hire - ตรวจสอบ Hire Date = Today - ตรวจสอบ Nationality = Non TH - ตรวจสอบ Employee Group = C - Expat Inbound 5. ตรวจสอบ Inpatriate สำหรับ Expat Inbound - ตรวจสอบ Tax Residency - ตรวจสอบ Tax Treaty - อ้างอิง TC-E2E-115 (Inpatriate) | L17: EC - RCM สร้างพนักงานใน EC โดยตรง ไม่ต้องให้ HR Admin กด Submit (Q&A ข้อ 7 และ 53) - HR Admin เปิดโปรไฟล์พนักงานที่ระบบสร้างไว้แล้ว เพื่อกรอกข้อมูลส่วนที่เหลือได้ - ระบบสร้างพนักงานใหม่สำเร็จโดยอัตโนมัติเมื่อรับข้อมูลจาก RCM - Event Reason = New Hire - Hire Date = Today - Nationality = Non TH - Employee Group = C - Expat Inbound - พบ National ID ซ้ำ ถ้าพนักงานเดิมเป็น inactive ระบบสร้าง Employee ID ใหม่ ถ้าเป็น active ระบบ update ข้อมูลที่ส่งเข้ามาทับ (Q&A ข้อ 44) Inpatriate - พนักงาน Expat Inbound ถูกตรวจ Tax Residency และ Tax Treaty ตาม TC-E2E-115 - รอบงานจริงและวิธียืนยันการรับไฟล์ = ? OQ-HIR-46 - ช่องที่ระบบล็อกไม่ให้แก้หลังรับข้อมูลจาก RCM = ? OQ-HIR-23 - การ Mapping Event Reason จาก RCM ไป EC และพฤติกรรมกรณีได้รับค่าที่ไม่รู้จัก = ? OQ-HIR-27 จุดที่ยังไม่มีคำตอบในเคสนี้ ให้รันจริงแล้วบันทึกค่าที่ระบบแสดงลงช่อง Actual Result Image และช่อง Note เพื่อใช้เป็นคำตอบ แล้วส่งให้ BA หรือ SA ยืนยัน หมายเลขคำถามที่ต้องเก็บคำตอบระหว่างรัน OQ-HIR-46, OQ-HIR-23, OQ-HIR-27 | M17: Cancelled | Q17: RCM ต่างแค่วันเริ่มงาน ซ้ำ 014 ต่างจาก HIR-EC-014 แค่สัญชาติ Non-TH กับ Group C ส่วนที่ต่างจริงคือ "ตรวจ Tax Residency และ Tax Treaty" ซึ่ง Expected ชี้ไป TC-E2E-115 เอง = ฝั่งภาษี ไม่ใช่ EC ส่วนต่างชาติผ่าน Key-in มี HIR-EC-005 ครอบแล้ว
A18: 17 | B18: Hiring | C18: E2E-17 | D18: Hiring | RCM - Success | Replacement | Hire Date = Today | Age < 60 | Female | TH | B - Expat Outbound | E18: HIR-EC-017 | F18: Positive | G18: Medium | H18: ตรวจสอบการจ้างพนักงานแบบ Replacement ผ่าน RCM สำเร็จ กรณีวันเริ่มงานวันนี้ อายุ < 60 ปี เพศหญิง สัญชาติไทย และกลุ่มพนักงาน Expat Outbound | I18: - Entry Route = RCM เงื่อนไขของเคสนี้ - Event Reason = Replacement - Hire Date = Today - Date of Birth = Age < 60 - Gender = Female - Nationality = Thai - Employee Group = B - Expat Outbound - Replaced Employee ID = Employee ID ที่มีอยู่จริงในระบบและสามารถใช้สำหรับ Replacement ได้ ค่าที่ต้องคีย์ ชุดข้อมูลจากถัง SIT ตรวจสอบเมื่อ 28 ส.ค. 2026 ชุดข้อมูล TD-47 - Business Group = CRC - Business Unit = CDG (10000075) Policy Profile = CDS - Company = C001 - Position = 40001378 Job Code = MKC10.21 - Department = 30000654 Store/ Branch Code = T134_1714 SSO Location = T134 - Division = 20000087 Cost Center = C00151100 Work Location = 50000087 - Work Schedule = D05H0830 Holiday Calendar = 01 - Personnel Grade (PG) = 12 - Employee Group = B - Expat Outbound Employee Sub Group = 12 - Employment Type = F สถานะ Position = ว่าง - ตาราง time_status_mapping กำหนด Time Status = 9 O.T. Flag = no - สิทธิ์ลาพักผ่อนปีแรก = 6 เงื่อนไขเฉพาะของเคสนี้ - คีย์ Employee Group = B - Expat Outbound Employee Sub Group = 12 ตามชุดข้อมูล - Hire Date = วันที่ทดสอบ Gender = Female Nationality = Thai - Replaced Employee ID = Employee ID ที่ลาออกแล้วและเคยครอง Position 40001378 - รายละเอียดเต็มดูชีท Hiring Test Data | J18: EC > Manage Pending Recruits | K18: 1. Login ด้วย <HR_ADMIN_ACCOUNT> - ไปที่ EC > Manage Pending Recruits - เปิดรายการพนักงานที่รับมาจาก RCM - ตรวจสอบข้อมูลที่ได้รับจาก RCM 2. กรอกข้อมูลส่วนที่เหลือให้ครบถ้วน - กำหนด Event Reason = Replacement - กำหนด Hire Date = Today - กำหนด Employee Group = B - Expat Outbound - ตรวจสอบว่าระบบแสดง Replaced Employee ID และกำหนดเป็น Required - กรอก Replaced Employee ID ตาม Test Data - กรอกข้อมูล Mandatory อื่นให้ครบถ้วนเพื่อให้สามารถ Submit ได้ 3. ตรวจสอบ Replaced Employee ID - ตรวจสอบว่าระบบ Validate ว่า Replaced Employee ID มีอยู่จริงก่อน Submit 4. กด Submit เพื่อสร้างพนักงานใหม่ 5. ตรวจสอบ Employee Profile ใน EC - ค้นหาพนักงานด้วย Employee ID - ตรวจสอบ Event Reason = Replacement - ตรวจสอบ Hire Date = Today - ตรวจสอบ Employee Group = B - Expat Outbound - ตรวจสอบ Replaced Employee ID 6. ตรวจสอบผลหลังสร้างพนักงาน - ตรวจสอบผลของ Replacement และ Expat Outbound ร่วมกันตาม Business Rule ที่ได้รับการยืนยัน | L18: EC - RCM สร้างพนักงานใน EC โดยตรง ไม่ต้องให้ HR Admin กด Submit (Q&A ข้อ 7 และ 53) - HR Admin เปิดโปรไฟล์พนักงานที่ระบบสร้างไว้แล้ว เพื่อกรอกข้อมูลส่วนที่เหลือได้ - ระบบสร้างพนักงานใหม่สำเร็จโดยอัตโนมัติเมื่อรับข้อมูลจาก RCM - Event Reason = Replacement - Hire Date = Today - Employee Group = B - Expat Outbound - พบ National ID ซ้ำ ถ้าพนักงานเดิมเป็น inactive ระบบสร้าง Employee ID ใหม่ ถ้าเป็น active ระบบ update ข้อมูลที่ส่งเข้ามาทับ (Q&A ข้อ 44) - ระบบไม่ตรวจว่า Replaced Employee ID ต้องอยู่ Position / Company / Business Unit เดียวกัน และไม่ตรวจสถานะ active ขอเพียงระบบค้นหาเจอ (Q&A ข้อ 34, 35, 37) Replaced Employee ID - เมื่อ Event Reason = Replacement ระบบแสดง Replaced Employee ID และกำหนดเป็น Required - ระบบตรวจ Replaced Employee ID มีอยู่จริงก่อนอนุญาตให้ Submit - หลัง Submit สำเร็จ ระบบบันทึก Replaced Employee ID ตามค่าที่กรอก - รอบงานจริงและวิธียืนยันการรับไฟล์ = ? OQ-HIR-46 - ช่องที่ระบบล็อกไม่ให้แก้หลังรับข้อมูลจาก RCM = ? OQ-HIR-23 - การ Mapping Event Reason จาก RCM ไป EC และพฤติกรรมกรณีได้รับค่าที่ไม่รู้จัก = ? OQ-HIR-27 จุดที่ยังไม่มีคำตอบในเคสนี้ ให้รันจริงแล้วบันทึกค่าที่ระบบแสดงลงช่อง Actual Result Image และช่อง Note เพื่อใช้เป็นคำตอบ แล้วส่งให้ BA หรือ SA ยืนยัน หมายเลขคำถามที่ต้องเก็บคำตอบระหว่างรัน OQ-HIR-46, OQ-HIR-23, OQ-HIR-27 | M18: Not Start | Q18: ตัดจากเคส E2E-17 ไฟล์ HR_SIT_E2E_V.0.1 (28).xlsx ชีท E2E All module โมดูลที่เคสเต็มเกี่ยวข้อง REC / EC / BE / TM / PY / Notification ยกไปรอบเชื่อมโมดูล ผลที่คาดหวังฝั่ง Notification / TM / BE / PY ยกไปรอบเชื่อมโมดูล ขั้นตอน รับข้อมูลพนักงานจากระบบสรรหา (RCM) เคสนี้มีจุดที่ยังไม่มีคำตอบ 3 จุด ไม่ต้องรอคำตอบก่อนรัน ให้รันเก็บค่าที่ระบบแสดงจริงแล้วแจ้ง BA หรือ SA ยืนยันหลังรัน ต้องมีรายการที่มาจากระบบสรรหาอยู่ในระบบก่อนเริ่ม ถ้ายังไม่เชื่อมระบบสรรหา ให้ทีมพัฒนายิงข้อมูลตัวอย่างเข้ามาให้หนึ่งรายการ คำถามข้อ 8 ในชีท Quesitons ตอบแล้วเมื่อ 30 ก.ค. 2026 ว่าฝั่ง EC ไม่ต้องให้ HR กด Submit แต่ขั้นตอนของเคสนี้ยังเขียนให้ HR กรอกและกด Submit ให้รันเพื่อดูพฤติกรรมจริง แล้วแจ้งกลับให้แก้ขั้นตอนในไฟล์ทีม
A19: 18 | B19: Hiring | C19: E2E-18 | D19: Hiring | RCM - Success | Replacement | Hire Date = Today | Age > 60 | Female | TH | D - Retirement | E19: HIR-EC-018 | F19: Positive | G19: Medium | H19: ตรวจสอบการจ้างพนักงานแบบ Replacement ผ่าน RCM สำเร็จ กรณีวันเริ่มงานวันนี้ อายุ > 60 ปี เพศหญิง สัญชาติไทย และกลุ่มพนักงาน Retirement | I19: - Entry Route = RCM เงื่อนไขของเคสนี้ - Event Reason = Replacement - Hire Date = Today - Date of Birth = Age > 60 - Gender = Female - Nationality = Thai - Employee Group = D - Retirement - Replaced Employee ID = Employee ID ที่มีอยู่จริงในระบบและสามารถใช้สำหรับ Replacement ได้ ค่าที่ต้องคีย์ ชุดข้อมูลจากถัง SIT ตรวจสอบเมื่อ 28 ส.ค. 2026 ชุดข้อมูล TD-49 - Business Group = CRC - Business Unit = CFR (10000003) Policy Profile = CFR - Company = C004 - Position = 40004879 Job Code = FAA10.41 - Department = 30002069 Store/ Branch Code = T170_1750 SSO Location = T170 - Division = 20001368 Cost Center = C00445700 Work Location = 50000034 - Work Schedule = D06H0800 Holiday Calendar = 03 - Personnel Grade (PG) = 12 - Employee Group = D - Retirement Employee Sub Group = 12 - Employment Type = F สถานะ Position = ว่าง - ตาราง time_status_mapping กำหนด Time Status = 2 O.T. Flag = yes - สิทธิ์ลาพักผ่อนปีแรก = 6 เงื่อนไขเฉพาะของเคสนี้ - คีย์ Employee Group = D - Retirement Employee Sub Group = 12 ตามชุดข้อมูล - Date of Birth = ทำให้อายุมากกว่า 60 ปี ณ วันที่จ้าง - Replaced Employee ID = Employee ID ที่ลาออกแล้วและเคยครอง Position 40004879 - รายละเอียดเต็มดูชีท Hiring Test Data | J19: EC > Manage Pending Recruits | K19: 1. Login ด้วย <HR_ADMIN_ACCOUNT> - ไปที่ EC > Manage Pending Recruits - เปิดรายการพนักงานที่รับมาจาก RCM - ตรวจสอบข้อมูลที่ได้รับจาก RCM 2. กรอกข้อมูลส่วนที่เหลือให้ครบถ้วนตาม Test Data - กำหนด Event Reason = Replacement - กำหนด Hire Date = Today - กำหนด Date of Birth ให้มี Age > 60 ณ Hire Date - กำหนด Nationality = Thai - กำหนด Employee Group = D - Retirement - ตรวจสอบว่าระบบแสดง Replaced Employee ID และกำหนดเป็น Required - กรอก Replaced Employee ID ตาม Test Data - กรอกข้อมูล Mandatory อื่นให้ครบถ้วนเพื่อให้สามารถ Submit ได้ 3. ตรวจสอบ Replaced Employee ID - ตรวจสอบว่าระบบ Validate ว่า Replaced Employee ID มีอยู่จริงก่อน Submit 4. กด Submit เพื่อสร้างพนักงานใหม่ 5. ตรวจสอบ Employee Profile ใน EC - ค้นหาพนักงานด้วย Employee ID - ตรวจสอบ Event Reason = Replacement - ตรวจสอบ Hire Date = Today - ตรวจสอบ Age > 60 ณ Hire Date - ตรวจสอบ Employee Group = D - Retirement - ตรวจสอบ Replaced Employee ID 6. ตรวจสอบกรณี Employee Group = D - Retirement และ Age > 60 - บันทึกผลที่พบสำหรับพนักงานที่ถูกกำหนด Employee Group = D - Retirement ตั้งแต่เริ่มงาน - ตรวจสอบผลของ SSO Exemption สำหรับ Age > 60 | L19: EC - RCM สร้างพนักงานใน EC โดยตรง ไม่ต้องให้ HR Admin กด Submit (Q&A ข้อ 7 และ 53) - HR Admin เปิดโปรไฟล์พนักงานที่ระบบสร้างไว้แล้ว เพื่อกรอกข้อมูลส่วนที่เหลือได้ - Event Reason = Replacement - Hire Date = Today - Age > 60 ณ Hire Date - Employee Group = D - Retirement - พบ National ID ซ้ำ ถ้าพนักงานเดิมเป็น inactive ระบบสร้าง Employee ID ใหม่ ถ้าเป็น active ระบบ update ข้อมูลที่ส่งเข้ามาทับ (Q&A ข้อ 44) - ระบบไม่ตรวจว่า Replaced Employee ID ต้องอยู่ Position / Company / Business Unit เดียวกัน และไม่ตรวจสถานะ active ขอเพียงระบบค้นหาเจอ (Q&A ข้อ 34, 35, 37) Replacement - เมื่อ Event Reason = Replacement ระบบแสดง Replaced Employee ID และกำหนดเป็น Required - ระบบตรวจ Replaced Employee ID มีอยู่จริงก่อนอนุญาตให้ Submit - หลัง Submit สำเร็จ ระบบบันทึก Replaced Employee ID ตามค่าที่กรอก - D - Retirement - ระบบบันทึก Employee Group = D - Retirement ตามข้อมูลที่ระบุ - Age > 60 / SSO - รอบงานจริงและวิธียืนยันการรับไฟล์ = ? OQ-HIR-46 - ช่องที่ระบบล็อกไม่ให้แก้หลังรับข้อมูลจาก RCM = ? OQ-HIR-23 - การ Mapping Event Reason จาก RCM ไป EC และพฤติกรรมกรณีได้รับค่าที่ไม่รู้จัก = ? OQ-HIR-27 - ความหมายของ Employee Group = D - Retirement และการรองรับการกำหนดกลุ่มนี้ตั้งแต่วันจ้าง = ? OQ-HIR-65 - ผลของ SSO Exemption สำหรับ Age > 60 = ? OQ-HIR-43 OQ-HIR-62 จุดที่ยังไม่มีคำตอบในเคสนี้ ให้รันจริงแล้วบันทึกค่าที่ระบบแสดงลงช่อง Actual Result Image และช่อง Note เพื่อใช้เป็นคำตอบ แล้วส่งให้ BA หรือ SA ยืนยัน หมายเลขคำถามที่ต้องเก็บคำตอบระหว่างรัน OQ-HIR-46, OQ-HIR-23, OQ-HIR-27, OQ-HIR-65, OQ-HIR-43, OQ-HIR-62 | M19: Cancelled | Q19: Replacement ผ่าน RCM ซ้ำ HIR-EC-017 ทุกบรรทัด ต่างแค่ Employee Group = D กับอายุ > 60 ซึ่ง HIR-EC-020 มี Group D อยู่แล้ว และอายุ > 60 มี HIR-EC-002
A20: 19 | B20: Hiring | C20: E2E-19 | D20: Hiring | RCM - Success | Replacement | Hire Date > Today | Age < 60 | Male | TH | F - DVT | E20: HIR-EC-019 | F20: Positive | G20: Medium | H20: ตรวจสอบการจ้างพนักงานแบบ Replacement ผ่าน RCM สำเร็จ กรณีวันเริ่มงานในอนาคต อายุ < 60 ปี เพศชาย สัญชาติไทย และกลุ่มพนักงาน DVT | I20: - Entry Route = RCM เงื่อนไขของเคสนี้ - Event Reason = Replacement - Hire Date > Today - Date of Birth = Age < 60 - Gender = Male - Nationality = Thai - Employee Group = F - DVT - Replaced Employee ID = Employee ID ที่มีอยู่จริงในระบบและสามารถใช้สำหรับ Replacement ได้ - กรอก DVT-specific fields ทั้ง 9 ช่อง ได้แก่ DVT Project Name / Partner University / Type / Degree Level / Course / Course of Time / Academic Year / Graduation Date / Bonding End Date - University Type = ระบุให้ชัดเจนเป็น DVT Partnered University หรือ Other University ก่อน Execute ค่าที่ต้องคีย์ ชุดข้อมูลจากถัง SIT ตรวจสอบเมื่อ 28 ส.ค. 2026 ชุดข้อมูล TD-53 - Business Group = CRC - Business Unit = CFR (10000003) Policy Profile = CFR - Company = C004 - Position = 40201447 Job Code = STA10.03 - Department = 30041915 Store/ Branch Code = T759_2116 SSO Location = T759 - Division = 20001352 Cost Center = C00426100 Work Location = 50001226 - Work Schedule = D06H0800 Holiday Calendar = 03 - Personnel Grade (PG) = NA - Employee Group = F - DVT Employee Sub Group = D1-Partner university - Employment Type = P สถานะ Position = ว่าง - ตาราง time_status_mapping กำหนด Time Status = 1 O.T. Flag = yes - สิทธิ์ลาพักผ่อนปีแรก = ? ไม่มีแถว Quota ที่ตรงกับกลุ่ม F ดู OQ-HIR-111 เงื่อนไขเฉพาะของเคสนี้ - คีย์ Employee Group = F - DVT Employee Sub Group = D1-Partner university ตามชุดข้อมูล - Hire Date = วันในอนาคต Gender = Male Nationality = Thai - Replaced Employee ID = Employee ID ที่ลาออกแล้วและเคยครอง Position 40201447 - กรอกช่องข้อมูลนักศึกษาทวิภาคีครบทั้ง 9 ช่อง - รายละเอียดเต็มดูชีท Hiring Test Data | J20: EC > Manage Pending Recruits | K20: 1. Login ด้วย <HR_ADMIN_ACCOUNT> - ไปที่ EC > Manage Pending Recruits - เปิดรายการพนักงานที่รับมาจาก RCM - ตรวจสอบข้อมูลที่ได้รับจาก RCM 2. กรอกข้อมูลส่วนที่เหลือให้ครบถ้วนตาม Test Data - กำหนด Event Reason = Replacement - กำหนด Hire Date > Today - กำหนด Nationality = Thai - กำหนด Employee Group = F - DVT - ตรวจสอบว่าระบบแสดง Replaced Employee ID และกำหนดเป็น Required - กรอก Replaced Employee ID ตาม Test Data - กรอก DVT-specific fields ทั้ง 9 ช่อง - ระบุ University Type เป็น DVT Partnered University หรือ Other University - กรอกข้อมูล Mandatory อื่นให้ครบถ้วนเพื่อให้สามารถ Submit ได้ 3. กด Submit เพื่อสร้างพนักงานใหม่ 4. ตรวจสอบ Employee Profile ใน EC - ค้นหาพนักงานด้วย Employee ID - ตรวจสอบ Event Reason = Replacement - ตรวจสอบ Hire Date > Today - ตรวจสอบ Employee Group = F - DVT - ตรวจสอบ Replaced Employee ID - ตรวจสอบข้อมูล DVT ทั้ง 9 ช่อง 5. ตรวจสอบผลของ Future Hire Date - ตรวจสอบว่า Employee Record ถูกสร้างหลัง Submit - ตรวจสอบ Employee Status ก่อนถึง Hire Date จริง 6. ตรวจสอบข้อมูล DVT ตามประเภทมหาวิทยาลัย - ตรวจสอบผลตาม University Type ที่กำหนด โดยอ้างอิงเงื่อนไขของ E2E-09 | L20: EC - RCM สร้างพนักงานใน EC โดยตรง ไม่ต้องให้ HR Admin กด Submit (Q&A ข้อ 7 และ 53) - HR Admin เปิดโปรไฟล์พนักงานที่ระบบสร้างไว้แล้ว เพื่อกรอกข้อมูลส่วนที่เหลือได้ - ระบบสร้าง Employee Record ได้ทันทีหลัง Submit โดยไม่ต้องรอถึง Hire Date - Event Reason = Replacement - Hire Date = วันที่ในอนาคตและมากกว่า Today - Employee Group = F - DVT - พบ National ID ซ้ำ ถ้าพนักงานเดิมเป็น inactive ระบบสร้าง Employee ID ใหม่ ถ้าเป็น active ระบบ update ข้อมูลที่ส่งเข้ามาทับ (Q&A ข้อ 44) - ระบบไม่ตรวจว่า Replaced Employee ID ต้องอยู่ Position / Company / Business Unit เดียวกัน และไม่ตรวจสถานะ active ขอเพียงระบบค้นหาเจอ (Q&A ข้อ 34, 35, 37) Replacement - เมื่อ Event Reason = Replacement ระบบแสดง Replaced Employee ID และกำหนดเป็น Required - หลัง Submit สำเร็จ ระบบบันทึก Replaced Employee ID ตามค่าที่กรอก DVT - เมื่อ Employee Group = F - DVT ระบบแสดง DVT-specific fields ทั้ง 9 ช่อง ได้แก่ DVT Project Name / Partner University / Type / Degree Level / Course / Course of Time / Academic Year / Graduation Date / Bonding End Date - ระบบบันทึกข้อมูล DVT ทั้ง 9 ช่องตามค่าที่กรอก - ต้องกำหนด University Type เป็น DVT Partnered University หรือ Other University ก่อน Execute เนื่องจากทั้งสองประเภทมีผลต่างกันตามเงื่อนไขของ E2E-09 - รอบงานจริงและวิธียืนยันการรับไฟล์ = ? OQ-HIR-46 - ช่องที่ระบบล็อกไม่ให้แก้หลังรับข้อมูลจาก RCM = ? OQ-HIR-23 - การ Mapping Event Reason จาก RCM ไป EC และพฤติกรรมกรณีได้รับค่าที่ไม่รู้จัก = ? OQ-HIR-27 - Employee Status = Active ทันทีหลัง Submit แม้ Hire Date ยังไม่ถึง (Q&A ข้อ 32) จุดที่ยังไม่มีคำตอบในเคสนี้ ให้รันจริงแล้วบันทึกค่าที่ระบบแสดงลงช่อง Actual Result Image และช่อง Note เพื่อใช้เป็นคำตอบ แล้วส่งให้ BA หรือ SA ยืนยัน หมายเลขคำถามที่ต้องเก็บคำตอบระหว่างรัน OQ-HIR-46, OQ-HIR-23, OQ-HIR-27 | M20: Not Start
A21: 20 | B21: Hiring | C21: E2E-20 | D21: Hiring | RCM - Success | Migration | Hire Date >= Today | Age = 60 | Male | TH | D - Retirement | Probation Exemption = Yes | E21: HIR-EC-020 | F21: Positive | G21: Medium | H21: ตรวจสอบการจ้างพนักงานแบบ Migration ผ่าน RCM สำเร็จ กรณีวันเริ่มงานตั้งแต่วันนี้เป็นต้นไป อายุ 60 ปี เพศชาย สัญชาติไทย กลุ่มพนักงาน Retirement และได้รับยกเว้นทดลองงาน | I21: - Entry Route = RCM เงื่อนไขของเคสนี้ - Event Reason = Migration - Hire Date > = Today - Date of Birth = Age = 60 พอดี ณ Hire Date - Gender = Male - Nationality = Thai - Employee Group = D - Retirement - Probation Exemption = Yes ค่าที่ต้องคีย์ ชุดข้อมูลจากถัง SIT ตรวจสอบเมื่อ 28 ส.ค. 2026 ชุดข้อมูล TD-49 - Business Group = CRC - Business Unit = CFR (10000003) Policy Profile = CFR - Company = C004 - Position = 40004879 Job Code = FAA10.41 - Department = 30002069 Store/ Branch Code = T170_1750 SSO Location = T170 - Division = 20001368 Cost Center = C00445700 Work Location = 50000034 - Work Schedule = D06H0800 Holiday Calendar = 03 - Personnel Grade (PG) = 12 - Employee Group = D - Retirement Employee Sub Group = 12 - Employment Type = F สถานะ Position = ว่าง - ตาราง time_status_mapping กำหนด Time Status = 2 O.T. Flag = yes - สิทธิ์ลาพักผ่อนปีแรก = 6 เงื่อนไขเฉพาะของเคสนี้ - คีย์ Employee Group = D - Retirement Employee Sub Group = 12 ตามชุดข้อมูล - Event Reason = Migration Probation Exemption = Yes - Date of Birth = ทำให้อายุครบ 60 ปีพอดี ณ วันที่จ้าง - รายละเอียดเต็มดูชีท Hiring Test Data | J21: EC > Manage Pending Recruits | K21: 1. Login ด้วย <HR_ADMIN_ACCOUNT> - ไปที่ EC > Manage Pending Recruits - เปิดรายการพนักงานที่รับมาจาก RCM - ตรวจสอบข้อมูลที่ได้รับจาก RCM 2. กรอกข้อมูลส่วนที่เหลือให้ครบถ้วนตาม Test Data - กำหนด Event Reason = Migration - กำหนด Hire Date >= Today - กำหนด Date of Birth ให้มี Age = 60 พอดี ณ Hire Date - กำหนด Employee Group = D - Retirement - กำหนด Probation Exemption = Yes - กรอกข้อมูล Mandatory อื่นให้ครบถ้วนเพื่อให้สามารถ Submit ได้ 3. กด Submit เพื่อสร้างพนักงาน 4. ตรวจสอบ Employee Profile ใน EC - ค้นหาพนักงานด้วย Employee ID - ตรวจสอบ Event Reason = Migration - ตรวจสอบ Hire Date >= Today - ตรวจสอบ Age = 60 พอดี ณ Hire Date - ตรวจสอบ Employee Group = D - Retirement - ตรวจสอบ Probation Exemption = Yes - ตรวจสอบ Pass Probation Date - ตรวจสอบว่าไม่แสดง Probationary Period End Date - ตรวจสอบว่าไม่มี Probation Record สำหรับพนักงานรายนี้ 5. ตรวจสอบ Employee Group = D - Retirement - บันทึกพฤติกรรมของพนักงานที่กำหนด D - Retirement ตั้งแต่เริ่มงาน 6. ตรวจสอบ Age = 60 Boundary - ตรวจสอบผลของเงื่อนไข Age = 60 พอดี โดยอ้างอิง Boundary เดียวกับ E2E-06 7. ตรวจสอบ Probation Exemption = Yes - ตรวจสอบ Pass Probation Date - ตรวจสอบว่าไม่มี Probationary Period End Date - ตรวจสอบว่าไม่มี Probation Record | L21: EC - RCM สร้างพนักงานใน EC โดยตรง ไม่ต้องให้ HR Admin กด Submit (Q&A ข้อ 7 และ 53) - HR Admin เปิดโปรไฟล์พนักงานที่ระบบสร้างไว้แล้ว เพื่อกรอกข้อมูลส่วนที่เหลือได้ - Hire Date >= Today ตามข้อมูลที่ระบุ - Migration + RCM - D - Retirement - Employee Group = D - Retirement ตาม Scenario - Age = 60 - Date of Birth / Hire Date ต้องสัมพันธ์กันและคำนวณได้ Age = 60 พอดี ณ Hire Date - พบ National ID ซ้ำ ถ้าพนักงานเดิมเป็น inactive ระบบสร้าง Employee ID ใหม่ ถ้าเป็น active ระบบ update ข้อมูลที่ส่งเข้ามาทับ (Q&A ข้อ 44) - ระบบใช้ Employee ID เป็นตัวชี้ว่าเป็นรายการ Migration เดิม และไม่สร้างพนักงานซ้ำ (Q&A ข้อ 41) - ค่าที่ระบบเก่ามีแต่ระบบใหม่ไม่มี ระบบแสดงค่าเดิมตามที่ migrate มา (Q&A ข้อ 18) Probation Exemption - Probation Exemption = Yes - ระบบกำหนด Probationary Period End Date = Hire Date (Q&A ข้อ 22) - ระบบไม่แสดง Probationary Period End Date - ระบบไม่สร้าง Probation Record สำหรับพนักงานรายนี้ - รอบงานจริงและวิธียืนยันการรับไฟล์ = ? OQ-HIR-46 - ช่องที่ระบบล็อกไม่ให้แก้หลังรับข้อมูลจาก RCM = ? OQ-HIR-23 - การ Mapping Event Reason จาก RCM ไป EC และพฤติกรรมกรณีได้รับค่าที่ไม่รู้จัก = ? OQ-HIR-27 - การรองรับ Event Reason = Migration ผ่าน Entry Route = RCM = ? OQ-HIR-66 - การรองรับ Employee Group = D - Retirement สำหรับการจ้างพนักงานตั้งแต่วันแรก = ? OQ-HIR-65 - ผลว่า Age = 60 พอดีอยู่ในเงื่อนไขได้รับยกเว้นหรือไม่ = ? OQ-HIR-62 จุดที่ยังไม่มีคำตอบในเคสนี้ ให้รันจริงแล้วบันทึกค่าที่ระบบแสดงลงช่อง Actual Result Image และช่อง Note เพื่อใช้เป็นคำตอบ แล้วส่งให้ BA หรือ SA ยืนยัน หมายเลขคำถามที่ต้องเก็บคำตอบระหว่างรัน OQ-HIR-46, OQ-HIR-23, OQ-HIR-27, OQ-HIR-66, OQ-HIR-65, OQ-HIR-62 | M21: Not Start | Q21: ตัดจากเคส E2E-20 ไฟล์ HR_SIT_E2E_V.0.1 (28).xlsx ชีท E2E All module โมดูลที่เคสเต็มเกี่ยวข้อง REC / EC / BE / TM / PY / Notification ยกไปรอบเชื่อมโมดูล ผลที่คาดหวังฝั่ง Notification / TM / BE / PY ยกไปรอบเชื่อมโมดูล ขั้นตอน รับข้อมูลพนักงานจากระบบสรรหา (RCM) / ตรวจสอบ Combination ของ Migration + RCM เคสนี้มีจุดที่ยังไม่มีคำตอบ 6 จุด ไม่ต้องรอคำตอบก่อนรัน ให้รันเก็บค่าที่ระบบแสดงจริงแล้วแจ้ง BA หรือ SA ยืนยันหลังรัน ต้องมีรายการที่มาจากระบบสรรหาอยู่ในระบบก่อนเริ่ม ถ้ายังไม่เชื่อมระบบสรรหา ให้ทีมพัฒนายิงข้อมูลตัวอย่างเข้ามาให้หนึ่งรายการ คำถามข้อ 8 ในชีท Quesitons ตอบแล้วเมื่อ 30 ก.ค. 2026 ว่าฝั่ง EC ไม่ต้องให้ HR กด Submit แต่ขั้นตอนของเคสนี้ยังเขียนให้ HR กรอกและกด Submit ให้รันเพื่อดูพฤติกรรมจริง แล้วแจ้งกลับให้แก้ขั้นตอนในไฟล์ทีม
A22: 21 | B22: Hiring | C22: E2E-21 | D22: Hiring | Keyin - Success | New Hire | DVT Student | Verify No Social Security Deduction | E22: HIR-EC-021 | F22: Positive | G22: High | H22: ตรวจสอบการจ้างพนักงานใหม่แบบ Key-in สำเร็จ กรณี DVT Student และไม่มีการหักประกันสังคม | I22: - Login = <HR_ADMIN_ACCOUNT> เงื่อนไขของเคสนี้ - Employee Group = F - DVT - Hire Date = วันแรกของงวดเวลาปัจจุบัน - ข้อมูล Mandatory อื่นที่จำเป็นสำหรับการสร้างพนักงานพร้อมใช้งาน ค่าที่ต้องคีย์ ชุดข้อมูลจากถัง SIT ตรวจสอบเมื่อ 28 ส.ค. 2026 ชุดข้อมูล TD-53 - Business Group = CRC - Business Unit = CFR (10000003) Policy Profile = CFR - Company = C004 - Position = 40201447 Job Code = STA10.03 - Department = 30041915 Store/ Branch Code = T759_2116 SSO Location = T759 - Division = 20001352 Cost Center = C00426100 Work Location = 50001226 - Work Schedule = D06H0800 Holiday Calendar = 03 - Personnel Grade (PG) = NA - Employee Group = F - DVT Employee Sub Group = D1-Partner university - Employment Type = P สถานะ Position = ว่าง - ตาราง time_status_mapping กำหนด Time Status = 1 O.T. Flag = yes - สิทธิ์ลาพักผ่อนปีแรก = ? ไม่มีแถว Quota ที่ตรงกับกลุ่ม F ดู OQ-HIR-111 เงื่อนไขเฉพาะของเคสนี้ - คีย์ Employee Group = F - DVT Employee Sub Group = D1-Partner university ตามชุดข้อมูล - Position 40201447 ชื่อ Student อยู่ใน Business Group CRC Business Unit CFR - ใช้ตรวจว่าระบบไม่หักประกันสังคมของกลุ่มนักศึกษาทวิภาคี - รายละเอียดเต็มดูชีท Hiring Test Data | J22: EC > Hire & Onboard (New Hire) | K22: 1. Login ด้วย <HR_ADMIN_ACCOUNT> - ไปที่หน้าสร้างพนักงานใหม่ 2. กรอกข้อมูลพนักงานใหม่ - กำหนด Employee Group = F - DVT - กำหนด Hire Date = วันแรกของงวดเวลาปัจจุบัน - กรอกข้อมูล Mandatory อื่นให้ครบถ้วนเพื่อให้สามารถ Submit ได้ 3. กด Submit เพื่อสร้างพนักงานใหม่ 4. ตรวจสอบ Employee Profile ใน EC - ค้นหาพนักงานด้วย Employee ID ที่สร้างขึ้น - ตรวจสอบ Employee Status - ตรวจสอบ Employee Group = F - DVT | L22: EC - ระบบสร้าง Employee ID เป็นตัวเลข 8 หลัก โดยหลักแรกเป็น 2 - Employee Status = Active - Employee Group = F - DVT ซึ่งเป็นกลุ่มนักศึกษาทวิภาคี - ฝั่ง EC ไม่มีช่องสำหรับตรวจสถานะการหักประกันสังคมโดยตรง | M22: Cancelled | Q22: EC ไม่มีฟิลด์ประกันสังคม → เป็นเรื่องของ PY
A23: 22 | B23: Hiring | C23: E2E-22 | D23: Hiring | Keyin - Success | New Hire | Probation Exemption | Verify No Probationary Period End Date / Probation Task | E23: HIR-EC-022 | F23: Positive | G23: High | H23: ตรวจสอบการจ้างพนักงานใหม่แบบ Key-in สำเร็จ กรณีได้รับยกเว้นทดลองงาน โดยไม่มี Probationary Period End Date และ Probation Task | I23: - Login = <HR_ADMIN_ACCOUNT> เงื่อนไขของเคสนี้ - Probation Exemption = Yes - Hire Date = วันแรกของงวดเวลาปัจจุบัน - Employee Group / Employee Type = ใช้กลุ่มที่รองรับ Probation Exemption โดยกลุ่มที่ได้รับการยกเว้นทั้งหมดรอยืนยัน ค่าที่ต้องคีย์ ชุดข้อมูลจากถัง SIT ตรวจสอบเมื่อ 28 ส.ค. 2026 ชุดข้อมูล TD-01 - Business Group = CRC - Business Unit = CDG (10000075) Policy Profile = CDS - Company = C001 - Position = 40106337 Job Code = MKB12.12 - Department = 30042174 Store/ Branch Code = T153_1733 SSO Location = T153 - Division = 20000079 Cost Center = C00132653 Work Location = 50000127 - Work Schedule = D05H0830 Holiday Calendar = 01 - Personnel Grade (PG) = 10 - Employee Group = A - Permanent Employee Sub Group = 10 - Employment Type = F สถานะ Position = ว่าง - ตาราง time_status_mapping กำหนด Time Status = 01 O.T. Flag = yes - สิทธิ์ลาพักผ่อนปีแรก = 6 เงื่อนไขเฉพาะของเคสนี้ - คีย์ Employee Group = A - Permanent Employee Sub Group = 10 ตามชุดข้อมูล - Probation Exemption = Yes Hire Date = วันแรกของงวดเวลาปัจจุบัน - รายละเอียดเต็มดูชีท Hiring Test Data | J23: EC > Hire & Onboard (New Hire) | K23: 1. Login ด้วย <HR_ADMIN_ACCOUNT> - ไปที่หน้าสร้างพนักงานใหม่ 2. กรอกข้อมูลพนักงานใหม่ - กำหนด Probation Exemption = Yes - กำหนด Hire Date ตาม Test Data - กรอกข้อมูล Mandatory อื่นให้ครบถ้วนเพื่อให้สามารถ Submit ได้ 3. กด Submit เพื่อสร้างพนักงานใหม่ 4. ตรวจสอบ Employee Profile ใน EC - ค้นหาพนักงานด้วย Employee ID ที่สร้างขึ้น - ตรวจสอบ Employee Status - ตรวจสอบ Probation Exemption = Yes - ตรวจสอบ Pass Probation Date - ตรวจสอบว่าไม่แสดง Probationary Period End Date 5. ตรวจสอบคิวงานทดลองงานของหัวหน้างาน - ตรวจสอบว่าไม่มี Probation Task / รายการทดลองงานของพนักงานที่สร้างใหม่ | L23: EC - ระบบสร้าง Employee ID เป็นตัวเลข 8 หลัก โดยหลักแรกเป็น 2 - Employee Status = Active - Probation Exemption = Yes - ระบบไม่แสดง Probationary Period End Date - ระบบกำหนด Probationary Period End Date = Hire Date (Q&A ข้อ 22) - พนักงานเข้าสถานะทำงานได้โดยไม่ผ่านขั้น Probation Probation Task - ระบบไม่สร้าง Probation Task / รายการ Probation ของพนักงานรายนี้ในคิวงานของหัวหน้างาน | M23: Cancelled | Q23: ยกเว้นทดลองงาน ซ้ำ 054
A24: 23 | B24: Hiring | C24: E2E-23 | D24: Hiring | Mass Upload | New Hire | Import Multiple Employees | Verify Success / Failed Records | E24: HIR-EC-023 | F24: Negative | G24: High | H24: ตรวจสอบการจ้างพนักงานใหม่หลายรายการผ่าน Mass Upload และผลลัพธ์รายการ Success / Failed | I24: - Login = <HR_ADMIN_ACCOUNT> เงื่อนไขของเคสนี้ - ไฟล์นำเข้ามีพนักงานทั้งหมด 3 ราย - รายที่ 1 = ข้อมูล Mandatory ครบถ้วน - รายที่ 2 = ข้อมูล Mandatory ไม่ครบ - รายที่ 3 = ข้อมูล Mandatory ครบถ้วน - รูปแบบไฟล์และรายชื่อคอลัมน์ที่ระบบรองรับยังรอยืนยัน เนื่องจากยังไม่มี Template ที่ยืนยันแล้ว ค่าที่ต้องคีย์ ชุดข้อมูลจากถัง SIT ตรวจสอบเมื่อ 28 ส.ค. 2026 ชุดข้อมูล TD-01 - Business Group = CRC - Business Unit = CDG (10000075) Policy Profile = CDS - Company = C001 - Position = 40106337 Job Code = MKB12.12 - Department = 30042174 Store/ Branch Code = T153_1733 SSO Location = T153 - Division = 20000079 Cost Center = C00132653 Work Location = 50000127 - Work Schedule = D05H0830 Holiday Calendar = 01 - Personnel Grade (PG) = 10 - Employee Group = A - Permanent Employee Sub Group = 10 - Employment Type = F สถานะ Position = ว่าง - ตาราง time_status_mapping กำหนด Time Status = 01 O.T. Flag = yes - สิทธิ์ลาพักผ่อนปีแรก = 6 ชุดข้อมูล TD-02 - Position = 40001349 Job Code = IAB11.21 - Department = 30000655 Store/ Branch Code = T134_1714 SSO Location = T134 - Division = 20000087 Cost Center = C00103100 Work Location = 50000087 - Personnel Grade (PG) = 11 - Employee Group = A - Permanent Employee Sub Group = 11 ชุดข้อมูล TD-09 - Business Unit = CFR (10000003) Policy Profile = CFR - Company = C004 - Position = 40004936 Job Code = STA10.41 - Department = 30002085 Store/ Branch Code = T173_1753 SSO Location = T173 - Division = 20001351 Cost Center = C00429530 Work Location = 50000034 - Work Schedule = D06H0800 Holiday Calendar = 03 เงื่อนไขเฉพาะของเคสนี้ - ไฟล์นำเข้ามี 3 บรรทัด บรรทัดที่ 1 ใช้ TD-01 บรรทัดที่ 2 ใช้ TD-02 แต่เว้นช่อง Position ว่างเพื่อให้เป็นรายการที่ผิดพลาด บรรทัดที่ 3 ใช้ TD-09 - ผลที่ต้องได้คือสำเร็จ 2 รายการ ผิดพลาด 1 รายการ และรายงานต้องระบุบรรทัดที่ 2 - รายละเอียดเต็มดูชีท Hiring Test Data | J24: EC > นำเข้าข้อมูลพนักงานเป็นชุด | K24: 1. Login ด้วย <HR_ADMIN_ACCOUNT> - ไปที่หน้าจอนำเข้าข้อมูลพนักงานเป็นชุด 2. เตรียมและแนบไฟล์นำเข้า - ใช้ไฟล์ที่มีพนักงาน 3 รายตาม Test Data โดยกำหนดให้รายที่ 2 มีข้อมูล Mandatory ไม่ครบ 3. สั่งนำเข้าข้อมูลพนักงาน 4. ตรวจสอบผลการนำเข้า - ตรวจสอบจำนวนรายการ Success / Failed - ตรวจสอบผลของแต่ละแถวในไฟล์ - ตรวจสอบเหตุผลของรายการที่ไม่ผ่าน Validation - ตรวจสอบเลขบรรทัดของ Failed Record เทียบกับไฟล์ต้นทาง 5. ตรวจสอบ Employee Record ใน EC - ค้นหาพนักงานจากแต่ละ Record ในไฟล์ - ตรวจสอบจำนวน Employee Record ที่ถูกสร้างเทียบกับผลการ Import | L24: EC - ระบบตรวจสอบข้อมูลแต่ละ Record ในไฟล์และแสดงผลการ Import - Record ที่ข้อมูล Mandatory ไม่ครบต้องไม่ถูกสร้างเป็น Employee Record - ระบบแสดงรายการ Success และ Failed แยกกัน - Failed Record แสดงเหตุผลที่ไม่ผ่าน Validation เป็นรายบรรทัด - Failed Record ระบุเลขบรรทัดที่สัมพันธ์กับไฟล์ต้นทาง เพื่อให้สามารถกลับไปตรวจสอบและแก้ไขข้อมูลได้ | M24: Not Start | Q24: ตัดจากเคส E2E-23 ไฟล์ HR_SIT_E2E_V.0.1 (28).xlsx ชีท E2E All module โมดูลที่เคสเต็มเกี่ยวข้อง EC ยกไปรอบเชื่อมโมดูล ผลที่คาดหวังฝั่ง Notification / TM ไม่อยู่ในขอบเขต / BE ไม่อยู่ในขอบเขต / PY ไม่อยู่ในขอบเขต
A25: 24 | B25: Hiring | C25: E2E-24 | D25: Hiring | Keyin - Success | New Hire | Benefit Plan = Manual Enroll | DOB Validation | Verify Employee Self-Enrollment | E25: HIR-EC-024 | F25: Positive | G25: Medium | H25: ตรวจสอบการจ้างพนักงานใหม่แบบ Key-in สำเร็จ กรณี Benefit Plan = Manual Enroll พร้อมตรวจสอบ DOB และการลงทะเบียน Benefit ด้วยตนเองของพนักงาน | I25: เงื่อนไขของเคสนี้ - Case A: Date of Birth ทำให้ Age < 15 ปี ณ Hire Date - Case B: Hire Date < Date of Birth - Case C: Date of Birth ใช้ปี พ.ศ. แทน ค.ศ. เช่น 2567 - Positive Flow: ใช้ Date of Birth / Hire Date ที่ผ่าน Validation - Employee ID = Employee ID ที่ระบบสร้างจาก Positive Flow ของเคสนี้ - Employee Account = <EMPLOYEE_ACCOUNT> ของพนักงานที่สร้างจากเคสนี้ - Benefit Plan Config = Manual Enroll - Employee ตรงกับ Eligibility Rule ของแผน - มี Benefit Plan แบบ Manual Enroll ที่พร้อมใช้ทดสอบ ค่าที่ต้องคีย์ ชุดข้อมูลจากถัง SIT ตรวจสอบเมื่อ 28 ส.ค. 2026 ชุดข้อมูล TD-01 - Business Group = CRC - Business Unit = CDG (10000075) Policy Profile = CDS - Company = C001 - Position = 40106337 Job Code = MKB12.12 - Department = 30042174 Store/ Branch Code = T153_1733 SSO Location = T153 - Division = 20000079 Cost Center = C00132653 Work Location = 50000127 - Work Schedule = D05H0830 Holiday Calendar = 01 - Personnel Grade (PG) = 10 - Employee Group = A - Permanent Employee Sub Group = 10 - Employment Type = F สถานะ Position = ว่าง - ตาราง time_status_mapping กำหนด Time Status = 01 O.T. Flag = yes - สิทธิ์ลาพักผ่อนปีแรก = 6 เงื่อนไขเฉพาะของเคสนี้ - คีย์ Employee Group = A - Permanent Employee Sub Group = 10 ตามชุดข้อมูล - รอบตรวจวันเกิด ใช้ค่าอื่นทั้งหมดตามชุดข้อมูล เปลี่ยนเฉพาะ Date of Birth ตามที่ระบุในเคส - รอบสมัคร Benefit เอง ใช้ Employee ID ที่สร้างสำเร็จจากรอบแรก - รายละเอียดเต็มดูชีท Hiring Test Data | J25: EC > Hire & Onboard | K25: 1. Login ด้วย <HR_ADMIN_ACCOUNT> และไปที่ Hire & Onboard (New Hire) 2. ตรวจสอบ Date of Birth Validation — Case A - กำหนด Date of Birth ให้ Age < 15 ปี ณ Hire Date - กรอกข้อมูล Mandatory อื่นให้ครบถ้วนและกด Submit - ตรวจสอบผล Validation 3. ตรวจสอบ Date of Birth Validation — Case B - กำหนด Hire Date < Date of Birth - กรอกข้อมูล Mandatory อื่นให้ครบถ้วนและกด Submit - ตรวจสอบผล Validation 4. ตรวจสอบ Date of Birth Validation — Case C - กรอก Date of Birth โดยใช้ปี พ.ศ. เช่น 2567 - กรอกข้อมูล Mandatory อื่นให้ครบถ้วนและกด Submit - ตรวจสอบผล Validation 5. Hire พนักงานด้วยข้อมูลที่ผ่าน Validation - กำหนด Date of Birth / Hire Date ที่ถูกต้องและให้พนักงานตรงกับ Eligibility Rule ของ Benefit Plan - กรอกข้อมูล Mandatory อื่นให้ครบถ้วนตาม Flow ของ E2E-01 - กด Submit และบันทึก Employee ID ที่ระบบสร้าง 6. ดำเนินการจนพนักงาน Pass Probation 7. ตรวจสอบผลหลัง Manual Enroll - ตรวจสอบผลการสมัคร - ตรวจสอบรายการสิทธิ์ของพนักงานหลังสมัคร | L25: EC - EC — Date of Birth Validation - Case A: ระบบไม่อนุญาตให้ Submit เมื่อ Age < 15 ปี ณ Hire Date - Case B: ระบบไม่อนุญาตให้ Submit เมื่อ Hire Date < Date of Birth - Case C: ระบบไม่อนุญาตให้ Submit เมื่อ Date of Birth ใช้ปี พ.ศ. แทน ค.ศ. - ระบบแสดง Error Message สำหรับข้อมูลที่ไม่ผ่าน Validation - ระบบไม่สร้าง Employee Record จากรายการที่ไม่ผ่าน Validation - EC — Positive Flow - เมื่อ Date of Birth / Hire Date ผ่าน Validation ระบบสามารถสร้างพนักงานได้สำเร็จ - ระบบสร้าง Employee ID สำหรับใช้ตรวจสอบต่อใน BE / ESS - EC ส่งข้อมูลพนักงานไปยัง BE ตาม Flow ปกติ โดย Manual Enroll ไม่มีผลต่างที่ฝั่ง EC | M25: Not Start | Q25: ตัดจากเคส E2E-24 ไฟล์ HR_SIT_E2E_V.0.1 (28).xlsx ชีท E2E All module โมดูลที่เคสเต็มเกี่ยวข้อง EC / BE / PY ยกไปรอบเชื่อมโมดูล ผลที่คาดหวังฝั่ง Notification / TM ไม่อยู่ในขอบเขต / BE / ESS / PY ยกไปรอบเชื่อมโมดูล ขั้นตอน ตรวจสอบ Benefit Plan ใน BE หลัง Pass Probation / ให้พนักงานสมัคร Benefit Plan ด้วยตนเอง
A26: 25 | B26: Hiring | C26: E2E-25 | D26: Hiring | Keyin - Success | New Hire | Hire Date = Today | BE - Employee Data Does Not Match Existing Eligibility Rule | E26: HIR-EC-025 | F26: Positive | G26: High | H26: ตรวจสอบการจ้างพนักงานใหม่แบบ Key-in สำเร็จ กรณีวันเริ่มงานวันนี้ และข้อมูลพนักงานไม่ตรงตาม Eligibility Rule ของ BE | I26: - Entry Route = Keyin - Login = <HR_ADMIN_ACCOUNT> เงื่อนไขของเคสนี้ - Event Reason = New Hire - Hire Date = Today - Date of Birth = Age = 60 ณ Hire Date - Gender = Male - Nationality = Thai - Probation Exemption = Yes - Business Unit / Personnel Grade (PG) / Employee Group = ใช้ Combination ที่ ไม่ตรงกับ Eligibility Rule ใดที่ตั้งค่าไว้ใน BE - กรอกข้อมูล Mandatory อื่นให้ครบถ้วนเพื่อให้สามารถ Submit ได้ ค่าที่ต้องคีย์ ชุดข้อมูลจากถัง SIT ตรวจสอบเมื่อ 28 ส.ค. 2026 ชุดข้อมูล TD-04 - Business Group = CRC - Business Unit = CDG (10000075) Policy Profile = CDS - Company = C001 - Position = 40002451 Job Code = EMA10.63 - Department = 30042278 Store/ Branch Code = T132_1712 SSO Location = T132 - Division = 20000191 Cost Center = C00101100 Work Location = 50000127 - Work Schedule = D05H0830 Holiday Calendar = 01 - Personnel Grade (PG) = UC - Employee Group = A - Permanent Employee Sub Group = UC - Employment Type = F สถานะ Position = ว่าง - ตาราง time_status_mapping กำหนด Time Status = ? ไม่มี rule ที่ตรงในตาราง O.T. Flag = ? ไม่มี rule ที่ตรงในตาราง - สิทธิ์ลาพักผ่อนปีแรก = 20 เงื่อนไขเฉพาะของเคสนี้ - คีย์ Employee Group = A - Permanent Employee Sub Group = UC ตามชุดข้อมูล - เลือกชุดนี้เพราะ Personnel Grade (PG) UC ไม่ปรากฏในกฎสิทธิ์ Benefit ฝั่ง BE เลย จึงเป็นคู่ที่ไม่ตรงกฎใดจริง ดู OQ-HIR-102 - Hire Date = วันที่ทดสอบ ใช้ตรวจว่าฝั่ง BE ตอบอย่างไรเมื่อไม่มีกฎที่ตรงกับพนักงานคนนี้ - รายละเอียดเต็มดูชีท Hiring Test Data | J26: EC > Hire & Onboard (New Hire) | K26: 1. Login ด้วย <HR_ADMIN_ACCOUNT> - ไปที่ EC > New Hire (Manual Key-in) 2. กรอกข้อมูลพนักงานตาม Test Data - กำหนด Event Reason = New Hire และ Hire Date = Today - กำหนด Probation Exemption = Yes - กรอกข้อมูล Mandatory อื่นให้ครบถ้วนเพื่อให้สามารถ Submit ได้ 3. กด Submit เพื่อสร้างพนักงาน - บันทึก Employee ID ที่ระบบสร้าง 4. ตรวจสอบ Employee Profile ใน EC - ค้นหาพนักงานด้วย Employee ID - ตรวจสอบ Employee Status / Hire Date / Probation Exemption - ตรวจสอบ Pass Probation Date และ Probationary Period End Date 5. ตรวจสอบผลกระทบกลับมายัง EC - ตรวจสอบว่า Employee Record ที่สร้างใน EC ยังคงอยู่หลัง BE ประมวลผล Eligibility | L26: EC - ระบบสร้าง Employee ID เป็นตัวเลข 8 หลัก โดยหลักแรกเป็น 2 - Employee Status = Active - Hire Date = Today - ระบบสร้างและบันทึก Employee Record สำเร็จตามข้อมูลที่กรอก Probation - Probation Exemption = Yes - ระบบกำหนด Probationary Period End Date = Hire Date (Q&A ข้อ 22) - ระบบไม่แสดง Probationary Period End Date | M26: Cancelled | Q26: เงื่อนไขสิทธิสวัสดิการเฝั่ง BE
A27: 26 | B27: Hiring | C27: E2E-26 | D27: Hiring | Keyin - Success | New Hire After Termination | Same National ID | Previous Service ≥ 1 Year | Verify New Employee ID & Service Continuity | E27: HIR-EC-026 | F27: Positive | G27: High | H27: ตรวจสอบการจ้างพนักงานใหม่หลัง Termination แบบ Key-in สำเร็จ โดยใช้ National ID เดิม และมีอายุงานเดิม ≥ 1 ปี พร้อมตรวจสอบ Employee ID ใหม่และความต่อเนื่องของอายุงาน | I27: - Entry Route = Keyin - Login = <HR_ADMIN_ACCOUNT> เงื่อนไขของเคสนี้ - มีพนักงานเดิมที่ Terminate แล้ว 1 คน - Employee Status ของรายการเดิม = Inactive / Terminated - Previous Service = ตั้งแต่ 1 ปีขึ้นไป - Employee ID เดิม = Employee ID ของพนักงานที่เคย Terminate - National ID = National ID เดียวกับพนักงานเดิม - Hire Date ใหม่ = วันที่จ้างครั้งใหม่ - อ้างอิงพนักงานที่ Terminate จาก Termination Section ค่าที่ต้องคีย์ ชุดข้อมูลจากถัง SIT ตรวจสอบเมื่อ 28 ส.ค. 2026 ชุดข้อมูล TD-09 - Business Group = CRC - Business Unit = CFR (10000003) Policy Profile = CFR - Company = C004 - Position = 40004936 Job Code = STA10.41 - Department = 30002085 Store/ Branch Code = T173_1753 SSO Location = T173 - Division = 20001351 Cost Center = C00429530 Work Location = 50000034 - Work Schedule = D06H0800 Holiday Calendar = 03 - Personnel Grade (PG) = 11 - Employee Group = A - Permanent Employee Sub Group = 11 - Employment Type = F สถานะ Position = ว่าง - ตาราง time_status_mapping กำหนด Time Status = 01 O.T. Flag = yes - สิทธิ์ลาพักผ่อนปีแรก = 6 เงื่อนไขเฉพาะของเคสนี้ - คีย์ Employee Group = A - Permanent Employee Sub Group = 11 ตามชุดข้อมูล - ต้องมีพนักงานที่ลาออกแล้วและมี Year of Service เดิมตั้งแต่ 1 ปีขึ้นไป 1 คน เพื่อใช้เลขบัตรประชาชนเดิม - รายละเอียดเต็มดูชีท Hiring Test Data หมายเหตุรหัสเหตุการณ์ RE_REHIRE_GE1 และ RE_REHIRE_LT1 ถูกทำเครื่องหมาย Delete ในไฟล์ Event_EventReason_Mapping-EC ฉบับ 28 ส.ค. 2026 และ BA ยืนยันในชีท Quesitons ข้อ 5 ว่าไม่มี process re-hire เคสนี้จึงคีย์ผ่านเส้นทาง New Hire ปกติ | J27: EC > Hire & Onboard (New Hire) | K27: 1. เตรียมพนักงานที่ Terminate แล้ว - ตรวจสอบ Employee ID เดิม - ตรวจสอบ Employee Status = Inactive / Terminated - ตรวจสอบว่าพนักงานมี Previous Service ตั้งแต่ 1 ปีขึ้นไป - บันทึก National ID / Tax ID, Hire Date เดิม และข้อมูลอายุงานเดิม 2. Login ด้วย <HR_ADMIN_ACCOUNT> - ไปที่ EC > New Hire (Manual Key-in) 3. Key-in พนักงานเดิมกลับเข้าทำงานผ่าน New Hire - กำหนด Event Reason = New Hire - ใช้ National ID / Tax ID เดิมของพนักงานก่อน Terminate - กำหนด Hire Date ใหม่ = Today - กำหนด Employee Group = A - Permanent - กรอกข้อมูล Mandatory อื่นให้ครบถ้วนเพื่อให้สามารถ Submit ได้ 4. กด Submit เพื่อสร้างพนักงานใหม่ - ตรวจสอบผล Validation ของ National ID / Tax ID เดิม 5. ตรวจสอบ Employee ID หลังสร้างพนักงานใหม่ - ค้นหาพนักงานด้วย National ID / Tax ID เดิม - ตรวจสอบ Employee ID ของรายการใหม่ - เปรียบเทียบ Employee ID ใหม่กับ Employee ID เดิมก่อน Terminate 6. ตรวจสอบ Employee Record ใน EC - ตรวจสอบ Event Reason = New Hire - ตรวจสอบ Hire Date ใหม่ - ตรวจสอบ Employee Status ของรายการใหม่ - ตรวจสอบว่ารายการเดิมยังคงสถานะ Terminated / Inactive - ตรวจสอบความสัมพันธ์ระหว่าง Employee Record ใหม่กับรายการเดิม 7. ตรวจสอบการนับอายุงาน - ตรวจสอบ Seniority / Years of Service ของรายการใหม่ - ตรวจสอบว่าระบบนำ Previous Service ตั้งแต่ 1 ปีขึ้นไปมานับต่อ หรือเริ่มนับใหม่จาก Hire Date ใหม่ | L27: EC - การรับพนักงานที่เคย Terminate กลับเข้าทำงานดำเนินการผ่าน New Hire Flow - ระบบไม่ Block การ Submit เนื่องจาก National ID / Tax ID เดิมซ้ำกับพนักงานที่ไม่ได้อยู่ในสถานะ Active - ระบบสร้าง Employee ID ใหม่ และไม่ใช้ Employee ID เดิมซ้ำ - Employee ID ใหม่เป็นตัวเลข 8 หลัก โดยหลักแรกเป็นเลข 2 และต้องไม่เท่ากับ Employee ID เดิม - Hire Date = วันที่จ้างครั้งใหม่ - Employee Status ของรายการใหม่ = Active - Employee Record เดิมยังคงสถานะ Terminated / Inactive และไม่ถูกเปลี่ยนกลับเป็น Active - การผูกความสัมพันธ์ระหว่าง Employee Record ใหม่กับรายการเดิมให้เป็นไปตามข้อสรุปของ Service Continuity - ไม่มี Event Reason สำหรับการรับกลับ รายการนี้ใช้ Event Reason = New Hire - วิธีนับ Year of Service หลังกลับเข้าทำงานว่าจะนำ Previous Service มานับต่อหรือเริ่มใหม่ยังไม่มี Requirement ยืนยัน | M27: Not Start | Q27: ตัดจากเคส E2E-26 ไฟล์ HR_SIT_E2E_V.0.1 (28).xlsx ชีท E2E All module โมดูลที่เคสเต็มเกี่ยวข้อง EC / BE / TM / PY ยกไปรอบเชื่อมโมดูล ผลที่คาดหวังฝั่ง Notification / TM ไม่อยู่ในขอบเขต / BE ไม่อยู่ในขอบเขต / PY / ผลข้ามโมดูล ตรวจหลัง Submit สำเร็จแล้ว ยกไปรอบเชื่อมโมดูล ขั้นตอน ตรวจสอบข้อมูลใน BE / TM / PY
A28: 27 | B28: Hiring | C28: E2E-27 | D28: Hiring | Keyin - Negative | New Hire After Termination | Previous Service < 1 Year | Verify Rehire Event Reason Removed | E28: HIR-EC-027 | F28: Negative | G28: Medium | H28: ตรวจสอบการจ้างพนักงานที่เคยพ้นสภาพแล้วแบบ Key-in กรณีอายุงานเดิมน้อยกว่า 1 ปี ว่าระบบตัดตัวเลือก Event Reason แบบ Rehire ออก | I28: - Entry Route = Keyin - Login = <HR_ADMIN_ACCOUNT> เงื่อนไขของเคสนี้ - มีพนักงานที่ Terminate ไปแล้ว 1 คน ซึ่งเคยมี Year of Service เดิมไม่ถึง 1 ปี - Event Reason = New Hire - Hire Date = Today - Date of Birth = Age < 60 - Gender = Male - Nationality = TH - Employee Group = A - Permanent - National ID / Tax ID = ใช้เลขเดิมของพนักงานที่ Terminate ไปแล้ว โดย Year of Service เดิมไม่ถึง 1 ปี ค่าที่ต้องคีย์ ชุดข้อมูลจากถัง SIT ตรวจสอบเมื่อ 28 ส.ค. 2026 ชุดข้อมูล TD-09 - Business Group = CRC - Business Unit = CFR (10000003) Policy Profile = CFR - Company = C004 - Position = 40004936 Job Code = STA10.41 - Department = 30002085 Store/ Branch Code = T173_1753 SSO Location = T173 - Division = 20001351 Cost Center = C00429530 Work Location = 50000034 - Work Schedule = D06H0800 Holiday Calendar = 03 - Personnel Grade (PG) = 11 - Employee Group = A - Permanent Employee Sub Group = 11 - Employment Type = F สถานะ Position = ว่าง - ตาราง time_status_mapping กำหนด Time Status = 01 O.T. Flag = yes - สิทธิ์ลาพักผ่อนปีแรก = 6 เงื่อนไขเฉพาะของเคสนี้ - คีย์ Employee Group = A - Permanent Employee Sub Group = 11 ตามชุดข้อมูล - ต้องมีพนักงานที่ลาออกแล้วและมี Year of Service เดิมไม่ถึง 1 ปี 1 คน เพื่อใช้เลขบัตรประชาชนเดิม - รายละเอียดเต็มดูชีท Hiring Test Data รหัสเหตุการณ์ที่ต้องตรวจว่าไม่มีให้เลือก - RE_REHIRE_GE1 Rehiring GE 1 year - RE_REHIRE_LT1 Rehiring LT 1 year ทั้งสองรหัสถูกทำเครื่องหมาย Delete ในไฟล์ Event_EventReason_Mapping-EC ฉบับ 28 ส.ค. 2026 | J28: EC > Hire & Onboard (New Hire) | K28: 1. Login ด้วย <HR_ADMIN_ACCOUNT> - ไปที่เมนู EC > New Hire (Manual Key-in) 2. ตรวจรายการใน Event Reason ของหน้า New Hire - เปิด dropdown Event Reason - อ่านรายการทั้งหมดที่ระบบแสดง - ตรวจว่าไม่มี RE_REHIRE_GE1 และไม่มี RE_REHIRE_LT1 3. ตรวจว่าไม่มีเมนูหรือปุ่มสำหรับรับพนักงานกลับเข้าทำงาน - ตรวจหน้า New Hire และหน้า Employee Profile ของพนักงานที่ Terminate แล้ว - ตรวจว่าไม่มีปุ่ม Rehire หรือ Reactivate ที่เปลี่ยนพนักงานเดิมกลับเป็น Active 4. คีย์พนักงานใหม่โดยใช้ National ID / Tax ID เดิมของพนักงานที่ Terminate ไปแล้ว - กรอกข้อมูลในส่วน Identity, Position & Organization, Compensation Information และ Payment Information ตาม Test Data - ใช้ Event Reason = New Hire - กด Submit 5. ตรวจสอบผลใน Employee Profile - ค้นหาพนักงานที่สร้างใหม่และเปิด Employee Profile - ตรวจสอบ Employee ID ที่ระบบสร้าง - เปิด Employee Profile ของรายการเดิมและตรวจสถานะ | L28: EC - dropdown Event Reason ไม่มี RE_REHIRE_GE1 และไม่มี RE_REHIRE_LT1 - ไม่มีเมนูหรือปุ่มสำหรับรับพนักงานกลับเข้าทำงาน ทั้งในหน้า New Hire และใน Employee Profile ของพนักงานที่ Terminate แล้ว - ระบบไม่ Block การ Submit เนื่องจาก National ID / Tax ID เดิมซ้ำกับพนักงานที่ไม่ได้อยู่ในสถานะ Active - ระบบสร้าง Employee ID ใหม่เป็นตัวเลข 8 หลัก หลักแรกเป็นเลข 2 และไม่เท่ากับ Employee ID เดิม - Employee Status ของรายการใหม่ = Active - Employee Record เดิมยังคงสถานะ Terminated / Inactive และไม่ถูกเปลี่ยนกลับเป็น Active - ถ้ายังพบรหัสใดรหัสหนึ่งใน dropdown ให้ถือว่าเคสนี้ Fail และแจ้ง BA เพราะขัดกับคำตอบในชีท Quesitons ข้อ 5 และขัดกับไฟล์ Event Reason ฉบับล่าสุด | M28: Cancelled | Q28: ทั้งคู่ยืนยันประโยคเดียวกัน — ออก Employee ID ใหม่ + RE_REHIRE ต้องไม่มีใน LOV ซ้ำ 026
A29: 28 | B29: Hiring | C29: E2E-28 | D29: Hiring | Field Validation | National ID / Tax-ID | Duplicate Check on Submit | Invalid Format | E29: HIR-EC-028 | F29: Negative | G29: High | H29: ตรวจสอบ Validation ของ National ID / Tax ID กรณีข้อมูลซ้ำขณะ Submit และรูปแบบข้อมูลไม่ถูกต้อง | I29: - Login = <HR_ADMIN_ACCOUNT> เงื่อนไขของเคสนี้ - มีพนักงานสถานะ Active อยู่แล้ว 1 คนสำหรับใช้เป็น Baseline - National ID / Tax-ID = ซ้ำกับพนักงาน Active ที่มีอยู่แล้ว และเป็นคนละคน ไม่ใช่ Rehire - รูปแบบ Thailand = N-NNNN-NNNNN-NN-N - รูปแบบ Vietnam = NNNNNNNNN - เตรียมข้อมูล National ID / Tax-ID ที่ จำนวนหลักไม่ครบ สำหรับทดสอบ Invalid Format ค่าที่ต้องคีย์ ชุดข้อมูลจากถัง SIT ตรวจสอบเมื่อ 28 ส.ค. 2026 ชุดข้อมูล TD-01 - Business Group = CRC - Business Unit = CDG (10000075) Policy Profile = CDS - Company = C001 - Position = 40106337 Job Code = MKB12.12 - Department = 30042174 Store/ Branch Code = T153_1733 SSO Location = T153 - Division = 20000079 Cost Center = C00132653 Work Location = 50000127 - Work Schedule = D05H0830 Holiday Calendar = 01 - Personnel Grade (PG) = 10 - Employee Group = A - Permanent Employee Sub Group = 10 - Employment Type = F สถานะ Position = ว่าง - ตาราง time_status_mapping กำหนด Time Status = 01 O.T. Flag = yes - สิทธิ์ลาพักผ่อนปีแรก = 6 เงื่อนไขเฉพาะของเคสนี้ - คีย์ Employee Group = A - Permanent Employee Sub Group = 10 ตามชุดข้อมูล - ต้องสร้างพนักงานตามชุดข้อมูลนี้ให้สำเร็จก่อน 1 คน แล้วจึงสร้างคนที่สองด้วยเลขบัตรประชาชนเดียวกันบน Position อื่น - รอบตรวจรูปแบบ ให้กรอกเลขบัตรประชาชน 12 หลัก และเลขที่มีตัวอักษรปน เพื่อดูข้อความแจ้งเตือนใต้ช่อง - รายละเอียดเต็มดูชีท Hiring Test Data | J29: EC > Hire & Onboard (New Hire) | K29: 1. Login ด้วย <HR_ADMIN_ACCOUNT> - ไปที่หน้าสร้างพนักงานใหม่ 2. ตรวจสอบ Duplicate National ID / Tax-ID - กรอก National ID / Tax-ID ให้ซ้ำกับพนักงาน Active ที่มีอยู่แล้ว - ตรวจสอบว่าระบบยังไม่ Validate Duplicate แบบ Real-time ขณะกรอกข้อมูล - กรอกข้อมูลบังคับให้ครบถ้วน - กด Submit - ตรวจสอบ Notice ที่ระบบแสดงเมื่อพบ National ID / Tax-ID ซ้ำ 3. ตรวจสอบ Invalid Format - กรอก National ID / Tax-ID ผิดรูปแบบ เช่น จำนวนหลักไม่ครบ - กรอกข้อมูลบังคับให้ครบถ้วน - กด Submit - ตรวจสอบผล Validation และเปรียบเทียบกับกรณี Duplicate | L29: EC - ระบบตรวจสอบ Duplicate National ID / Tax-ID ตอนกด Submit เท่านั้น ไม่ Validate Duplicate แบบ Real-time ขณะกรอกข้อมูล - เมื่อพบ National ID / Tax-ID ซ้ำกับพนักงาน Active ที่มีอยู่แล้ว ระบบต้องแสดง Notice แจ้งว่าข้อมูลซ้ำ / มีอยู่แล้ว - ผลนี้เป็นคำตอบที่ยืนยันอย่างเป็นทางการของประเด็นที่เคย OPEN ใน E2E-04 ของ Sheet E2E All Module - กรณี National ID / Tax-ID ผิดรูปแบบหรือจำนวนหลักไม่ครบ ระบบต้อง Reject ก่อนเข้าสู่ขั้นตอนตรวจ Duplicate - รูปแบบที่ใช้ตรวจสอบ: Thailand = N-NNNN-NNNNN-NN-N / Vietnam = NNNNNNNNN | M29: Not Start | Q29: ตัดจากเคส E2E-28 ไฟล์ HR_SIT_E2E_V.0.1 (28).xlsx ชีท E2E All module โมดูลที่เคสเต็มเกี่ยวข้อง EC ยกไปรอบเชื่อมโมดูล ผลที่คาดหวังฝั่ง Notification / TM ไม่อยู่ในขอบเขต / BE ไม่อยู่ในขอบเขต / PY ไม่อยู่ในขอบเขต
A30: 29 | B30: Hiring | C30: E2E-29 | D30: Hiring | Keyin | Event Reason | Verify Hiring Restriction | E30: HIR-EC-029 | F30: Negative | G30: High | H30: ตรวจสอบว่า Event Reason บนหน้า Key-in แสดงเฉพาะ New Hire / Replacement / Migration | I30: - Entry Route = Keyin - Login = <HR_ADMIN_ACCOUNT> เงื่อนไขของเคสนี้ - ข้อมูลทดสอบเดียวกับ E2E-01 ทุกค่า เปลี่ยนเฉพาะ Event Reason | J30: EC > Hire & Onboard (New Hire) | K30: 1. Login ด้วย <HR_ADMIN_ACCOUNT> - ไปที่เมนู EC > New Hire (Manual Key-in) 2. ตรวจสอบ Event Reason - ตรวจสอบว่า Event Reason dropdown และ Event Reason อื่นๆ ถูกกรองออกเป็น background code | L30: EC - dropdown แสดง 3 ค่า : Event Reason บนหน้า Key-in แสดงเฉพาะ New Hire / Replacement / Migration - ไม่แสดง Event Reason : H_CORENTRY, H_INENTRY, H_TEMPASG | M30: Failed | N30: 46267 | O30: QA-Take | P30: BUG 71932
A31: 30 | B31: Hiring | C31: E2E-30 | D31: Hiring | Keyin - Success | Migration | Past Hire Date | Verify Employee Creation & Years of Service Impact | E31: HIR-EC-030 | F31: Positive | G31: High | H31: ตรวจสอบการจ้างพนักงานแบบ Migration ผ่าน Key-in กรณี Hire Date ย้อนหลัง พร้อมตรวจสอบการสร้างพนักงานและผลกระทบต่อ Years of Service | I31: - Entry Route = Keyin - Login = <HR_ADMIN_ACCOUNT> เงื่อนไขของเคสนี้ - Menu = Hire & Onboard - Event Reason = Migration - Hire Date = 01/01 ของปีก่อนหน้า - Date of Birth = Age < 60 - Gender = Male - Nationality = TH - Employee Group = A - Permanent ค่าที่ต้องคีย์ ชุดข้อมูลจากถัง SIT ตรวจสอบเมื่อ 28 ส.ค. 2026 ชุดข้อมูล TD-01 - Business Group = CRC - Business Unit = CDG (10000075) Policy Profile = CDS - Company = C001 - Position = 40106337 Job Code = MKB12.12 - Department = 30042174 Store/ Branch Code = T153_1733 SSO Location = T153 - Division = 20000079 Cost Center = C00132653 Work Location = 50000127 - Work Schedule = D05H0830 Holiday Calendar = 01 - Personnel Grade (PG) = 10 - Employee Group = A - Permanent Employee Sub Group = 10 - Employment Type = F สถานะ Position = ว่าง - ตาราง time_status_mapping กำหนด Time Status = 01 O.T. Flag = yes - สิทธิ์ลาพักผ่อนปีแรก = 6 เงื่อนไขเฉพาะของเคสนี้ - คีย์ Employee Group = A - Permanent Employee Sub Group = 10 ตามชุดข้อมูล - Event Reason = HIREDM Hire Date = 1 มกราคมของปีก่อนหน้า - รายละเอียดเต็มดูชีท Hiring Test Data | J31: EC > Hire & Onboard (New Hire) | K31: 1. Login ด้วย <HR_ADMIN_ACCOUNT> - ไปที่เมนู EC > New Hire (Manual Key-in) 2. กรอกข้อมูลในส่วน Identity - กรอก Salutation, First Name / Last Name (TH และ EN), Date of Birth และ National ID / Tax ID ตาม Test Data - กำหนด Event Reason = Migration - กำหนด Hire Date = 01/01 ของปีก่อนหน้า 3. กรอกข้อมูลในส่วน Position & Organization - กรอก Company, Business Unit, Division, Department, Position, Employee Group, Employee SubGroup และ Cost Centre ตาม Test Data 4. กรอกข้อมูลในส่วน Compensation Information - กรอก Pay Group, Pay Component, Frequency, Amount และ Currency ให้ครบถ้วน 5. กรอกข้อมูลในส่วน Payment Information - กรอก Bank, Account Number, Bank Country/Region, Currency และ Payment Method 6. กด Submit เพื่อสร้างพนักงานใหม่ 7. ตรวจสอบ Employee Profile ใน EC - ค้นหาพนักงานที่สร้างใหม่ด้วย Employee ID และเปิด Employee Profile - ตรวจสอบ Hire Date ที่บันทึก 8. ตรวจสอบการนับอายุงานใน EC - ตรวจสอบ Seniority Date - ตรวจสอบ Years of Service - ตรวจสอบผลของ include_in_work_experience สำหรับ Event Reason = Migration | L31: EC - ระบบสร้างพนักงานสำเร็จและบันทึก Hire Date ตามวันที่ย้อนหลังที่ระบุ - ระบบไม่นับช่วงนี้เป็น Year of Service เนื่องจาก Event Reason = Migration กำหนด include_in_work_experience = ไม่นับ - ระบบใช้ Employee ID เป็นตัวชี้ว่าเป็นรายการ Migration เดิม และไม่สร้างพนักงานซ้ำ (Q&A ข้อ 41) - ค่าที่ระบบเก่ามีแต่ระบบใหม่ไม่มี ระบบแสดงค่าเดิมตามที่ migrate มา (Q&A ข้อ 18) | M31: Not Start | Q31: ตัดจากเคส E2E-30 ไฟล์ HR_SIT_E2E_V.0.1 (28).xlsx ชีท E2E All module โมดูลที่เคสเต็มเกี่ยวข้อง EC / BE / TM / PY ยกไปรอบเชื่อมโมดูล ผลที่คาดหวังฝั่ง Notification / TM / BE / PY ยกไปรอบเชื่อมโมดูล ขั้นตอน ตรวจสอบสิทธิ์ที่ผูกกับอายุงานใน TM / ตรวจสอบข้อมูลใน BE
A32: 31 | B32: Hiring | C32: E2E-31 | D32: Hiring | Keyin - Success | Correction Entry (H_CORENTRY) | Hire Date = Today | Age < 60 | Male | TH | A - Permanent | Verify Payroll Event Code | E32: HIR-EC-031 | F32: Positive | G32: Medium | H32: ตรวจสอบการจ้างพนักงานแบบ Correction Entry (H_CORENTRY) ผ่าน Key-in สำเร็จ กรณีวันเริ่มงานวันนี้ อายุ < 60 ปี เพศชาย สัญชาติไทย พนักงานประจำ และตรวจสอบ Payroll Event Code | I32: - Entry Route = Keyin - Login = <HR_ADMIN_ACCOUNT> เงื่อนไขของเคสนี้ - Event Reason = H_CORENTRY - Hire Date = Today - Date of Birth = Age < 60 - Gender = Male - Nationality = TH - Employee Group = A - Permanent - ต้องยืนยันกับ SA ก่อนว่า H_CORENTRY สามารถเลือกได้โดย HR หรือเป็น Background Code ค่าที่ต้องคีย์ ชุดข้อมูลจากถัง SIT ตรวจสอบเมื่อ 28 ส.ค. 2026 ชุดข้อมูล TD-01 - Business Group = CRC - Business Unit = CDG (10000075) Policy Profile = CDS - Company = C001 - Position = 40106337 Job Code = MKB12.12 - Department = 30042174 Store/ Branch Code = T153_1733 SSO Location = T153 - Division = 20000079 Cost Center = C00132653 Work Location = 50000127 - Work Schedule = D05H0830 Holiday Calendar = 01 - Personnel Grade (PG) = 10 - Employee Group = A - Permanent Employee Sub Group = 10 - Employment Type = F สถานะ Position = ว่าง - ตาราง time_status_mapping กำหนด Time Status = 01 O.T. Flag = yes - สิทธิ์ลาพักผ่อนปีแรก = 6 เงื่อนไขเฉพาะของเคสนี้ - คีย์ Employee Group = A - Permanent Employee Sub Group = 10 ตามชุดข้อมูล - รหัส H_CORENTRY ไม่มีในตาราง Event Reason ของ SA ดู OQ-HIR-113 - รายละเอียดเต็มดูชีท Hiring Test Data | J32: EC > Hire & Onboard (New Hire) | K32: 1. Login ด้วย <HR_ADMIN_ACCOUNT> - ไปที่เมนู EC > New Hire (Manual Key-in) 2. ตรวจสอบ Event Reason = H_CORENTRY (Correction entry) - ตรวจสอบว่า H_CORENTRY แสดงให้ HR เลือกใน Event Reason หรือเป็น Background Code - หากระบบอนุญาตให้เลือก ให้กำหนด Event Reason = H_CORENTRY 3. กรอกข้อมูลในส่วน Identity - กรอก Salutation, First Name / Last Name (TH และ EN), Date of Birth, National ID / Tax ID และ Hire Date ตาม Test Data 4. กรอกข้อมูลในส่วน Position & Organization - กรอก Company, Business Unit, Division, Department, Position, Employee Group, Employee SubGroup และ Cost Centre ตาม Test Data 5. กรอกข้อมูลในส่วน Compensation Information - กรอก Pay Group, Pay Component, Frequency, Amount และ Currency ให้ครบถ้วน 6. กรอกข้อมูลในส่วน Payment Information - กรอก Bank, Account Number, Bank Country/Region, Currency และ Payment Method 7. กด Submit เพื่อสร้างพนักงานใหม่ 8. ตรวจสอบ Employee Profile ใน EC - ค้นหาพนักงานที่สร้างใหม่ด้วย Employee ID และเปิด Employee Profile | L32: EC - ระบบสร้างพนักงานสำเร็จ - การที่ H_CORENTRY สามารถเลือกโดย HR หรือเป็น Background Code = ? OQ-HIR-21 จุดที่ยังไม่มีคำตอบในเคสนี้ ให้รันจริงแล้วบันทึกค่าที่ระบบแสดงลงช่อง Actual Result Image และช่อง Note เพื่อใช้เป็นคำตอบ แล้วส่งให้ BA หรือ SA ยืนยัน หมายเลขคำถามที่ต้องเก็บคำตอบระหว่างรัน OQ-HIR-21 | M32: Cancelled | Q32: ยกเลิก: Event Reason = H_CORENTRY ไม่ถูก expose ให้ HR เลือกบนหน้า Key-in ซึ่งแสดงเฉพาะ New Hire / Replacement / Migration จึงเล่นเคสนี้ไม่ได้
A33: 32 | B33: Hiring | C33: E2E-32 | D33: Hiring | Keyin - Success | New Hire | Hire Date = Today | Age < 60 | Male | TH | E - Temporary | Temporary (P1 - Daily) | Verify Daily Wage Calculation Basis | E33: HIR-EC-032 | F33: Positive | G33: High | H33: ตรวจสอบการจ้างพนักงานใหม่แบบ Key-in สำเร็จ กรณีพนักงานชั่วคราว P1 - Daily และตรวจสอบเกณฑ์การคำนวณค่าจ้างรายวัน | I33: - Entry Route = Keyin - Login = <HR_ADMIN_ACCOUNT> เงื่อนไขของเคสนี้ - Menu = Hire & Onboard - Hire Date = Today - Date of Birth = Age < 60 - Gender = Male - Nationality = TH - Employee Group = E - Temporary - Contract Type = C1 Contract Monthly - Contract End Date = Contract End Date จริง - อัตราค่าจ้าง = อัตราต่อวัน - ต้องมี Work Schedule ที่ผูกกับ Position นี้อยู่แล้ว ค่าที่ต้องคีย์ ชุดข้อมูลจากถัง SIT ตรวจสอบเมื่อ 28 ส.ค. 2026 ชุดข้อมูล TD-50 - Business Group = CRC - Business Unit = CFR (10000003) Policy Profile = CFR - Company = C004 - Position = 40172617 Job Code = STA10.03 - Department = 30002732 Store/ Branch Code = T251_1831 SSO Location = T251 - Division = 20001351 Cost Center = C00429550 Work Location = 50000472 - Work Schedule = D06H0800 Holiday Calendar = 03 - Personnel Grade (PG) = NA - Employee Group = E - Temporary Employee Sub Group = P1-Daily - Employment Type = P สถานะ Position = ว่าง - ตาราง time_status_mapping กำหนด Time Status = 2 O.T. Flag = yes - สิทธิ์ลาพักผ่อนปีแรก = ? แถว Quota ของกลุ่มนี้ระบุ Personnel Grade (PG) 01 ถึง 20 ซึ่งไม่ครอบ NA ดู OQ-HIR-111 เงื่อนไขเฉพาะของเคสนี้ - คีย์ Employee Group = E - Temporary Employee Sub Group = P1-Daily ตามชุดข้อมูล - Contract Type = C1 Contract Monthly อัตราค่าจ้างเป็นอัตราต่อวัน - Position นี้ผูก Work Schedule D06H0800 อยู่แล้ว จึงใช้ตรวจฐานคำนวณค่าจ้างรายวันได้ - รายละเอียดเต็มดูชีท Hiring Test Data | J33: EC > Hire & Onboard (New Hire) | K33: 1. Login ด้วย <HR_ADMIN_ACCOUNT> - ไปที่เมนู EC > New Hire (Manual Key-in) 2. กรอกข้อมูลในส่วน Identity - กรอก Salutation, First Name / Last Name (TH และ EN), Date of Birth, National ID / Tax ID, Hire Date และ Event Reason ตาม Test Data 3. กรอกข้อมูลในส่วน Position & Organization - กรอก Company, Business Unit, Division, Department, Position และ Cost Centre ตาม Test Data - กำหนด Employee Group = E - Temporary - กำหนด Employee Subgroup = P1 (รายวัน) - กำหนด Contract Type = C1 Contract Monthly และกรอก Contract End Date ตาม Test Data 4. กรอกข้อมูลในส่วน Compensation Information - กรอกอัตราค่าจ้างเป็นอัตราต่อวัน - กรอก Pay Group, Pay Component, Frequency, Amount และ Currency ให้ครบถ้วน - ตรวจสอบหน่วยของค่าตอบแทนที่ระบบแสดงสำหรับ Employee Subgroup = P1 (รายวัน) 5. กรอกข้อมูลในส่วน Payment Information - กรอก Bank, Account Number, Bank Country/Region, Currency และ Payment Method 6. กด Submit เพื่อสร้างพนักงานใหม่ 7. ตรวจสอบ Employee Profile ใน EC - ค้นหาพนักงานที่สร้างใหม่ด้วย Employee ID และเปิด Employee Profile - ตรวจสอบ Employee Group, Employee Subgroup, Contract Type, Contract End Date และอัตราค่าจ้างที่บันทึก 8. ตรวจสอบหน่วยค่าตอบแทนสำหรับพนักงานรายวัน - ตรวจสอบว่าหน้าจอเปลี่ยนหน่วยของช่องค่าตอบแทนตามประเภทการจ้างหรือไม่ - ตรวจสอบว่าพนักงานประเภทรายวันสามารถกรอกค่าตอบแทนเป็นอัตราต่อเดือนได้หรือไม่ | L33: EC - ระบบบังคับให้มี Contract End Date เนื่องจาก Employee Group = E - Temporary เป็นกลุ่มที่ต้องมีสัญญา - ระบบบันทึกอัตราค่าจ้างเป็นหน่วยรายวัน ไม่ใช่รายเดือน - การที่หน้าจอต้องเปลี่ยนหน่วยของช่องค่าตอบแทนตาม Employment Type = ? OQ-HIR-81 จุดที่ยังไม่มีคำตอบในเคสนี้ ให้รันจริงแล้วบันทึกค่าที่ระบบแสดงลงช่อง Actual Result Image และช่อง Note เพื่อใช้เป็นคำตอบ แล้วส่งให้ BA หรือ SA ยืนยัน หมายเลขคำถามที่ต้องเก็บคำตอบระหว่างรัน OQ-HIR-81 | M33: Cancelled | Q33: หน่วยค่าจ้างรายวัน/รายชั่วโมง ซ้ำกับชุด Wage Type ซ้ำ 88 และ 091
A34: 33 | B34: Hiring | C34: E2E-33 | D34: Hiring | Keyin - Success | New Hire | Hire Date = Today | Age < 60 | Female | TH | E - Temporary | Temporary (P3 - Hourly) | Verify Hourly Wage Calculation Basis | E34: HIR-EC-033 | F34: Positive | G34: High | H34: ตรวจสอบการจ้างพนักงานใหม่แบบ Key-in สำเร็จ กรณีพนักงานชั่วคราว P3 - Hourly และตรวจสอบเกณฑ์การคำนวณค่าจ้างรายชั่วโมง | I34: - Entry Route = Keyin - Login = <HR_ADMIN_ACCOUNT> เงื่อนไขของเคสนี้ - Menu = Hire & Onboard - Hire Date = Today - Date of Birth = Age < 60 - Gender = Female - Nationality = TH - Employee Group = E - Temporary - อัตราค่าจ้าง = อัตราต่อชั่วโมง ค่าที่ต้องคีย์ ชุดข้อมูลจากถัง SIT ตรวจสอบเมื่อ 28 ส.ค. 2026 ชุดข้อมูล TD-51 - Business Group = CRC - Business Unit = CFR (10000003) Policy Profile = CFR - Company = C004 - Position = 40187613 Job Code = STA10.03 - Department = 30002291 Store/ Branch Code = T192_1772 SSO Location = T192 - Division = 20001351 Cost Center = C00429520 Work Location = 50000107 - Work Schedule = D06H0800 Holiday Calendar = 03 - Personnel Grade (PG) = NA - Employee Group = E - Temporary Employee Sub Group = P3-Hourly - Employment Type = P สถานะ Position = ว่าง - ตาราง time_status_mapping กำหนด Time Status = 2 O.T. Flag = yes - สิทธิ์ลาพักผ่อนปีแรก = ? แถว Quota ของกลุ่มนี้ระบุ Personnel Grade (PG) 01 ถึง 20 ซึ่งไม่ครอบ NA ดู OQ-HIR-111 เงื่อนไขเฉพาะของเคสนี้ - คีย์ Employee Group = E - Temporary Employee Sub Group = P3-Hourly ตามชุดข้อมูล - อัตราค่าจ้างเป็นอัตราต่อชั่วโมง Gender = Female - รายละเอียดเต็มดูชีท Hiring Test Data | J34: EC > Hire & Onboard (New Hire) | K34: 1. Login ด้วย <HR_ADMIN_ACCOUNT> - ไปที่เมนู EC > New Hire (Manual Key-in) 2. กรอกข้อมูลในส่วน Identity - กรอก Salutation, First Name / Last Name (TH และ EN), Date of Birth, National ID / Tax ID, Hire Date และ Event Reason ตาม Test Data 3. กรอกข้อมูลในส่วน Position & Organization - กรอก Company, Business Unit, Division, Department, Position และ Cost Centre ตาม Test Data - กำหนด Employee Group = E - Temporary - กำหนด Employee Subgroup = P3 (รายชั่วโมง) 4. กรอกข้อมูลในส่วน Compensation Information - ตรวจสอบ Pay Component สำหรับพนักงานรายชั่วโมง - กรอกอัตราค่าจ้างเป็นอัตราต่อชั่วโมง - กรอกข้อมูล Compensation Information ให้ครบถ้วน 5. กรอกข้อมูลในส่วน Payment Information - กรอก Bank, Account Number, Bank Country/Region, Currency และ Payment Method 6. กด Submit เพื่อสร้างพนักงานใหม่ 7. ตรวจสอบ Employee Profile ใน EC - ค้นหาพนักงานที่สร้างใหม่ด้วย Employee ID และเปิด Employee Profile - ตรวจสอบ Employee Class และวันสิ้นสุดสัญญาที่บันทึก - ตรวจสอบข้อมูล Compensation ที่บันทึก 8. ตรวจสอบกรณีมีเศษนาที - ตรวจสอบวิธีการปัดเศษนาทีของระบบ - บันทึก Actual Behavior ที่พบ | L34: EC - หน้า Compensation แสดง Pay Component = TH_1004 (Hourly Rate-T/P/S) - Frequency = HRS - Currency = THB - Employee Class แสดง E (E - Temporary) - ช่อง Contract End Date แสดงค่าที่กรอก - การบังคับกรอก Contract End Date เมื่อ Employee Group = E - Temporary = ? OQ-HIR-49 จุดที่ยังไม่มีคำตอบในเคสนี้ ให้รันจริงแล้วบันทึกค่าที่ระบบแสดงลงช่อง Actual Result Image และช่อง Note เพื่อใช้เป็นคำตอบ แล้วส่งให้ BA หรือ SA ยืนยัน หมายเลขคำถามที่ต้องเก็บคำตอบระหว่างรัน OQ-HIR-49 | M34: Cancelled | Q34: หน่วยค่าจ้างรายวัน/รายชั่วโมง ซ้ำกับชุด Wage Type ซ้ำ 88 และ 091
A35: 34 | B35: Hiring | C35: E2E-34 | D35: Hiring | Keyin | New Hire | Employee Subgroup 07 vs 7 | Verify Leading Zero Preservation | E35: HIR-EC-034 | F35: Positive | G35: High | H35: ตรวจสอบ Employee Subgroup 07 และ 7 ในการจ้างแบบ Key-in ว่าระบบคงเลข 0 นำหน้าอย่างถูกต้อง | I35: - Entry Route = Keyin - Login = <HR_ADMIN_ACCOUNT> เงื่อนไขของเคสนี้ - ชุดข้อมูลตั้งต้นระบุว่า 07 = ค่าที่ยังใช้งานอยู่ - ชุดข้อมูลตั้งต้นระบุว่า 7 = ค่าที่เลิกใช้แล้ว - รอบที่สองทดสอบด้วย Employee Sub Group = 7 หาก Dropdown มีค่าให้เลือก ค่าที่ต้องคีย์ ชุดข้อมูลจากถัง SIT ตรวจสอบเมื่อ 28 ส.ค. 2026 ชุดข้อมูล TD-59 - Business Group = CRC - Business Unit = CFR (10000003) Policy Profile = CFR - Company = C004 - Position = 40103309 Job Code = FBD10.12 - Department = 30040602 Store/ Branch Code = T200_1780 SSO Location = T200 - Division = 20001358 Cost Center = C00402995 Work Location = 50000171 - Work Schedule = D06H0800 Holiday Calendar = 03 - Personnel Grade (PG) = 08 - Employee Group = A - Permanent Employee Sub Group = 08 - Employment Type = F สถานะ Position = ว่าง - ตาราง time_status_mapping กำหนด Time Status = 01 O.T. Flag = yes - สิทธิ์ลาพักผ่อนปีแรก = 6 เงื่อนไขเฉพาะของเคสนี้ - คีย์ Employee Group = A - Permanent Employee Sub Group = 08 ตามชุดข้อมูล - Personnel Grade (PG) ต่ำสุดที่มีจริงในสาม Business Group คือ 08 ระดับ 07 มีเฉพาะ Business Unit นอกขอบเขต ดู OQ-HIR-112 - รอบที่ 1 คีย์ 08 แล้วตรวจว่าค่าที่บันทึกยังเป็น 08 ไม่ถูกตัดเป็น 8 รอบที่ 2 ถ้าตัวเลือกมีค่า 8 ให้เลือกแล้วบันทึกผล - รายละเอียดเต็มดูชีท Hiring Test Data | J35: EC > Hire & Onboard (New Hire) | K35: 1. Login ด้วย <HR_ADMIN_ACCOUNT> - ไปที่เมนู EC > New Hire (Manual Key-in) 2. กรอกข้อมูลในส่วน Identity - กรอก Salutation, First Name / Last Name (TH และ EN), Date of Birth, National ID / Tax ID, Hire Date และ Event Reason ตาม Test Data ของ E2E-01 3. กรอกข้อมูลในส่วน Position & Organization - กรอก Company, Business Unit, Division, Department, Position, Employee Group และ Cost Centre ตาม Test Data - เลือก Employee Subgroup = 07 - ตรวจสอบว่าค่าที่แสดงยังคงเป็น 07 ไม่ถูกเปลี่ยนเป็น 7 4. กรอกข้อมูลในส่วน Compensation Information - กรอก Pay Group, Pay Component, Frequency, Amount และ Currency ให้ครบถ้วน 5. กรอกข้อมูลในส่วน Payment Information - กรอก Bank, Account Number, Bank Country/Region, Currency และ Payment Method 6. กด Submit เพื่อสร้างพนักงานใหม่ 7. ตรวจสอบ Employee Profile ใน EC - ค้นหาพนักงานที่สร้างใหม่ด้วย Employee ID และเปิด Employee Profile - ตรวจสอบ Employee Subgroup ที่ระบบบันทึก 8. ทดสอบรอบที่สองด้วย Employee Subgroup = 7 - ตรวจสอบว่า Dropdown มีค่า 7 ซึ่งเป็นค่าที่เลิกใช้แล้วให้เลือกหรือไม่ - หากมีค่า 7 ให้เลือก ให้ดำเนินการทดสอบและบันทึกผลที่พบ 9. ตรวจสอบความถูกต้องของ Employee Subgroup - หาก EC, ไฟล์ส่งออก หรือ Payload ของ TM / BE / PY เปลี่ยนค่า 07 เป็น 7 ให้บันทึกเป็น Defect | L35: EC - ระบบต้องเก็บและแสดง Employee Subgroup = 07 โดยไม่ตัดเลขศูนย์นำหน้า - ระบบต้องไม่ให้เลือก Employee Subgroup = 07 ซึ่งเป็นค่าที่เลิกใช้แล้ว หรือหากระบบยังอนุญาตให้เลือก ต้องมีคำอธิบายจาก FO | M35: Passed | N35: 46267 | O35: QA-Wannaphon | Q35: ตัดจากเคส E2E-34 ไฟล์ HR_SIT_E2E_V.0.1 (28).xlsx ชีท E2E All module โมดูลที่เคสเต็มเกี่ยวข้อง EC / TM / BE / PY ยกไปรอบเชื่อมโมดูล ผลที่คาดหวังฝั่ง Notification / TM / BE / PY ยกไปรอบเชื่อมโมดูล ขั้นตอน ตรวจสอบค่าที่ส่งไป Downstream
A36: 35 | B36: Hiring | C36: E2E-35 | D36: Hiring | Keyin - Success | New Hire | Hire Date = Today | Age < 60 | Male | TH | H - Contingent Worker | Long-Term Contract | Verify Contract End Date 31/12/9999 | E36: HIR-EC-035 | F36: Positive | G36: Medium | H36: ตรวจสอบการจ้างพนักงานใหม่แบบ Key-in สำเร็จ กรณี Contingent Worker สัญญาระยะยาว และ Contract End Date = 31/12/9999 | I36: - Entry Route = Keyin - Login = <HR_ADMIN_ACCOUNT> เงื่อนไขของเคสนี้ - Hire Date = Today - Date of Birth = Age < 60 - Gender = Male - Nationality = TH - Employee Group = H - บุคคลภายนอกที่จ่ายเงิน - Contract Type = C3 Contract Long term - Contract End Date = 31/12/9999 ค่าที่ต้องคีย์ ชุดข้อมูลจากถัง SIT ตรวจสอบเมื่อ 28 ส.ค. 2026 ชุดข้อมูล TD-57 - Business Group = CU - Business Unit = CU (10000013) Policy Profile = SU-OTHER - Company = C013 - Position = 40016139 Job Code = BDA10.01 - Department = 30005382 Store/ Branch Code = T077_1644 SSO Location = T077 - Division = 20000239 Cost Center = C01301137 Work Location = 50000127 - Work Schedule = D05H0830 Holiday Calendar = 01 - Personnel Grade (PG) = NA - Employee Group = H - Contingent Worker Employee Sub Group = C1-Consultant - Employment Type = P สถานะ Position = ว่าง - ตาราง time_status_mapping กำหนด Time Status = 9 O.T. Flag = no - สิทธิ์ลาพักผ่อนปีแรก = ? ไม่มีแถว Quota ที่ตรงกับกลุ่ม H ดู OQ-HIR-111 เงื่อนไขเฉพาะของเคสนี้ - คีย์ Employee Group = H - Contingent Worker Employee Sub Group = C1-Consultant ตามชุดข้อมูล - Contract Type = C3 Contract Long term Contract End Date = 31/12/9999 - รายละเอียดเต็มดูชีท Hiring Test Data | J36: EC > Hire & Onboard (New Hire) | K36: 1. Login ด้วย <HR_ADMIN_ACCOUNT> - ไปที่เมนู EC > New Hire (Manual Key-in) 2. กรอกข้อมูลในส่วน Identity - กรอก Salutation, First Name / Last Name (TH และ EN), Date of Birth, National ID / Tax ID, Hire Date และ Event Reason ตาม Test Data 3. กรอกข้อมูลในส่วน Position & Organization - กรอก Company, Business Unit, Division, Department, Position, Employee SubGroup และ Cost Centre ตาม Test Data - กำหนด Employee Group = H - บุคคลภายนอกที่จ่ายเงิน - กำหนด Contract Type = C3 Contract Long term - กรอก Contract End Date = 31/12/9999 4. กรอกข้อมูลในส่วน Compensation Information - กรอก Pay Group, Pay Component, Frequency, Amount และ Currency ให้ครบถ้วน 5. กรอกข้อมูลในส่วน Payment Information - กรอก Bank, Account Number, Bank Country/Region, Currency และ Payment Method 6. กด Submit เพื่อสร้างพนักงานใหม่ 7. ตรวจสอบ Employee Profile ใน EC - ค้นหาพนักงานที่สร้างใหม่ด้วย Employee ID และเปิด Employee Profile - ตรวจสอบ Employee Group, Contract Type และ Contract End Date ที่ระบบบันทึก 8. ตรวจสอบ Contract End Date = 31/12/9999 - ตรวจสอบว่าระบบยอมรับวันที่ 31/12/9999 - ตรวจสอบว่าค่าที่บันทึกยังคงเป็น 31/12/9999 และไม่ถูกเปลี่ยนเป็นค่าว่าง | L36: EC - ระบบยอมรับ Contract End Date = 31/12/9999 เป็น Contract End Date สำหรับ Contract Type = C3 Contract Long term - ระบบบันทึก Contract End Date = 31/12/9999 และไม่เปลี่ยนเป็นค่าว่าง - ระบบบังคับให้ Employee Group = H ต้องมีสัญญาเสมอ - ระบบไม่สร้างงานหรือการแจ้งเตือนเรื่องสัญญาใกล้หมดสำหรับ Contract End Date = 31/12/9999 | M36: Not Start | Q36: ตัดจากเคส E2E-35 ไฟล์ HR_SIT_E2E_V.0.1 (28).xlsx ชีท E2E All module โมดูลที่เคสเต็มเกี่ยวข้อง EC / BE / TM / PY ยกไปรอบเชื่อมโมดูล ผลที่คาดหวังฝั่ง Notification / TM / BE / PY ยกไปรอบเชื่อมโมดูล ขั้นตอน ตรวจสอบการแจ้งเตือนหมดสัญญา / ตรวจสอบข้อมูลใน BE / TM / PY
A37: 36 | B37: Hiring | C37: E2E-36 | D37: Hiring | Keyin - Success | New Hire | Hire Date = Today | Age < 60 | Female | TH | E - Temporary | Contract End Date = Next Month-End | Verify Auto Termination | E37: HIR-EC-036 | F37: Positive | G37: High | H37: ตรวจสอบการจ้างพนักงานใหม่แบบ Key-in สำเร็จ กรณีพนักงานชั่วคราวมี Contract End Date เป็นวันสิ้นเดือนถัดไป และตรวจสอบ Auto Termination | I37: - Entry Route = Keyin - Login = <HR_ADMIN_ACCOUNT> เงื่อนไขของเคสนี้ - Employee Group = E - Temporary - Contract Type = C1 Contract Monthly - Contract End Date = วันสุดท้ายของเดือนถัดไป - ต้องยืนยันกับ BA ก่อนว่ามีกลไกปิดงานอัตโนมัติเมื่อสัญญาหมดจริงหรือไม่ ค่าที่ต้องคีย์ ชุดข้อมูลจากถัง SIT ตรวจสอบเมื่อ 28 ส.ค. 2026 ชุดข้อมูล TD-52 - Business Group = CRC - Business Unit = CFR (10000003) Policy Profile = CFR - Company = C004 - Position = 40191218 Job Code = STA10.03 - Department = 30003233 Store/ Branch Code = T337_1917 SSO Location = T337 - Division = 20001351 Cost Center = C00429520 Work Location = 50000100 - Work Schedule = D06H0800 Holiday Calendar = 03 - Personnel Grade (PG) = NA - Employee Group = E - Temporary Employee Sub Group = P5-Event - Employment Type = P สถานะ Position = ว่าง - ตาราง time_status_mapping กำหนด Time Status = 9 O.T. Flag = no - สิทธิ์ลาพักผ่อนปีแรก = ? แถว Quota ของกลุ่มนี้ระบุ Personnel Grade (PG) 01 ถึง 20 ซึ่งไม่ครอบ NA ดู OQ-HIR-111 เงื่อนไขเฉพาะของเคสนี้ - คีย์ Employee Group = E - Temporary Employee Sub Group = P5-Event ตามชุดข้อมูล - Contract Type = C1 Contract Monthly Contract End Date = วันสุดท้ายของเดือนถัดไป - รายละเอียดเต็มดูชีท Hiring Test Data | J37: EC > Hire & Onboard (New Hire) | K37: 1. Login ด้วย <HR_ADMIN_ACCOUNT> - ไปที่เมนู EC > New Hire (Manual Key-in) 2. กรอกข้อมูลในส่วน Identity - กรอก Salutation, First Name / Last Name (TH และ EN), Date of Birth, National ID / Tax ID, Hire Date และ Event Reason ตาม Test Data 3. กรอกข้อมูลในส่วน Position & Organization - กรอก Company, Business Unit, Division, Department, Position, Employee SubGroup และ Cost Centre ตาม Test Data - กำหนด Employee Group = E - Temporary - กำหนด Contract Type = C1 Contract Monthly - กรอก Contract End Date = วันสุดท้ายของเดือนถัดไป 4. กรอกข้อมูลในส่วน Compensation Information - กรอก Pay Group, Pay Component, Frequency, Amount และ Currency ให้ครบถ้วน 5. กรอกข้อมูลในส่วน Payment Information - กรอก Bank, Account Number, Bank Country/Region, Currency และ Payment Method 6. กด Submit เพื่อสร้างพนักงานใหม่ 7. ตรวจสอบ Employee Profile ใน EC - ค้นหาพนักงานที่สร้างใหม่ด้วย Employee ID และเปิด Employee Profile - ตรวจสอบ Contract Type และ Contract End Date ที่ระบบบันทึก 8. ตรวจสอบสถานะพนักงานเมื่อถึง Contract End Date - ตรวจสอบว่าระบบเปลี่ยน Employee Status อัตโนมัติหรือรอ HR ดำเนินการ - บันทึก Actual Behavior ที่พบ | L37: EC - ระบบบันทึก Contract End Date ตามวันที่ระบุถูกต้อง - การที่ระบบต้องเปลี่ยน Employee Status อัตโนมัติเมื่อถึง Contract End Date หรือรอ HR ดำเนินการ = ? OQ-HIR-156 จุดที่ยังไม่มีคำตอบในเคสนี้ ให้รันจริงแล้วบันทึกค่าที่ระบบแสดงลงช่อง Actual Result Image และช่อง Note เพื่อใช้เป็นคำตอบ แล้วส่งให้ BA หรือ SA ยืนยัน หมายเลขคำถามที่ต้องเก็บคำตอบระหว่างรัน OQ-HIR-156 | M37: Cancelled | Q37: วันสิ้นสุดสัญญาสิ้นเดือนถัดไป ฝั่ง EC แค่บันทึกวันที่ ส่วน auto-terminate เป็น scheduler ซ้ำกับ 35
A38: 37 | B38: Hiring | C38: E2E-37 | D38: Hiring | Keyin - Success | New Hire | Hire Date = Day 20 of Month | Age < 60 | Male | TH | A - Permanent | Pay Group = ES (CDS:01-31:EOM16D, Period 1-31, Paid Month-End) | Verify Current Payroll Cycle | E38: HIR-EC-037 | F38: Positive | G38: High | H38: ตรวจสอบการจ้างพนักงานใหม่แบบ Key-in สำเร็จ กรณี Hire Date = วันที่ 20 และ Pay Group = ES พร้อมตรวจสอบการเข้า Payroll Cycle ปัจจุบัน | I38: - Entry Route = Keyin - Login = <HR_ADMIN_ACCOUNT> เงื่อนไขของเคสนี้ - Hire Date = วันที่ 20 ของเดือนปัจจุบัน - Date of Birth = Age < 60 - Gender = Male - Nationality = TH - Employee Group = A - Permanent - รอบจ่าย = วันที่ 1 ถึงสิ้นเดือน - จำนวนวันฐาน = 30 วัน - ต้องทราบก่อนว่าพนักงานถูกผูกกับรอบจ่ายใด และรอบนั้นใช้จำนวนวันฐานเท่าไร ค่าที่ต้องคีย์ ชุดข้อมูลจากถัง SIT ตรวจสอบเมื่อ 28 ส.ค. 2026 ชุดข้อมูล TD-01 - Business Group = CRC - Business Unit = CDG (10000075) Policy Profile = CDS - Company = C001 - Position = 40106337 Job Code = MKB12.12 - Department = 30042174 Store/ Branch Code = T153_1733 SSO Location = T153 - Division = 20000079 Cost Center = C00132653 Work Location = 50000127 - Work Schedule = D05H0830 Holiday Calendar = 01 - Personnel Grade (PG) = 10 - Employee Group = A - Permanent Employee Sub Group = 10 - Employment Type = F สถานะ Position = ว่าง - ตาราง time_status_mapping กำหนด Time Status = 01 O.T. Flag = yes - สิทธิ์ลาพักผ่อนปีแรก = 6 เงื่อนไขเฉพาะของเคสนี้ - คีย์ Employee Group = A - Permanent Employee Sub Group = 10 ตามชุดข้อมูล - Hire Date = วันที่ 20 ของเดือนที่ทดสอบ Pay Group = ES - รายละเอียดเต็มดูชีท Hiring Test Data | J38: EC > Hire & Onboard (New Hire) | K38: 1. Login ด้วย <HR_ADMIN_ACCOUNT> - ไปที่เมนู EC > New Hire (Manual Key-in) 2. กรอกข้อมูลในส่วน Identity - กรอก Salutation, First Name / Last Name (TH และ EN), Date of Birth, National ID / Tax ID และ Event Reason ตาม Test Data - กำหนด Hire Date = วันที่ 20 ของเดือนปัจจุบัน 3. กรอกข้อมูลในส่วน Position & Organization - กรอก Company, Business Unit, Division, Department, Position, Employee Group, Employee SubGroup และ Cost Centre ตาม Test Data 4. กรอกข้อมูลในส่วน Compensation Information - กำหนด Pay Group = ES - กรอก Pay Component, Frequency, Amount และ Currency ให้ครบถ้วน 5. กรอกข้อมูลในส่วน Payment Information - กรอก Bank, Account Number, Bank Country/Region, Currency และ Payment Method 6. กด Submit เพื่อสร้างพนักงานใหม่ 7. ตรวจสอบ Employee Profile ใน EC - ค้นหาพนักงานที่สร้างใหม่ด้วย Employee ID และเปิด Employee Profile - ตรวจสอบ Employee Status, Hire Date และ Pay Group ที่ระบบบันทึก | L38: EC - ระบบสร้างพนักงานสำเร็จ - Employee Status = Active - ระบบเริ่มนับ Probation Day 1 - ระบบบันทึก Hire Date = วันที่ 20 ของเดือนปัจจุบันตามที่ระบุ - ระบบบันทึก Pay Group = ES | M38: Cancelled | Q38: รอบจ่าย Pay Group ES = PY
A39: 38 | B39: Hiring | C39: E2E-38 | D39: Hiring | Keyin - Success | New Hire | Hire Date = Day 21 of Month | Age < 60 | Male | TH | A - Permanent | Pay Group = ES (CDS:01-31:EOM16D, Period 1-31, Paid Month-End) | Verify Payroll Cycle Lock | E39: HIR-EC-038 | F39: Positive | G39: High | H39: ตรวจสอบการจ้างพนักงานใหม่แบบ Key-in สำเร็จ กรณี Hire Date = วันที่ 21 และ Pay Group = ES พร้อมตรวจสอบ Payroll Cycle Lock | I39: - Entry Route = Keyin - Login = <HR_ADMIN_ACCOUNT> เงื่อนไขของเคสนี้ - Hire Date = วันที่ 21 ของเดือนปัจจุบัน - Date of Birth = Age < 60 - Gender = Male - Nationality = TH - Employee Group = A - Permanent - รันคู่กับ E2E-H11 ใน Environment และ Payroll Period เดียวกันเพื่อเปรียบเทียบผล ค่าที่ต้องคีย์ ชุดข้อมูลจากถัง SIT ตรวจสอบเมื่อ 28 ส.ค. 2026 ชุดข้อมูล TD-01 - Business Group = CRC - Business Unit = CDG (10000075) Policy Profile = CDS - Company = C001 - Position = 40106337 Job Code = MKB12.12 - Department = 30042174 Store/ Branch Code = T153_1733 SSO Location = T153 - Division = 20000079 Cost Center = C00132653 Work Location = 50000127 - Work Schedule = D05H0830 Holiday Calendar = 01 - Personnel Grade (PG) = 10 - Employee Group = A - Permanent Employee Sub Group = 10 - Employment Type = F สถานะ Position = ว่าง - ตาราง time_status_mapping กำหนด Time Status = 01 O.T. Flag = yes - สิทธิ์ลาพักผ่อนปีแรก = 6 เงื่อนไขเฉพาะของเคสนี้ - คีย์ Employee Group = A - Permanent Employee Sub Group = 10 ตามชุดข้อมูล - Hire Date = วันที่ 21 ของเดือนที่ทดสอบ Pay Group = ES - รันคู่กับ E2E-37 ในงวดเดียวกันเพื่อเทียบผล - รายละเอียดเต็มดูชีท Hiring Test Data | J39: EC > Hire & Onboard (New Hire) | K39: 1. Login ด้วย <HR_ADMIN_ACCOUNT> - ไปที่เมนู EC > New Hire (Manual Key-in) 2. กรอกข้อมูลในส่วน Identity - กรอก Salutation, First Name / Last Name (TH และ EN), Date of Birth, National ID / Tax ID และ Event Reason ตาม Test Data - กำหนด Hire Date = วันที่ 21 ของเดือนปัจจุบัน 3. กรอกข้อมูลในส่วน Position & Organization - กรอก Company, Business Unit, Division, Department, Position, Employee Group, Employee SubGroup และ Cost Centre ตาม Test Data 4. กรอกข้อมูลในส่วน Compensation Information - กำหนด Pay Group = ES - กรอก Pay Component, Frequency, Amount และ Currency ให้ครบถ้วน 5. กรอกข้อมูลในส่วน Payment Information - กรอก Bank, Account Number, Bank Country/Region, Currency และ Payment Method 6. กด Submit เพื่อสร้างพนักงานใหม่ 7. ตรวจสอบ Employee Profile ใน EC - ค้นหาพนักงานที่สร้างใหม่ด้วย Employee ID และเปิด Employee Profile - ตรวจสอบ Employee Status, Hire Date และ Pay Group ที่ระบบบันทึก 8. ตรวจสอบการปลดล็อก - ตรวจสอบผู้ดำเนินการปลดล็อก - ตรวจสอบเวลาที่สามารถปลดล็อกได้ | L39: EC - ระบบสร้างพนักงานสำเร็จ - Employee Status = Active - ระบบบันทึก Hire Date = วันที่ 21 ของเดือนปัจจุบันตามที่ระบุ - ระบบบันทึก Pay Group = ES - หน้าจอ EC ต้องไม่แสดงสถานะล้มเหลวจากการที่พนักงานถูกล็อกฝั่ง Salary เนื่องจากการถูกล็อกเป็นเรื่องของ PY ไม่ใช่ความผิดพลาดของการ Hiring | M39: Cancelled | Q39: การล็อกวันที่ 21 เป็นฝั่ง PY ไม่ใช่ EC
A40: 39 | B40: Hiring | C40: E2E-39 | D40: Hiring | Keyin - Success | New Hire | Hire Date = Feb 21 | Age < 60 | Female | TH | A - Permanent | Pay Group = ES | Verify 30-Day Payroll Basis | E40: HIR-EC-039 | F40: Positive | G40: High | H40: ตรวจสอบการจ้างพนักงานใหม่แบบ Key-in สำเร็จ กรณี Hire Date = 21 กุมภาพันธ์ และ Pay Group = ES พร้อมตรวจสอบเกณฑ์การคำนวณ Payroll แบบ 30 วัน | I40: - Entry Route = Keyin - Login = <HR_ADMIN_ACCOUNT> เงื่อนไขของเคสนี้ - Hire Date = 21 กุมภาพันธ์ - Date of Birth = Age < 60 - Gender = Female - Nationality = TH - Employee Group = A - Permanent - ต้องรันในงวดที่เดือนกุมภาพันธ์มี 28 หรือ 29 วันจริง หรือใช้การตั้งวันของระบบทดสอบ ค่าที่ต้องคีย์ ชุดข้อมูลจากถัง SIT ตรวจสอบเมื่อ 28 ส.ค. 2026 ชุดข้อมูล TD-01 - Business Group = CRC - Business Unit = CDG (10000075) Policy Profile = CDS - Company = C001 - Position = 40106337 Job Code = MKB12.12 - Department = 30042174 Store/ Branch Code = T153_1733 SSO Location = T153 - Division = 20000079 Cost Center = C00132653 Work Location = 50000127 - Work Schedule = D05H0830 Holiday Calendar = 01 - Personnel Grade (PG) = 10 - Employee Group = A - Permanent Employee Sub Group = 10 - Employment Type = F สถานะ Position = ว่าง - ตาราง time_status_mapping กำหนด Time Status = 01 O.T. Flag = yes - สิทธิ์ลาพักผ่อนปีแรก = 6 เงื่อนไขเฉพาะของเคสนี้ - คีย์ Employee Group = A - Permanent Employee Sub Group = 10 ตามชุดข้อมูล - Hire Date = 21 กุมภาพันธ์ Gender = Female Pay Group = ES - รายละเอียดเต็มดูชีท Hiring Test Data | J40: EC > Hire & Onboard (New Hire) | K40: 1. Login ด้วย <HR_ADMIN_ACCOUNT> - ไปที่เมนู EC > New Hire (Manual Key-in) 2. กรอกข้อมูลในส่วน Identity - กรอก Salutation, First Name / Last Name (TH และ EN), Date of Birth, National ID / Tax ID และ Event Reason ตาม Test Data - กำหนด Hire Date = 21 กุมภาพันธ์ 3. กรอกข้อมูลในส่วน Position & Organization - กรอก Company, Business Unit, Division, Department, Position, Employee Group, Employee SubGroup และ Cost Centre ตาม Test Data 4. กรอกข้อมูลในส่วน Compensation Information - กำหนด Pay Group = ES - กรอก Pay Component, Frequency, Amount และ Currency ให้ครบถ้วน 5. กรอกข้อมูลในส่วน Payment Information - กรอก Bank, Account Number, Bank Country/Region, Currency และ Payment Method 6. กด Submit เพื่อสร้างพนักงานใหม่ 7. ตรวจสอบ Employee Profile ใน EC - ค้นหาพนักงานที่สร้างใหม่ด้วย Employee ID และเปิด Employee Profile - ตรวจสอบ Employee Status, Hire Date และ Pay Group ที่ระบบบันทึก | L40: EC - ระบบสร้างพนักงานสำเร็จและออก Employee ID - Employee Status = A (Active) - ระบบบันทึก Hire Date = 21 กุมภาพันธ์ - ระบบบันทึก Pay Group = ES | M40: Cancelled | Q40: ฐานคำนวณ 30 วันเดือน ก.พ. = PY
A41: 40 | B41: Hiring | C41: E2E-40 | D41: Hiring | Keyin - Success | New Hire | Hire Date = Month-End | Age < 60 | Male | TH | A - Permanent | Verify Payroll Lock & Proration | E41: HIR-EC-040 | F41: Positive | G41: Medium | H41: ตรวจสอบการจ้างพนักงานใหม่แบบ Key-in สำเร็จ กรณี Hire Date = วันสิ้นเดือน พร้อมตรวจสอบ Payroll Lock และ Proration | I41: - Entry Route = Keyin - Login = <HR_ADMIN_ACCOUNT> เงื่อนไขของเคสนี้ - Hire Date = วันสุดท้ายของเดือนปัจจุบัน - Date of Birth = Age < 60 - Gender = Male - Nationality = TH - Employee Group = A - Permanent ค่าที่ต้องคีย์ ชุดข้อมูลจากถัง SIT ตรวจสอบเมื่อ 28 ส.ค. 2026 ชุดข้อมูล TD-01 - Business Group = CRC - Business Unit = CDG (10000075) Policy Profile = CDS - Company = C001 - Position = 40106337 Job Code = MKB12.12 - Department = 30042174 Store/ Branch Code = T153_1733 SSO Location = T153 - Division = 20000079 Cost Center = C00132653 Work Location = 50000127 - Work Schedule = D05H0830 Holiday Calendar = 01 - Personnel Grade (PG) = 10 - Employee Group = A - Permanent Employee Sub Group = 10 - Employment Type = F สถานะ Position = ว่าง - ตาราง time_status_mapping กำหนด Time Status = 01 O.T. Flag = yes - สิทธิ์ลาพักผ่อนปีแรก = 6 เงื่อนไขเฉพาะของเคสนี้ - คีย์ Employee Group = A - Permanent Employee Sub Group = 10 ตามชุดข้อมูล - Hire Date = วันสุดท้ายของเดือนที่ทดสอบ - รายละเอียดเต็มดูชีท Hiring Test Data | J41: EC > Hire & Onboard (New Hire) | K41: 1. Login ด้วย <HR_ADMIN_ACCOUNT> - ไปที่เมนู EC > New Hire (Manual Key-in) 2. กรอกข้อมูลในส่วน Identity - กรอก Salutation, First Name / Last Name (TH และ EN), Date of Birth, National ID / Tax ID และ Event Reason ตาม Test Data - กำหนด Hire Date = วันสุดท้ายของเดือนปัจจุบัน 3. กรอกข้อมูลในส่วน Position & Organization - กรอก Company, Business Unit, Division, Department, Position, Employee Group, Employee SubGroup และ Cost Centre ตาม Test Data 4. กรอกข้อมูลในส่วน Compensation Information - กรอก Pay Group, Pay Component, Frequency, Amount และ Currency ให้ครบถ้วน 5. กรอกข้อมูลในส่วน Payment Information - กรอก Bank, Account Number, Bank Country/Region, Currency และ Payment Method 6. กด Submit เพื่อสร้างพนักงานใหม่ 7. ตรวจสอบ Employee Profile ใน EC - ค้นหาพนักงานที่สร้างใหม่ด้วย Employee ID และเปิด Employee Profile - ตรวจสอบ Hire Date และสถานะพนักงาน - ตรวจสอบวันที่เริ่มนับ Probation 8. ตรวจสอบ Probation - ตรวจสอบว่าระบบเริ่มนับ Probation จาก Hire Date = วันสุดท้ายของเดือน | L41: EC - ระบบสร้างพนักงานสำเร็จ - ระบบบันทึก Hire Date = วันสุดท้ายของเดือนตามที่ระบุ - ระบบไม่แสดงข้อความเตือนจากการกำหนด Hire Date เป็นวันสุดท้ายของเดือน - ระบบเริ่มนับ Probation ตั้งแต่ Hire Date | M41: Cancelled | Q41: คิดเงินตามสัดส่วนสิ้นเดือน = PY
A42: 41 | B42: Hiring | C42: E2E-41 | D42: Hiring | Keyin - Success | New Hire |Hire Date = Apr 13 | Age < 60 | Male | TH | A - Permanent | Holiday Calendar = 03 | Verify Songkran Leave | E42: HIR-EC-041 | F42: Positive | G42: High | H42: ตรวจสอบการจ้างพนักงานใหม่แบบ Key-in สำเร็จ กรณี Hire Date = 13 เมษายน และ Holiday Calendar = 03 พร้อมตรวจสอบสิทธิวันหยุดสงกรานต์ | I42: - Entry Route = Keyin - Login = <HR_ADMIN_ACCOUNT> เงื่อนไขของเคสนี้ - Hire Date = 13 เมษายน - Date of Birth = Age < 60 - Gender = Male - Nationality = TH - Employee Group = A - Permanent - ต้องยืนยันรหัส Holiday Calendar ที่หน้าจอให้เลือกก่อน เนื่องจากรหัสในหน้าจอกับรหัสในตารางแม่ยังไม่ตรงกัน ค่าที่ต้องคีย์ ชุดข้อมูลจากถัง SIT ตรวจสอบเมื่อ 28 ส.ค. 2026 ชุดข้อมูล TD-09 - Business Group = CRC - Business Unit = CFR (10000003) Policy Profile = CFR - Company = C004 - Position = 40004936 Job Code = STA10.41 - Department = 30002085 Store/ Branch Code = T173_1753 SSO Location = T173 - Division = 20001351 Cost Center = C00429530 Work Location = 50000034 - Work Schedule = D06H0800 Holiday Calendar = 03 - Personnel Grade (PG) = 11 - Employee Group = A - Permanent Employee Sub Group = 11 - Employment Type = F สถานะ Position = ว่าง - ตาราง time_status_mapping กำหนด Time Status = 01 O.T. Flag = yes - สิทธิ์ลาพักผ่อนปีแรก = 6 เงื่อนไขเฉพาะของเคสนี้ - คีย์ Employee Group = A - Permanent Employee Sub Group = 11 ตามชุดข้อมูล - ชุดนี้ผูก Holiday Calendar 03 อยู่แล้วตาม Position จริง จึงใช้ตรวจสิทธิ์ลาสงกรานต์ได้โดยไม่ต้องแก้ปฏิทิน - Hire Date = 13 เมษายน - รายละเอียดเต็มดูชีท Hiring Test Data | J42: EC > Hire & Onboard (New Hire) | K42: 1. Login ด้วย <HR_ADMIN_ACCOUNT> - ไปที่เมนู EC > New Hire (Manual Key-in) 2. กรอกข้อมูลในส่วน Identity - กรอก Salutation, First Name / Last Name (TH และ EN), Date of Birth, National ID / Tax ID และ Event Reason ตาม Test Data - กำหนด Hire Date = 13 เมษายน 3. กรอกข้อมูลในส่วน Position & Organization - กรอก Company, Business Unit, Division, Department, Position, Employee Group, Employee SubGroup และ Cost Centre ตาม Test Data - ตรวจสอบ Holiday Calendar = 03 ตามหน่วยงานที่เลือก 4. กรอกข้อมูลในส่วน Compensation Information - กรอก Pay Group, Pay Component, Frequency, Amount และ Currency ให้ครบถ้วน 5. กรอกข้อมูลในส่วน Payment Information - กรอก Bank, Account Number, Bank Country/Region, Currency และ Payment Method 6. กด Submit เพื่อสร้างพนักงานใหม่ 7. ตรวจสอบ Employee Profile ใน EC - ค้นหาพนักงานที่สร้างใหม่ด้วย Employee ID และเปิด Employee Profile - ตรวจสอบ Employee Status, Hire Date และ Holiday Calendar ที่ระบบบันทึก 8. ตรวจสอบผลของ Hire Date ที่ตรงกับวันหยุด - ตรวจสอบว่าระบบยอมให้ Hire Date = 13 เมษายนหรือไม่ - ตรวจสอบวันที่ระบบเริ่มนับเป็นวันทำงานวันแรก | L42: EC - ระบบสร้างพนักงานสำเร็จ - Employee Status = A (Active) - ระบบบันทึก Hire Date = 13 เมษายน - Holiday Calendar = 03 (Store Calendar) ตาม Department ที่เลือก - การที่ระบบยอมให้ Hire Date ตรงกับวันหยุดหรือไม่ และวันแรกที่นับเป็นวันทำงานคือวันใด = ? OQ-HIR-09 จุดที่ยังไม่มีคำตอบในเคสนี้ ให้รันจริงแล้วบันทึกค่าที่ระบบแสดงลงช่อง Actual Result Image และช่อง Note เพื่อใช้เป็นคำตอบ แล้วส่งให้ BA หรือ SA ยืนยัน หมายเลขคำถามที่ต้องเก็บคำตอบระหว่างรัน OQ-HIR-09 | M42: Not Start | Q42: ตัดจากเคส E2E-41 ไฟล์ HR_SIT_E2E_V.0.1 (28).xlsx ชีท E2E All module โมดูลที่เคสเต็มเกี่ยวข้อง EC / TM ยกไปรอบเชื่อมโมดูล ผลที่คาดหวังฝั่ง Notification / TM / BE ไม่อยู่ในขอบเขต / PY ไม่อยู่ในขอบเขต ยกไปรอบเชื่อมโมดูล ขั้นตอน ตรวจสอบสิทธิ์วันลาใน TM เคสนี้มีจุดที่ยังไม่มีคำตอบ 1 จุด ไม่ต้องรอคำตอบก่อนรัน ให้รันเก็บค่าที่ระบบแสดงจริงแล้วแจ้ง BA หรือ SA ยืนยันหลังรัน
A43: 42 | B43: Hiring | C43: E2E-42 | D43: Hiring | Keyin - Success | New Hire | Hire Date = Apr 14 | Age < 60 | Male | TH | A - Permanent | Holiday Calendar = 03 | Verify Songkran Leave Boundary | E43: HIR-EC-042 | F43: Positive | G43: High | H43: ตรวจสอบการจ้างพนักงานใหม่แบบ Key-in สำเร็จ กรณี Hire Date = 14 เมษายน และ Holiday Calendar = 03 พร้อมตรวจสอบ Boundary ของสิทธิวันหยุดสงกรานต์ | I43: - Entry Route = Keyin - Login = <HR_ADMIN_ACCOUNT> เงื่อนไขของเคสนี้ - Hire Date = 14 เมษายน - Date of Birth = Age < 60 - Gender = Male - Nationality = TH - Employee Group = A - Permanent - รันคู่กับ E2E-H15 เพื่อเปรียบเทียบและตรวจสอบขอบเขตวันที่ของสิทธิ์ 2703 ลาพิเศษ (สงกรานต์) ค่าที่ต้องคีย์ ชุดข้อมูลจากถัง SIT ตรวจสอบเมื่อ 28 ส.ค. 2026 ชุดข้อมูล TD-09 - Business Group = CRC - Business Unit = CFR (10000003) Policy Profile = CFR - Company = C004 - Position = 40004936 Job Code = STA10.41 - Department = 30002085 Store/ Branch Code = T173_1753 SSO Location = T173 - Division = 20001351 Cost Center = C00429530 Work Location = 50000034 - Work Schedule = D06H0800 Holiday Calendar = 03 - Personnel Grade (PG) = 11 - Employee Group = A - Permanent Employee Sub Group = 11 - Employment Type = F สถานะ Position = ว่าง - ตาราง time_status_mapping กำหนด Time Status = 01 O.T. Flag = yes - สิทธิ์ลาพักผ่อนปีแรก = 6 เงื่อนไขเฉพาะของเคสนี้ - คีย์ Employee Group = A - Permanent Employee Sub Group = 11 ตามชุดข้อมูล Holiday Calendar 03 - Hire Date = 14 เมษายน รันคู่กับ E2E-41 เพื่อตรวจขอบเขตวันที่ - รายละเอียดเต็มดูชีท Hiring Test Data | J43: EC > Hire & Onboard (New Hire) | K43: 1. Login ด้วย <HR_ADMIN_ACCOUNT> - ไปที่เมนู EC > New Hire (Manual Key-in) 2. กรอกข้อมูลในส่วน Identity - กรอก Salutation, First Name / Last Name (TH และ EN), Date of Birth, National ID / Tax ID และ Event Reason ตาม Test Data - กำหนด Hire Date = 14 เมษายน 3. กรอกข้อมูลในส่วน Position & Organization - กรอก Company, Business Unit, Division, Department, Position, Employee Group, Employee SubGroup และ Cost Centre ตาม Test Data - ตรวจสอบ Holiday Calendar = 03 4. กรอกข้อมูลในส่วน Compensation Information - กรอก Pay Group, Pay Component, Frequency, Amount และ Currency ให้ครบถ้วน 5. กรอกข้อมูลในส่วน Payment Information - กรอก Bank, Account Number, Bank Country/Region, Currency และ Payment Method 6. กด Submit เพื่อสร้างพนักงานใหม่ 7. ตรวจสอบ Employee Profile ใน EC - ค้นหาพนักงานที่สร้างใหม่ด้วย Employee ID และเปิด Employee Profile - ตรวจสอบ Employee Status, Hire Date และ Holiday Calendar ที่ระบบบันทึก 8. เปรียบเทียบผลกับ E2E-H15 - เปรียบเทียบสิทธิ์ 2703 ของ Hire Date = 14 เมษายน กับผลของ E2E-H15 - บันทึกผลเพื่อใช้ตรวจสอบว่าขอบเขตของสิทธิ์อยู่ที่วันที่ 14 หรือ 15 เมษายน | L43: EC - ระบบสร้างพนักงานสำเร็จ - Employee Status = A (Active) - ระบบบันทึก Hire Date = 14 เมษายน - Holiday Calendar = 03 (Store Calendar) | M43: Cancelled | Q43: วันหยุดสงกรานต์ 14 เม.ย. = TM
A44: 43 | B44: Hiring | C44: E2E-43 | D44: Hiring | Keyin - Success | New Hire | Hire Date = Apr 13 | Age < 60 | Male | TH | A - Permanent | Non-Branch Holiday Calendar | Verify No Songkran Leave | E44: HIR-EC-043 | F44: Positive | G44: Medium | H44: ตรวจสอบการจ้างพนักงานใหม่แบบ Key-in สำเร็จ กรณี Hire Date = 13 เมษายน และใช้ Non-Branch Holiday Calendar โดยต้องไม่ได้รับสิทธิวันหยุดสงกรานต์ | I44: - Entry Route = Keyin - Login = <HR_ADMIN_ACCOUNT> เงื่อนไขของเคสนี้ - Hire Date = 13 เมษายน - Date of Birth = Age < 60 - Gender = Male - Nationality = TH - Employee Group = A - Permanent - รันคู่กับ E2E-H15 เพื่อเปรียบเทียบผล ค่าที่ต้องคีย์ ชุดข้อมูลจากถัง SIT ตรวจสอบเมื่อ 28 ส.ค. 2026 ชุดข้อมูล TD-01 - Business Group = CRC - Business Unit = CDG (10000075) Policy Profile = CDS - Company = C001 - Position = 40106337 Job Code = MKB12.12 - Department = 30042174 Store/ Branch Code = T153_1733 SSO Location = T153 - Division = 20000079 Cost Center = C00132653 Work Location = 50000127 - Work Schedule = D05H0830 Holiday Calendar = 01 - Personnel Grade (PG) = 10 - Employee Group = A - Permanent Employee Sub Group = 10 - Employment Type = F สถานะ Position = ว่าง - ตาราง time_status_mapping กำหนด Time Status = 01 O.T. Flag = yes - สิทธิ์ลาพักผ่อนปีแรก = 6 เงื่อนไขเฉพาะของเคสนี้ - คีย์ Employee Group = A - Permanent Employee Sub Group = 10 ตามชุดข้อมูล - ชุดนี้ผูก Holiday Calendar 01 ซึ่งไม่ใช่ 03 และไม่ใช่ 04 จึงใช้เป็นเคสที่ต้องไม่ได้สิทธิ์ลาสงกรานต์ - Hire Date = 13 เมษายน รันคู่กับ E2E-41 เพื่อเทียบผล - รายละเอียดเต็มดูชีท Hiring Test Data | J44: EC > Hire & Onboard (New Hire) | K44: 1. Login ด้วย <HR_ADMIN_ACCOUNT> - ไปที่เมนู EC > New Hire (Manual Key-in) 2. กรอกข้อมูลในส่วน Identity - กรอก Salutation, First Name / Last Name (TH และ EN), Date of Birth, National ID / Tax ID และ Event Reason ตาม Test Data - กำหนด Hire Date = 13 เมษายน 3. กรอกข้อมูลในส่วน Position & Organization - กรอก Company, Business Unit, Division, Department, Position, Employee Group, Employee SubGroup และ Cost Centre ตาม Test Data - กำหนด Holiday Calendar เป็นรหัสอื่นที่ไม่ใช่ 03 และ 04 4. กรอกข้อมูลในส่วน Compensation Information - กรอก Pay Group, Pay Component, Frequency, Amount และ Currency ให้ครบถ้วน 5. กรอกข้อมูลในส่วน Payment Information - กรอก Bank, Account Number, Bank Country/Region, Currency และ Payment Method 6. กด Submit เพื่อสร้างพนักงานใหม่ 7. ตรวจสอบ Employee Profile ใน EC - ค้นหาพนักงานที่สร้างใหม่ด้วย Employee ID และเปิด Employee Profile - ตรวจสอบ Employee Status, Hire Date และ Holiday Calendar ที่ระบบบันทึก | L44: EC - ระบบสร้างพนักงานสำเร็จ - Employee Status = A (Active) - ระบบบันทึก Hire Date = 13 เมษายน - Holiday Calendar แสดง 01 (HO Calendar) ซึ่งไม่ใช่ปฏิทินกลุ่ม Branch | M44: Cancelled | Q44: ปฏิทิน 01 vs 03 มาจากกฎ derive เดียวกัน ซ้ำกับ 41
A45: 44 | B45: Hiring | C45: E2E-44 | D45: Hiring | Keyin - Success | New Hire | Hire Date = Today | Age < 60 | Male | TH | A - Permanent | Business Group = CPN | Verify Downstream Rules | E45: HIR-EC-044 | F45: Positive | G45: High | H45: ตรวจสอบการจ้างพนักงานใหม่แบบ Key-in สำเร็จ กรณี Business Group = CPN และตรวจสอบกฎที่ส่งผลต่อ Downstream System | I45: - Entry Route = Keyin - Login = <HR_ADMIN_ACCOUNT> เงื่อนไขของเคสนี้ - รันคู่กับ E2E-01 ซึ่งใช้ Business Group = CRC เพื่อเปรียบเทียบผล ค่าที่ต้องคีย์ ชุดข้อมูลจากถัง SIT ตรวจสอบเมื่อ 28 ส.ค. 2026 ชุดข้อมูล TD-35 - Business Group = CPN - Business Unit = CPN (10000009) Policy Profile = CPN - Company = C066 - Position = 40051012 Job Code = MKG10.21 - Department = 30015233 Branch = T583_1020 SSO Location = T583 - Division = 20001469 Cost Center = 001CMA1423 Work Location = 50000109 - Work Schedule = D05H0830 Holiday Calendar = 01 - Personnel Grade (PG) = 11 Employee Sub Group ที่ต้องคีย์ = 11 - ตารางกำหนด Time Status = 01 O.T. Flag = yes สิทธิ์ลาพักผ่อนปีแรก = 7 วัน เงื่อนไขเฉพาะของเคสนี้ - Personnel Grade (PG) = 11 ใช้แทน 10 ที่เคยระบุ เพราะ CPN ไม่มี Position ว่าง Personnel Grade (PG) 10 ดู CF-SIT-07 - ตารางกำหนด Time Status = 01 O.T. Flag = yes สิทธิ์ลาปีแรก = 7 วัน - รันคู่กับ E2E-01 ซึ่งเป็น CRC และได้สิทธิ์ลาปีแรก 6 วัน - รายละเอียดเต็มดูชีท Hiring Test Data หมายเหตุ - ดราฟต์เดิมระบุ Personnel Grade (PG) = 10 ใช้ 11 / 11 ตามชุดข้อมูลจริงในถัง SIT | J45: EC > Hire & Onboard (New Hire) | K45: 1. Login ด้วย <HR_ADMIN_ACCOUNT> - ไปที่เมนู EC > New Hire (Manual Key-in) 2. กรอกข้อมูลในส่วน Identity - กรอก Salutation, First Name / Last Name (TH และ EN), Date of Birth, National ID / Tax ID, Hire Date และ Event Reason ตาม Test Data 3. กรอกข้อมูลในส่วน Position & Organization - กำหนด Business Group = CPN - กำหนด Business Unit เป็นหน่วยธุรกิจที่อยู่ใต้ CPN - กรอก Company, Division, Department, Position, Employee Group, Employee SubGroup และ Cost Centre ตาม Test Data - กำหนด Personal Grade (PG) = 10 4. กรอกข้อมูลในส่วน Compensation Information - กรอก Pay Group, Pay Component, Frequency, Amount และ Currency ให้ครบถ้วน 5. กรอกข้อมูลในส่วน Payment Information - กรอก Bank, Account Number, Bank Country/Region, Currency และ Payment Method 6. กด Submit เพื่อสร้างพนักงานใหม่ 7. ตรวจสอบ Employee Profile ใน EC - ค้นหาพนักงานที่สร้างใหม่ด้วย Employee ID และเปิด Employee Profile - ตรวจสอบ Business Group / Business Unit ที่ระบบบันทึก - ตรวจสอบ Retirement Date ที่ระบบคำนวณ 8. ตรวจสอบนโยบายการนับสายและการหักเงิน - ตรวจสอบนโยบายที่ระบบกำหนดให้พนักงาน - บันทึกผลที่พบ 9. ตรวจสอบ Retirement Date - ตรวจสอบวันที่ระบบคำนวณให้สำหรับ Business Group = CPN 10. เปรียบเทียบผลกับ E2E-01 - บันทึกความแตกต่างที่พบ | L45: EC - ระบบสร้างพนักงานสำเร็จ - ระบบบันทึก Business Group = CPN และ Business Unit ตามที่ระบุ - Retirement Date = วันที่ 1 มกราคม ถัดจากวันที่พนักงานอายุครบ 60 ปี - Business Group = CRC และ CU ใช้ Retirement Date = วันที่ 1 มีนาคม ถัดจากวันที่พนักงานอายุครบ 60 ปี | M45: Not Start | Q45: ตัดจากเคส E2E-44 ไฟล์ HR_SIT_E2E_V.0.1 (28).xlsx ชีท E2E All module โมดูลที่เคสเต็มเกี่ยวข้อง EC / BE / TM / PY ยกไปรอบเชื่อมโมดูล ผลที่คาดหวังฝั่ง Notification / TM / BE / PY ยกไปรอบเชื่อมโมดูล ขั้นตอน ตรวจสอบโควตาลาพักร้อน
A46: 45 | B46: Hiring | C46: E2E-45 | D46: Hiring | Keyin - Success | New Hire | Hire Date = Today | Age < 60 | Female | TH | A - Permanent | Business Group = CU | Verify Leave & Time Rules | E46: HIR-EC-045 | F46: Positive | G46: Medium | H46: ตรวจสอบการจ้างพนักงานใหม่แบบ Key-in สำเร็จ กรณี Business Group = CU และตรวจสอบกฎการลาและเวลาทำงาน | I46: - Entry Route = Keyin - Login = <HR_ADMIN_ACCOUNT> เงื่อนไขของเคสนี้ - Hire Date = Today - Date of Birth = Age < 60 - Gender = Female - Nationality = TH - Employee Group = A - Permanent - รันคู่กับ E2E-01 (CRC) และ E2E-H18 (CPN) เพื่อเปรียบเทียบผล ค่าที่ต้องคีย์ ชุดข้อมูลจากถัง SIT ตรวจสอบเมื่อ 28 ส.ค. 2026 ชุดข้อมูล TD-19 - Business Group = CU - Business Unit = CU (10000013) Policy Profile = SU-CMC & SDO - Company = C013 - Position = 40035281 Job Code = MKB10.41 - Department = 30011330 Branch = T081_1648 SSO Location = T081 - Division = 20000021 Cost Center = C01301910 Work Location = 50000140 - Work Schedule = D05H0830 Holiday Calendar = 01 - Personnel Grade (PG) = 11 Employee Sub Group ที่ต้องคีย์ = 11 - ตารางกำหนด Time Status = 01 O.T. Flag = yes สิทธิ์ลาพักผ่อนปีแรก = 6 วัน เงื่อนไขเฉพาะของเคสนี้ - Personnel Grade (PG) = 11 ใช้แทน 10 ที่เคยระบุ เพราะ CU ไม่มี Position ว่าง Personnel Grade (PG) 10 ดู CF-SIT-07 - ตารางกำหนด Time Status = 01 O.T. Flag = yes สิทธิ์ลาปีแรก = 6 วัน - CU มีสอง Policy Profile แต่ตารางเวลาอ้าง CU ค่าเดียว ดู CF-SIT-21 - รายละเอียดเต็มดูชีท Hiring Test Data หมายเหตุ - ดราฟต์เดิมระบุ Personnel Grade (PG) = 10 ใช้ 11 / 11 ตามชุดข้อมูลจริงในถัง SIT | J46: EC > Hire & Onboard (New Hire) | K46: 1. Login ด้วย <HR_ADMIN_ACCOUNT> - ไปที่เมนู EC > New Hire (Manual Key-in) 2. กรอกข้อมูลในส่วน Identity - กรอก Salutation, First Name / Last Name (TH และ EN), Date of Birth, National ID / Tax ID, Hire Date และ Event Reason ตาม Test Data 3. กรอกข้อมูลในส่วน Position & Organization - กำหนด Business Group = CU - กรอก Company, Business Unit, Division, Department, Position, Employee Group, Employee SubGroup และ Cost Centre ตาม Test Data - กำหนด Personal Grade (PG) = 10 4. กรอกข้อมูลในส่วน Compensation Information - กรอก Pay Group, Pay Component, Frequency, Amount และ Currency ให้ครบถ้วน 5. กรอกข้อมูลในส่วน Payment Information - กรอก Bank, Account Number, Bank Country/Region, Currency และ Payment Method 6. กด Submit เพื่อสร้างพนักงานใหม่ 7. ตรวจสอบ Employee Profile ใน EC - ค้นหาพนักงานที่สร้างใหม่ด้วย Employee ID และเปิด Employee Profile - ตรวจสอบ Employee Status และ Business Group ที่ระบบบันทึก - ตรวจสอบ Retirement Date ที่ระบบคำนวณ 8. ตรวจสอบผลตาม Business Group - ตรวจสอบโควตาวันลาที่พนักงานได้รับ - ตรวจสอบนโยบายการลงเวลาที่ระบบกำหนดให้ - ตรวจสอบว่าข้อมูล Business Group = CU ถูกส่งไปยังระบบปลายทางเพื่อใช้แยกกฎสิทธิ์หรือไม่ 9. เปรียบเทียบผลระหว่าง Business Group - เปรียบเทียบผลของ CU กับ E2E-01 (CRC) และ E2E-H18 (CPN) - เปรียบเทียบโควตาวันลา นโยบายการลงเวลา และ Retirement Date - บันทึกความแตกต่างที่พบของทั้ง 3 Business Group | L46: EC - ระบบสร้างพนักงานสำเร็จ - Employee Status = A (Active) - Business Group ต้องแสดง CU ตามค่าที่เลือก ไม่ใช่ค่า Default | M46: Cancelled | Q46: Business Group CU แสดงค่า = ไม่มี logic EC ให้ตรวจ นอกจากค่าที่คีย์ถูกบันทึก
A47: 46 | B47: Hiring | C47: E2E-46 | D47: Hiring | Keyin | New Hire | Hire Date ≥ Jun 1, 2025 | Age < 60 | Male | TH | A - Permanent | Business Unit = CMG | Verify Missing First-Year Leave Rule | E47: HIR-EC-046 | F47: Positive | G47: High | H47: ตรวจสอบการจ้างพนักงานใหม่แบบ Key-in กรณี Business Unit = CMG และ Hire Date ≥ 1 มิถุนายน 2025 พร้อมตรวจสอบกรณีไม่พบกฎการลาในปีแรก | I47: - Entry Route = Keyin - Login = <HR_ADMIN_ACCOUNT> เงื่อนไขของเคสนี้ - Hire Date = วันที่ตั้งแต่ 1 มิถุนายน 2025 เป็นต้นไป - Date of Birth = Age < 60 - Gender = Male - Nationality = TH - Employee Group = A - Permanent - ต้องยืนยันกับ SA TM ก่อนว่าเมื่อระบบจับ Rule ไม่เจอ ระบบต้องตอบอย่างไร ค่าที่ต้องคีย์ ชุดข้อมูลจากถัง SIT ตรวจสอบเมื่อ 28 ส.ค. 2026 ชุดข้อมูล TD-40 - Business Group = CRC - Business Unit = CMG (10000010) Policy Profile = CMG - Company = C059 - Position = 40107598 Job Code = STC11.40 - Department = 30015116 Branch = T557_1016 SSO Location = T557 - Division = 20000277 Cost Center = C059DUMMY Work Location = 50000132 - Work Schedule = D06H0800 Holiday Calendar = 03 - Personnel Grade (PG) = 10 Employee Sub Group ที่ต้องคีย์ = 10 - ตารางกำหนด Time Status = 01 O.T. Flag = yes สิทธิ์ลาพักผ่อนปีแรก = 6 วัน ชุดข้อมูล TD-41 - Position = 40184075 Job Code = STC12.12 - Department = 30015096 Branch = T557_1019 SSO Location = T557 - Division = 20000163 Cost Center = C059DUMMY Work Location = 50000132 - Work Schedule = D06H0800 Holiday Calendar = 01 - Personnel Grade (PG) = 10 Employee Sub Group ที่ต้องคีย์ = 10 เงื่อนไขเฉพาะของเคสนี้ - Hire Date ตั้งแต่ 1 มิถุนายน 2025 เป็นต้นไป ตารางให้สิทธิ์ลาปีแรก 6 วัน - Hire Date ก่อน 1 มิถุนายน 2025 ตารางให้ 7 วัน รันสองรอบเพื่อเทียบ - รายละเอียดเต็มดูชีท Hiring Test Data | J47: EC > Hire & Onboard (New Hire) | K47: 1. Login ด้วย <HR_ADMIN_ACCOUNT> - ไปที่เมนู EC > New Hire (Manual Key-in) 2. กรอกข้อมูลในส่วน Identity - กรอก Salutation, First Name / Last Name (TH และ EN), Date of Birth, National ID / Tax ID และ Event Reason ตาม Test Data - กำหนด Hire Date เป็นวันที่ตั้งแต่ 1 มิถุนายน 2025 เป็นต้นไป 3. กรอกข้อมูลในส่วน Position & Organization - กำหนด Business Group = CRC - กำหนด Business Unit = CMG - กรอก Company, Division, Department, Position, Employee Group, Employee SubGroup และ Cost Centre ตาม Test Data - กำหนด Personal Grade (PG) = 10 4. กรอกข้อมูลในส่วน Compensation Information - กรอก Pay Group, Pay Component, Frequency, Amount และ Currency ให้ครบถ้วน 5. กรอกข้อมูลในส่วน Payment Information - กรอก Bank, Account Number, Bank Country/Region, Currency และ Payment Method 6. กด Submit เพื่อสร้างพนักงานใหม่ 7. ตรวจสอบ Employee Profile ใน EC - ค้นหาพนักงานที่สร้างใหม่ด้วย Employee ID และเปิด Employee Profile - ตรวจสอบ Employee Status, Business Group, Business Unit และ Company ที่ระบบบันทึก 8. ตรวจสอบ Rule ที่ใช้คำนวณสิทธิ์ - ตรวจสอบว่าระบบมีการบันทึก Rule Code / Rule Version ที่ใช้ตัดสินโควตาหรือไม่ - บันทึกค่าที่พบ 9. ตรวจสอบกรณีระบบไม่พบ Rule - ตรวจสอบว่าระบบแสดง Error, กำหนดโควตาเป็น 0 หรือใช้กฎกลาง - บันทึก Actual Behavior ที่พบ | L47: EC - ระบบสร้างพนักงานสำเร็จ - Employee Status = A (Active) - Business Unit แสดงรหัสของ CMG - Business Group แสดงค่าที่ผูกกับ Business Unit นั้น - Company แสดงรหัส Company ที่อยู่ในรายการ Company ของ Business Unit นั้น | M47: Cancelled | Q47: วันลาปีแรก CMG = TM
